Workbook

Sheet Companies_Results
A1: Company Details | B1: Company Details | T1: Company Details | U1: Company Details | V1: Company Details | W1: Size Metrics | X1: Financials | Y1: Company Details | Z1: Company Details | AA1: Financials | AB1: Company Details | AC1: Industry | AD1: Industry | AE1: Industry | AF1: Industry
A2: Company Details | B2: Company Details | T2: Company Details | U2: Company Location | V2: Company Details | W2: Size Metrics | X2: Income Statement | Y2: Company Location | Z2: Company Location | AA2: Balance Sheet | AB2: Company Details | AC2: Industry Company Details | AD2: Industry Company Details | AE2: Industry Company Details | AF2: Industry Company Details
AC3: Primary RBICS | AD3: Primary RBICS | AE3: Primary RBICS | AF3: Primary RBICS
A4: Identifier | B4: Name | C4: Propose to Include? | D4: Outreach | E4: Identified Contact | F4: Status | G4: Connect4 Data | H4: IBISworld Data | I4: MarketLine Data | J4: ANZREU Purchases? | K4: Reported Emissions | L4: Project Classification | M4: Year | N4: Reported - Scope 1 | O4: Reported - Scope 2 | P4: CER 2023-24 Scope 1 | Q4: CER 2023-24 Scope 2 | R4: EBITDA (MM) (AUD) | S4: Net Income (MM) (AUD) | T4: Company Type Main | U4: Company Country | V4: Year Founded | W4: Number of Employees | X4: Revenue (MM) (AUD) | Y4: Company Region | Z4: Company State | AA4: Total Assets (MM) (AUD) | AB4: Business Description | AC4: Primary FactSet RBICS Industry Group | AD4: Primary FactSet RBICS Sub Sector | AE4: Primary FactSet RBICS Sector | AF4: Primary FactSet RBICS Industry | AH4: Extracted Scope 1 (kgCO2e) | AI4: Scope 1 Confidence | AJ4: Scope 1 Context | AK4: Extracted Scope 2 (kgCO2e) | AL4: Scope 2 Confidence | AM4: Scope 2 Context | AN4: Extracted Scope 3 (kgCO2e) | AO4: Scope 3 Confidence | AP4: Scope 3 Context | AQ4: Net Zero Mentions | AR4: Profitability Ratio | AS4: Reputational Concern Ratio
B5: Nestle | D5: AC | F5: Agreed to interview. | R5: =IFERROR(_xlfn.XLOOKUP($A5,Profitability!$A$5:$A$342,Profitability!$Q$5:$Q$342),"na") | S5: =IFERROR(_xlfn.XLOOKUP($A5,Profitability!$A$5:$A$342,Profitability!$R$5:$R$342),"na")
A6: WDS-AU | B6: Woodside Energy Group Ltd. | D6: KH | E6: Harold Yap | F6: Agreed to questionnaire. | P6: 8421985 | Q6: 5330 | R6: =IFERROR(_xlfn.XLOOKUP($A6,Profitability!$A$5:$A$342,Profitability!$Q$5:$Q$342),"na") | S6: =IFERROR(_xlfn.XLOOKUP($A6,Profitability!$A$5:$A$342,Profitability!$R$5:$R$342),"na") | T6: Public | U6: Australia | V6: 1971 | W6: 4718 | X6: 21202.274 | Y6: Pacific | Z6: Western Australia (WA) | AA6: 98948.555 | AB6: Woodside Energy Group Ltd. engages in the exploration, evaluation, development, and production of hydrocarbon and oil and gas properties. It operates through the following segments: North West Shelf, Pluto, Australia Oil, Wheatstone, Development, and Others. The North West Shelf segment produces liquefied natural gas, pipeline natural gas, condensate, liquefied petroleum gas and crude oil from the North West Shelf ventures. The Pluto segment develops liquefied natural gas in assigned permit areas. The Australia Oil segment is involved in the exploration, evaluation, development, production and sale of crude oil in assigned permit areas. The Wheatstone segment is involved in the exploration, evaluation, and development of liquefied natural gas, pipeline natural gas, and condensate. The Development segment includes the exploration of gas resources in Scarborough, Sangomar, and other project areas. The Other segment is composed of the activities undertaken by exploration, international and Sunrise Business Units. The company was founded on July 26, 1954 and is headquartered in Perth, Australia. | AC6: Other Fossil Fuel Exploration and Production | AD6: Fossil Fuel Exploration and Production | AE6: Upstream Energy | AF6: Asia/Pacific Fossil Fuel Exploration/Production | AH6: 5437000 | AI6: 0.9 | AJ6: === Table 4 (page 5) === HIGHLIGHTS,CONFIDENCE IN LNG,SCOPE 1 AND 2,NEW ENERGY | AK6: 6320000 | AL6: 0.9 | AM6: ,"compared to historical and/or current conventions or analogues, for example relating to an otherwise similar resource, process,",, ,,Starting base,Woodside uses a starting base of 6.32 Mt CO2-e which is representative of the gross annual average equity Scope 1 and 2 ,"production facility, product or service, or activity. When applied to Woodside's strategy, please see the definition of lower-carbon",,greenhouse gas emissions over 2016-2020 and which may be adjusted (up or down) for potential equity changes in producing | AN6: 3000 | AO6: 0.9 | AP6: ,methane emissions benchmarks., • This is reinforced by firm demand side commitments to,,Scope 3 targets.18 "offtake, with over 15 Mt of LNG contracted to Asian buyers",• We are pursuing emissions reduction opportunities and, | AQ6: 8 | AR6: 0.255488 | AS6: 0.000377
A7: BHP-AU | B7: BHP Group Ltd. | D7: KH | E7: Tom McKeon | F7: Invitation sent | M7: 2025 | N7: =7.4*10^6 | O7: =1.3*10^6 | P7: 3698759 | Q7: 1314290 | R7: =IFERROR(_xlfn.XLOOKUP($A7,Profitability!$A$5:$A$342,Profitability!$Q$5:$Q$342),"na") | S7: =IFERROR(_xlfn.XLOOKUP($A7,Profitability!$A$5:$A$342,Profitability!$R$5:$R$342),"na") | T7: Public | U7: Australia | V7: 1885 | W7: - | X7: 79153.099 | Y7: Pacific | Z7: Victoria (VIC) | AA7: 166002.9 | AB7: BHP Group Ltd. engages in the exploration, development, production and processing of iron ore, metallurgical coal, and copper. It operates through the following segments: Copper, Iron Ore, and Coal. The Copper segment refers to the mining of copper, silver, lead, zinc, molybdenum, uranium, and gold. The Iron Ore segment involves in the mining of iron ore. The Coal segment focuses on metallurgical coal and energy coal. The company was founded on August 13, 1885 and is headquartered in Melbourne, Australia. | AC7: Base Metal Mining | AD7: Metal Ore Mining | AE7: Mining and Mineral Products | AF7: Other Base Metal Ore Mining | AH7: 7400000 | AI7: 1 | AJ7: ,,FY2025,FY2024,FY2023 Total,Scope 1 emissions,7.4,8.1,8.0 operations,,,, | AK7: 1300000 | AL7: 1 | AM7: line with its strategy and risk management process,,,, "b) Disclose Scope 1, Scope 2, and, if appropriate,",Pages 48 to 53,–,–,– "Scope 3 GHG emissions, and the related risks",,,, | AN7: 378200000 | AO7: 1 | AP7: 3.7" Total Scope 3 emissions,"378.2 377.7 | AQ7: 98 | AR7: 0.175939 | AS7: 0.001238
A8: MIN-AU | B8: Mineral Resources Ltd. | D8: KH | E8: Laurren Duncan | F8: Invitation sent | P8: 704979 | Q8: 11055 | R8: =IFERROR(_xlfn.XLOOKUP($A8,Profitability!$A$5:$A$342,Profitability!$Q$5:$Q$342),"na") | S8: =IFERROR(_xlfn.XLOOKUP($A8,Profitability!$A$5:$A$342,Profitability!$R$5:$R$342),"na") | T8: Public | U8: Australia | V8: 2006 | W8: 8456 | X8: 4472 | Y8: Pacific | Z8: Western Australia (WA) | AA8: 11927 | AB8: Mineral Resources Ltd. engages in mining and processing of mineral properties. The firm operates through the following segments: Mining Services, Iron Ore, Energy, Lithium, Other Commodities, and Central. It offers contract crushing, infrastructure, and recovery of base metals concentrate. The company was founded by Christopher J. Ellison on February 27, 2006, and is headquartered in Perth, Australia. | AC8: Base Metal Mining | AD8: Metal Ore Mining | AE8: Mining and Mineral Products | AF8: Other Base Metal Ore Mining | AH8: 731084 | AI8: 1 | AJ8: Total Scope 1 GHG emissions (tCO2-e),"731,084" | AK8: 150947 | AL8: 1 | AM8: High Impact Environmental Incidents (Level 4 and, ,0 above), | AQ8: 23 | AR8: -0.202147 | AS8: 0.005143
A9: LTR-AU | B9: Liontown Resources Ltd. | D9: KH | E9: Secondary only. Requested. | F9: Invitation sent | R9: =IFERROR(_xlfn.XLOOKUP($A9,Profitability!$A$5:$A$342,Profitability!$Q$5:$Q$342),"na") | S9: =IFERROR(_xlfn.XLOOKUP($A9,Profitability!$A$5:$A$342,Profitability!$R$5:$R$342),"na") | T9: Public | U9: Australia | V9: 2006 | W9: - | X9: 0 | Y9: Pacific | Z9: Western Australia (WA) | AA9: 1384.924 | AB9: Liontown Resources Ltd. engages in the exploration and evaluation of minerals. Its projects include Kathleen Valley, Buldania, Moora Gold-PGE-Ni-Cu, and Toolebuc. The company was founded on February 2, 2006 and is headquartered in West Perth, Australia. | AC9: Base Metal Mining | AD9: Metal Ore Mining | AE9: Mining and Mineral Products | AF9: Lithium Ore Mining | AH9: 35822 | AI9: 0.9 | AJ9: Scope 1,tCO2-e,"35,822.02","41,605.88" | AK9: 9276 | AL9: 0.9 | AM9: Scope 2,tCO2-e,"9,217.31","1,891.67" | AN9: 0 | AQ9: 0
A10: WHC-AU | B10: Whitehaven Coal Ltd. | D10: KH | E10: Secondary only. Requested. | F10: Invitation sent | P10: 1228004 | Q10: 137673 | R10: =IFERROR(_xlfn.XLOOKUP($A10,Profitability!$A$5:$A$342,Profitability!$Q$5:$Q$342),"na") | S10: =IFERROR(_xlfn.XLOOKUP($A10,Profitability!$A$5:$A$342,Profitability!$R$5:$R$342),"na") | T10: Public | U10: Australia | V10: 2007 | W10: - | X10: 5832 | Y10: Pacific | Z10: New South Wales (NSW) | AA10: 12227 | AB10: Whitehaven Coal Ltd. engages in the development and operation of coal mines. The firm operates through the following segments: Open Cut Operations and Underground Operations. Its projects include Canyon, Maules Creek, Narrabri North, Rocglen, Sunnyside, Tarrawonga, Vickery, Werris Creek and Other Projects. The company was founded by Keith Ross in 1999 and is headquartered in Sydney, Australia. | AC10: Asia/Pacific International Coal Mining | AD10: Coal and Uranium Mining | AE10: Upstream Energy | AF10: Asia/Pacific International Coal Mining | AH10: 1958000 | AI10: 1 | AJ10: === Table 8 (page 32) === and Daunia mines. Scope 1 emissions,offsetting Scope 2 emissions on a whole-,,,,,, ,,,,,"1,958",, | AK10: 271000 | AL10: 1 | AM10: ,,,for June Qtr,,51% ,Our Scope 2 emissions (location based),,271,, ,"totalled 271 kt CO2-e, with the increase",,,, | AQ10: 8 | AR10: 0.111283 | AS10: 0.001372
A11: WES-AU | B11: Wesfarmers Ltd. | D11: KH | E11: Kylie Ashenbrenner | F11: Invitation sent | P11: 826977 | Q11: 485184 | R11: =IFERROR(_xlfn.XLOOKUP($A11,Profitability!$A$5:$A$342,Profitability!$Q$5:$Q$342),"na") | S11: =IFERROR(_xlfn.XLOOKUP($A11,Profitability!$A$5:$A$342,Profitability!$R$5:$R$342),"na") | T11: Public | U11: Australia | V11: 1981 | W11: 118000 | X11: 45576 | Y11: Pacific | Z11: Western Australia (WA) | AA11: 30269.001 | AB11: Wesfarmers Ltd. engages in the provision of fresh food, groceries, general merchandise, liquor, fuel, and financial services. It operates through the following segments: Bunnings; Kmart Group; Chemicals, Energy, and Fertilisers (WesCEF); Officeworks; Industrial and Safety; Health; Catch; and Other. The Bunnings segment consists of retailers of building materials and home and garden improvement products and servicing households and commercial customers including builders, trades, and businesses. The Kmart Group segment comprises of Kmart and Target which are retailers of apparel and general merchandise, including toys, leisure, entertainment, home, and consumable; and Catch which is an online retailer offering branded products on a first-party basis and a third-party online marketplace. The WesCEF segment refers to manufacturer and marketer of chemicals for industry, mining, mineral processing, broadacre and horticultural fertilisers, marketer and distributor of LPG and LNG; and manufacturer of wood-plastic composite decking and screening products. The Officeworks segment covers the retail and supply of office products and solutions for households, small-to-medium sized businesses, and the education sector. The Industrial and Safety segment supplies and distributes maintenance, repair, and operating products; manufactures and markets industrial gases and equipment; supplies, manufactures, and distributes workwear clothing in Australia and internationally. The Health segment wholesales and retails pharmaceutical, health, wellbeing, and beauty products. The Catch segment operates as an online retailer offering branded products on first-party basis and a third-party online marketplace. The Other segment includes food and stables retailing; forest products; property; investment banking; OneDigital, and Corporate. The company was founded in 1914 and is headquartered in Perth, Australia. | AC11: Mixed Home Improvement and Furnishings Stores | AD11: Home Improvement Retail | AE11: Consumer Retail | AF11: Mixed Home Improvement and Furnishings Stores | AH11: 789700 | AI11: 1 | AJ11: ,and others in the sectors in which, focus on reducing operational Scope 1,,financial disclosure requirements apply ,they operate., | AK11: 236900 | AL11: 1 | AM11: ,they operate., and Scope 2 greenhouse gas emissions,,to the Group from 1 July 2025 for financial (operational emissions). All divisions have,"This year, we established cross-functional",year 2026 reporting. As the ASRS S2 | AN11: 30500000 | AO11: 1 | AP11: and value chains.,, The Group’s Scope 31 emissions arise from,The Group’s Scope 3 emissions are,Category 4 — Upstream transportation "a wide range of activities across suppliers,",concentrated in four categories and those,and distribution includes emissions that | AQ11: 24 | AR11: 0.0642 | AS11: 0.000527
A12: QAN-AU | B12: Qantas Airways Ltd. | D12: KH | E12: Darren Wee | F12: Invitation sent | P12: 4528002 | Q12: 59740 | R12: =IFERROR(_xlfn.XLOOKUP($A12,Profitability!$A$5:$A$342,Profitability!$Q$5:$Q$342),"na") | S12: =IFERROR(_xlfn.XLOOKUP($A12,Profitability!$A$5:$A$342,Profitability!$R$5:$R$342),"na") | T12: Public | U12: Australia | V12: 1950 | W12: 25000 | X12: 23409 | Y12: Pacific | Z12: New South Wales (NSW) | AA12: 23356.001 | AB12: Qantas Airways Ltd. engages in international and domestic air transportation services. It operates through the following segments: Qantas Domestic, Qantas International, Jetstar Group, Qantas Loyalty, and Corporate. The Qantas Domestic segment is involved in the carrier in the Australian domestic market measured by capacity. The Qantas International segment refers to the carrier into and out of Australia, also targeting business and leisure customers who value the full-service experience. The Jetstar Group segment focuses on operations in Australia, delivering low fares and a differentiated product offering to the price-sensitive market. The Qantas Loyalty segment consists of consumer and SME coalition loyalty programs. The Corporate segment refers to centralized management and governance of the Qantas Group. The company was founded on November 16, 1920 and is headquartered in Mascot, Australia. | AC12: Air Passenger Transportation | AD12: Passenger Transportation | AE12: Industrial Services | AF12: Asia/Pacific Air Passenger Service Providers | AH12: 12139425 | AJ12: FY25 Scope 1 emissions (tCO₂e). | AK12: 58106 | AM12: FY25 Global Scope 2 GHG emissions (tCO₂e) (location-based method). | AN12: 7305845 | AP12: FY25 Scope 3 emissions (tCO₂e). | AQ12: 30 | AR12: 0.068563 | AS12: 0.001282
A13: MGR-AU | B13: Mirvac Group | D13: KH | E13: Secondary only. Requested. | F13: Invitation sent | R13: =IFERROR(_xlfn.XLOOKUP($A13,Profitability!$A$5:$A$342,Profitability!$Q$5:$Q$342),"na") | S13: =IFERROR(_xlfn.XLOOKUP($A13,Profitability!$A$5:$A$342,Profitability!$R$5:$R$342),"na") | T13: Public | U13: Australia | V13: 1972 | W13: 1651 | X13: 2466 | Y13: Pacific | Z13: New South Wales (NSW) | AA13: 15290 | AB13: Mirvac Group engages in real estate investment, development, third party capital management, and property asset management. It operates through the following segments: Investment, Funds, and Development. The Investment segment focuses on directly owned assets, co-investment stakes in funds, and investments in joint ventures and associates alongside capital partners. The Funds segment includes both funds management and asset management operations. The Development segment deals with commercial and mixed-use, build to rent, and residential projects. The company was founded by Henry Pollack and Robert Hamilton in 1972 and is headquartered in Sydney, Australia. | AC13: Equity REITs | AD13: Real Estate Investment Trusts (REITs) | AE13: Real Estate | AF13: Equity REITs | AH13: 6618 | AI13: 1 | AJ13: Total Scope 1,"6,618","9,632","10,711","9,371", | AK13: 73110 | AL13: 1 | AM13: Total Scope 2,"73,110",—,—,—, | AN13: 0 | AQ13: 0 | AR13: 0.027575 | AS13: 0
A14: ILU-AU | B14: Iluka Resources Ltd. | D14: KH | E14: Sarah Hodgson | F14: Invitation sent | R14: =IFERROR(_xlfn.XLOOKUP($A14,Profitability!$A$5:$A$342,Profitability!$Q$5:$Q$342),"na") | S14: =IFERROR(_xlfn.XLOOKUP($A14,Profitability!$A$5:$A$342,Profitability!$R$5:$R$342),"na") | T14: Public | U14: Australia | V14: 1954 | W14: 971 | X14: 1170.3 | Y14: Pacific | Z14: Western Australia (WA) | AA14: 3925.1999 | AB14: Iluka Resources Ltd. engages in the exploration, development, mining, processing, marketing, and rehabilitation of mineral sands products. It operates through the following segments: Jacinth-Ambrosia/Mid West (JA/MW), Cataby/South West (C/SW), Rare Earths (RE), and United States/Murray Basin (US/MB). The JA/MW segment deals with mining operations at Jacinth-Ambrosia located in South Australia, and associated processing operations at the Narngulu mineral separation plant in mid-west Western Australia. The C/SW segment represents mining activities at Cataby and processing of ilmenite at Synthetic Rutile Kilns 1 and 2, located in Western Australia. The RE segment refers to the Eneabba Rare Earths Refinery, which is currently being constructed in Western Australia and associated feasibility studies alongside Phase 1 and 2 of the Eneabba development, and the Group's investment in Northern Minerals Limited. The US/MB segment focuses on rehabilitation obligations in Florida and Virginia, and certain idle assets located in Australia. The company was founded on July 24, 1954 and is headquartered in Perth, Australia. | AC14: Base Metal Mining | AD14: Metal Ore Mining | AE14: Mining and Mineral Products | AF14: Non-Ferrous Metal Ore Mining | AH14: 392000 | AJ14: 2024 Scope 1 emissions (392 ktCO2e). | AK14: 71000 | AM14: 2024 Scope 2 emissions (71 ktCO2e). | AN14: 0 | AP14: Iluka is currently examining its scope 3 emissions and intends to disclose this information in future reports. | AQ14: 1 | AR14: 0.197642 | AS14: 0.000854
A15: RHC-AU | B15: Ramsay Health Care Ltd. | D15: KH | E15: Siobhan Leach | F15: Invitation sent | P15: 16136 | Q15: 131592 | R15: =IFERROR(_xlfn.XLOOKUP($A15,Profitability!$A$5:$A$342,Profitability!$Q$5:$Q$342),"na") | S15: =IFERROR(_xlfn.XLOOKUP($A15,Profitability!$A$5:$A$342,Profitability!$R$5:$R$342),"na") | T15: Public | U15: Australia | V15: 1975 | W15: 90000 | X15: 17791.6 | Y15: Pacific | Z15: New South Wales (NSW) | AA15: 22959.801 | AB15: Ramsay Health Care Ltd. engages in the healthcare services and the operation of hospitals and day surgery facilities. It operates through the following geographical segments : Asia Pacific, UK, France and Nordics. The company was founded by Paul Joseph Ramsay in 1964 and is headquartered in Sydney, Australia. | AC15: Acute Care and Institutional Patient Care | AD15: Patient Care | AE15: Healthcare Services | AF15: General and Acute Hospitals | AH15: 88711 | AJ15: FY25 Group Scope 1 emissions (tCO2-e) derived from summing Gas and fuel (59,949), Anaesthetic gases (26,244), and Refrigerants (2,518). | AK15: 129225 | AM15: FY25 Group Scope 2 emissions (tCO2-e) (Market-based Electricity). | AN15: 0 | AP15: No specific total Scope 3 quantification found in the provided tables, although Scope 3 is included in the net zero target scope. | AQ15: 20 | AR15: 0.001349 | AS15: 0.001124
A16: MND-AU | B16: Monadelphous Group Ltd. | D16: KH | E16: Rebecca Voyer | F16: Invitation sent | R16: =IFERROR(_xlfn.XLOOKUP($A16,Profitability!$A$5:$A$342,Profitability!$Q$5:$Q$342),"na") | S16: =IFERROR(_xlfn.XLOOKUP($A16,Profitability!$A$5:$A$342,Profitability!$R$5:$R$342),"na") | T16: Public | U16: Australia | V16: 1981 | W16: 7375 | X16: 2153.156 | Y16: Pacific | Z16: Western Australia (WA) | AA16: 1005.23 | AB16: Monadelphous Group Ltd. provides construction, maintenance and industrial services to the resources, energy and infrastructure sectors. The firm's divisions include Engineering Construction; and Maintenance and Industrial Services. The Engineering Construction division provides large-scale multidisciplinary project management and construction services. The Maintenance and Industrial Services division specializes in the planning, management and execution of mechanical and electrical maintenance services, shutdowns, sustaining capital works, fixed plant maintenance services, access solutions, specialist coatings and rail maintenance services. . It operates through the following geographical segments: Australia, Chile, Papua New Guinea, Mongolia, and Other overseas locations. The company was founded in 1972 and is headquartered in Perth, Australia. | AC16: Specialty Contracting Services | AD16: Facilities and Construction Services | AE16: Industrial Services | AF16: Industrial Specialty Engineering Contractors | AH16: 6608 | AI16: 0.9 | AJ16: which the Company will reference,, ,"year ended 30 June 2025 was 6,608", progress of its Net Zero by 2050 and,, | AK16: 7599000 | AL16: 0.9 | AM16: figure is 7,599 tCO2-e. | AQ16: 22 | AR16: 0.038883 | AS16: 0.010218
A17: BSL-AU | B17: BlueScope Steel Ltd. | D17: KH | E17: Megan Wheeldon | F17: Invitation sent | P17: 6131585 | Q17: 806487 | R17: =IFERROR(_xlfn.XLOOKUP($A17,Profitability!$A$5:$A$342,Profitability!$Q$5:$Q$342),"na") | S17: =IFERROR(_xlfn.XLOOKUP($A17,Profitability!$A$5:$A$342,Profitability!$R$5:$R$342),"na") | T17: Public | U17: Australia | V17: 1921 | W17: 16500 | X17: 16294.4 | Y17: Pacific | Z17: Victoria (VIC) | AA17: 15781 | AB17: BlueScope Steel Ltd. engages in the manufacture of steel products. It operates through the following segments: Australian Steel Products, North Star BlueScope Steel, Buildings and Coated Products North America, Coated Products Asia, and New Zealand and Pacific Islands. The Australian Steel Products segment produces and markets coated and painted flat steel products. The North Star BlueScope Steel segment is a single site electric arc furnace producer of hot rolled coil. The Buildings and Coated Products North America segment includes engineered building solutions and servicing the low-rise non-residential construction needs of customers. The Coated Products Asia segment offers metal coated and painted steel building products. The New Zealand and Pacific Islands segment consists of New Zealand Steel, Pacific Steel, and BlueScope Pacific Islands business areas. The company was founded on July 15, 2002 and is headquartered in Melbourne, Australia. | AC17: Primary Metals Products | AD17: Metal Products | AE17: Mining and Mineral Products | AF17: Diversified Primary Metals Processors | AH17: 8500000 | AJ17: FY25 Scope 1 GHG emissions (8,500 ktCO2-e) | AK17: 1700000 | AM17: FY25 Scope 2 GHG emissions (1,700 ktCO2-e) | AN17: 12770000 | AP17: FY25 Scope 3 GHG emissions (12,770 ktCO2-e) | AQ17: 14 | AR17: 0.004554 | AS17: 0.000859
A18: FMG-AU | B18: Fortescue Ltd. | D18: KH | E18: Bronwyn Grieve | F18: Invitation sent | P18: 2002222 | Q18: 513963 | R18: =IFERROR(_xlfn.XLOOKUP($A18,Profitability!$A$5:$A$342,Profitability!$Q$5:$Q$342),"na") | S18: =IFERROR(_xlfn.XLOOKUP($A18,Profitability!$A$5:$A$342,Profitability!$R$5:$R$342),"na") | T18: Public | U18: Australia | V18: 1983 | W18: - | X18: 23996.69 | Y18: Pacific | Z18: Western Australia (WA) | AA18: 47844.664 | AB18: Fortescue Ltd. engages in the development of iron ore deposits. It operates through the Metals and Energy segments. The Metals segment includes exploration, development, production, processing, sale, and transportation of iron ore, and the exploration for other minerals. The Energy segment is involved in the development of green electricity, green hydrogen, and green ammonia projects. The company was founded by John Andrew Henry Forrest in April 2003 and is headquartered in East Perth, Australia. | AC18: Base Metal Mining | AD18: Metal Ore Mining | AE18: Mining and Mineral Products | AF18: Other Base Metal Ore Mining | AH18: 2640000 | AI18: 1 | AJ18: Total Group Scope 1,2.64,2.36,12.0% | AK18: 520000 | AL18: 1 | AM18: Australian terrestrial iron ore operations Scope 2 emissions (location-based),0.37,0.36,0.35 | AN18: 275880000 | AO18: 1 | AP18: Total Group Scope 3 emissions,275.88,269.31,2.4% | AQ18: 8 | AR18: 0.217039 | AS18: 0.000333
A19: WOR-AU | B19: Worley Ltd. | D19: KH | E19: Secondary only. Requested. | F19: Invitation sent | R19: =IFERROR(_xlfn.XLOOKUP($A19,Profitability!$A$5:$A$342,Profitability!$Q$5:$Q$342),"na") | S19: =IFERROR(_xlfn.XLOOKUP($A19,Profitability!$A$5:$A$342,Profitability!$R$5:$R$342),"na") | T19: Public | U19: Australia | V19: 2001 | W19: 45500 | X19: 11222 | Y19: Pacific | Z19: New South Wales (NSW) | AA19: 11019 | AB19: Worley Ltd. engages in the provision of services to the resources, energy, and industrial sectors. It operates through the following segments: Energy and Chemical Services, Mining, Minerals and Metal Services, Major Projects and Integrated Solutions and Advisian. The Energy and Chemical Services segment includes engineering, procurement, project management, program management, and operations. The Mining, Minerals and Metals Services segment line of business combines extensive local experience and innovative, integrated solutions with technically-led centers of excellence to explore process improvements, develop fit-for-purpose engineering and project execution, and accelerate the translation of customer objectives into actions that drive production and project certainty. The Major Projects and Integrated Solutions segment focuses on delivering projects that pose a level of commercial and reputational risk for Worley by the nature of their size, complexity and the scope of services and also engages in delivering integrated solutions, which include maintenance, modification, operations, engineering, fabrication, construction, hook-up and commissioning services to existing assets around the globe. The Advisian segment provides a true end-to-end offering integrating strategy, management and technical consulting expertise to clients in the hydrocarbons, resources and infrastructure sectors. The company was founded by John Michael Grill in 1971 and is headquartered in Sydney, Australia. | AC19: Infrastructure Construction/Contracting Services | AD19: Facilities and Construction Services | AE19: Industrial Services | AF19: Process Plants, Utilities and Energy Construction | AH19: 24485 | AI19: 1 | AJ19: "GHG emissions from diesel generators at four leased sites in India were reclassified from Scope 1 to Scope 3 – category 8, as they relate to base building operations" managed by landlords. This caused our Scope 1 & 2 emissions to decrease by approximately 27t CO2e. 27/38360 0.1% decrease in emissions compared to FY2024. Change in boundary | AK19: 6524 | AL19: 1 | AM19: We report Scope 2 emissions using both location-based and market-based methods as recommended by the GHG Protocol Scope 2 Guidance. | AN19: 1317095 | AO19: 1 | AP19: Our Climate Change Position Statement (CCPS) sets out the actions we’re taking in response to climate change. We are decarbonizing our business and are, "committed to reducing Scope 1 and 2 GHG emissions to net zero by 2030, and Scope 3 emissions by 2050. We plan to achieve our Scope 1 and 2 commitments", "through initiatives, such as reducing energy use and switching to renewable energy and low carbon fuels. We will achieve our Scope 3 commitments through working", | AQ19: 26 | AR19: 0.036446 | AS19: 0.002317
A20: VCX-AU | B20: Vicinity Centres | D20: KH | E20: Jason Temby | F20: Invitation sent | R20: =IFERROR(_xlfn.XLOOKUP($A20,Profitability!$A$5:$A$342,Profitability!$Q$5:$Q$342),"na") | S20: =IFERROR(_xlfn.XLOOKUP($A20,Profitability!$A$5:$A$342,Profitability!$R$5:$R$342),"na") | T20: Public | U20: Australia | V20: 1985 | W20: 1246 | X20: 1330.1 | Y20: Pacific | Z20: Victoria (VIC) | AA20: 16342.5 | AB20: Vicinity Centres operates as a real estate investment trust, which engages in the development, operation, and management of shopping centers. It operates through the following business segments: Property Investment and Strategic Partnerships. The Property Investment segment comprises of net property income derived from investment in retail property. The Strategic Partnerships segement offers property management, development, leasing, and management of wholesale property funds. The company was founded on February 18, 1985 and is headquartered in Chadstone, Australia. | AC20: Equity REITs | AD20: Real Estate Investment Trusts (REITs) | AE20: Real Estate | AF20: Equity REITs | AH20: 5516 | AI20: 1 | AJ20: === Table 6 (page 145) === "We reviewed a selection of performance metrics, as",,14 Gender 40:40:20 target,63:37:0 | AK20: 108143 | AL20: 1 | AM20: Total Scope 1 greenhouse gas (GHG) emissions,tCO2-e,"1,116",(28%),(53%) Total Scope 2 GHG emissions,tCO2-e,"36,816",0%,(38%) Total Scope 1 and Scope 2 GHG emissions,tCO2-e,"37,932",(1%),(38%) | AN20: 204469 | AO20: 1 | AP20: Total Scope 1 greenhouse gas (GHG) emissions,tCO2-e,"1,116",(28%),(53%) Total Scope 2 GHG emissions,tCO2-e,"36,816",0%,(38%) Total Scope 1 and Scope 2 GHG emissions,tCO2-e,"37,932",(1%),(38%) | AQ20: 17 | AR20: 0.755282 | AS20: 0.012781
A21: DXS-AU | B21: Dexus | D21: KH | E21: Ramana James | F21: Invitation sent | R21: =IFERROR(_xlfn.XLOOKUP($A21,Profitability!$A$5:$A$342,Profitability!$Q$5:$Q$342),"na") | S21: =IFERROR(_xlfn.XLOOKUP($A21,Profitability!$A$5:$A$342,Profitability!$R$5:$R$342),"na") | T21: Public | U21: Australia | V21: 2004 | W21: 900 | X21: 1007.6 | Y21: Pacific | Z21: New South Wales (NSW) | AA21: 15388.6 | AB21: Dexus engages in real estate investments, leasing, and tenant services. It operates through the following segments: Office, Industrial, Co-Investment, Property Management, Funds Management, Development and Trading, and All Other. The Office segment offers domestic space with any associated retail space, car parks, and developments. The Industrial segment consists of domestic industrial properties, industrial estates, and developments. The Co-Investment segment focuses on income distribution earned from investments in pooled real assets and funds. The Property Management segment provides management services for third party clients and owned assets. The Funds Management segment offers management of third-party client assets. The Development and Trading segment includes the revenue earned and costs incurred on developments and inventory. The All Other segment involves the corporate expenses associated with maintaining and operating, and the treasury function managed through a centralized treasury department. The company was founded in 2004 and is headquartered in Sydney, Australia. | AC21: Equity REITs | AD21: Real Estate Investment Trusts (REITs) | AE21: Real Estate | AF21: Equity REITs | AH21: 7669 | AI21: 1 | AJ21: Scope 1 GHG emissions,tCO2e,"7,669" | AK21: 0 | AL21: 1 | AM21: Scope 2 location-based GHG emissions,tCO2e,"90,686" | AN21: 26006 | AO21: 1 | AP21: Scope 3 location-based GHG emissions,tCO2e,"34,745" | AQ21: 22 | AR21: 0.003374 | AS21: 0.021834
A22: COH-AU | B22: Cochlear Ltd. | D22: KH | E22: Michael Grasso | F22: Invitation sent | R22: =IFERROR(_xlfn.XLOOKUP($A22,Profitability!$A$5:$A$342,Profitability!$Q$5:$Q$342),"na") | S22: =IFERROR(_xlfn.XLOOKUP($A22,Profitability!$A$5:$A$342,Profitability!$R$5:$R$342),"na") | T22: Public | U22: Australia | V22: 1983 | W22: 5500 | X22: 2355.8 | Y22: Pacific | Z22: New South Wales (NSW) | AA22: 2825.0001 | AB22: Cochlear Ltd. engages in the provision of implantable hearing solutions. The firm operates through the following geographical segments: Americas, EMEA, Asia Pacific, Corporate and Other. The company was founded by Michael S. Hirshorn in 1981 and is headquartered in Sydney, Australia. | AC22: Specialized Medical Devices | AD22: Other Medical Devices | AE22: Healthcare Equipment | AF22: Other Specialized Medical Devices | AH22: 951 | AI22: 1 | AJ22: pathway for adults,and services,"a culture of aspiration,",of initiatives to reduce our,,returns ,,"achievement, experimentation","Scope 1, 2 and 3 carbon",, • Develop the acoustic implant,• Support recipient access to,,,•,Improve efficiency and agility | AK22: 1980 | AL22: 1 | AM22: ,operate on 100% renewable energy. We are actively working to,,, Scope 1 and Scope 2 emissions,,,, ,expand renewable energy use across all locations.,,, | AN22: 66616 | AO22: 1 | AP22: ,"necessary to our operations, we are actively exploring viable",,,,,,,,, ,low-emission alternatives.,Scope 34,tCO2e,"66,616*","14,418","10,950","2,196",186,"4,774","18,630" ,,Carbon offsets5,tCO2e,"3,401","11,422","7,941","1,150",0,0,0 | AQ22: 2 | AR22: 0.165082 | AS22: 0.000849
A23: CWP-AU | B23: Cedar Woods Properties Ltd. | D23: KH | E23: Karl White | F23: Invitation sent | R23: =IFERROR(_xlfn.XLOOKUP($A23,Profitability!$A$5:$A$342,Profitability!$Q$5:$Q$342),"na") | S23: =IFERROR(_xlfn.XLOOKUP($A23,Profitability!$A$5:$A$342,Profitability!$R$5:$R$342),"na") | T23: Public | U23: Australia | V23: 1987 | W23: 93 | X23: 468.595 | Y23: Pacific | Z23: Western Australia (WA) | AA23: 857.68402 | AB23: Cedar Woods Properties Ltd. engages in property investment and development. The firm's principal interests are in urban land and built form development for residential, industrial and commercial purposes. Its projects include St. A in St Albans, Jackson Green in Clayton South, Williams Landing, Bushmead, Harrisdale Green, Ellendale, and Glenside. The company was founded by William George Hames and Ross James Neumann in 1987 and is headquartered in West Perth, Australia. | AC23: Other Real Estate Investment and Services | AD23: Real Estate Investment and Services | AE23: Real Estate | AF23: Real Estate Developers | AH23: 74 | AJ23: Reported as combined Scope 1 & 2 net Greenhouse Gas Emissions (t-CO2-e). | AK23: 74 | AM23: Reported as combined Scope 1 & 2 net Greenhouse Gas Emissions (t-CO2-e). | AN23: 0 | AP23: No specific Scope 3 total found. | AQ23: 0 | AR23: 0.102733 | AS23: 0
A24: CNI-AU | B24: Centuria Capital Group | D24: KH | E24: Andrew Scerri | F24: Invitation sent | R24: =IFERROR(_xlfn.XLOOKUP($A24,Profitability!$A$5:$A$342,Profitability!$Q$5:$Q$342),"na") | S24: =IFERROR(_xlfn.XLOOKUP($A24,Profitability!$A$5:$A$342,Profitability!$R$5:$R$342),"na") | T24: Public | U24: Australia | V24: 1980 | W24: - | X24: 431.797 | Y24: Pacific | Z24: New South Wales (NSW) | AA24: 3586.8881 | AB24: Centuria Capital Group is funds manager company. It operates through the following segments: Property Funds, Co-Investments, Developments, Property & Development Finance, Investment Bonds and Corporate. Property Funds Segment which specializes in listed and unlisted property funds. Co-Investments Segment provides direct interest in property funds, properties held for development and other liquid investments. Developments Segment gives completion of structured property developments which span sectors ranging from commercial office,industrial and health through to affordable housing and residential mixed use. Property and Development Finance Segment deals with provision of real estate secured non-bank finance for development projects, bridge finance and residual stock. Investment Bonds Segment including single and multi-premium investments. The company was founded in 1980 and is headquartered in Sydney, Australia. | AC24: Asset Management and Financial Advisory Services | AD24: Investment Services | AE24: Investment Services | AF24: Alternative Investment Managers | AQ24: 1 | AR24: 0.191518 | AS24: 0.002316
A25: CHC-AU | B25: Charter Hall Group | D25: KH | E25: Janaki Dhagat | F25: Invitation sent | R25: =IFERROR(_xlfn.XLOOKUP($A25,Profitability!$A$5:$A$342,Profitability!$Q$5:$Q$342),"na") | S25: =IFERROR(_xlfn.XLOOKUP($A25,Profitability!$A$5:$A$342,Profitability!$R$5:$R$342),"na") | T25: Public | U25: Australia | V25: 1991 | W25: - | X25: 687.8 | Y25: Pacific | Z25: New South Wales (NSW) | AA25: 3584.4001 | AB25: Charter Hall Group engages in managing and investing in office, retail, and industrial properties. It operates through the following segments: Property Investments, Development investments, and Funds Management. The Property Investments segment comprises an investment portfolio of property funds. The Development investments segment comprises investments in developments. The Funds Management segment offers investment management services and real estate management services. The company was founded by Cedric Fuchs and David John Southon in 1991 and is headquartered in Sydney, Australia. | AC25: Equity REITs | AD25: Real Estate Investment Trusts (REITs) | AE25: Real Estate | AF25: Equity REITs | AH25: 23741 | AI25: 0.9 | AJ25: ,"we are signatories, and prioritises reducing energy",, ,,"centres increased from 0.5MW to 17.5MW, coupled with","St, 480 Swan St and 60 King William St, have all-electric" reduction aligned to climate science.,"consumption, eliminating fossil fuels, and compensating",, | AK25: 100938 | AL25: 0.9 | AM25: In FY25 we achieved a 77% reduction,From 1 July our whole platform will,Nature-based carbon offsets,80% of the onsite solar across the,Achieved 48% waste diversion from in net Scope 1 and Scope 2 emissions1,operate at 100% renewable energy,(9% of total Scope 1 and Scope 2,Group supplied tenants with clean,landfill across Office and Shopping from our FY17 baseline.,supply in assets under operational,emissions) enabled us to achieve our,"energy, reducing our downstream",Centre Retail sites under operational | AN25: 280000 | AO25: 0.9 | AP25: ,"we are signatories, and prioritises reducing energy",, ,,"centres increased from 0.5MW to 17.5MW, coupled with","St, 480 Swan St and 60 King William St, have all-electric" reduction aligned to climate science.,"consumption, eliminating fossil fuels, and compensating",, | AQ25: 64 | AR25: 0.328293 | AS25: 0.09305
A26: SCG-AU | B26: Scentre Group | D26: KH | E26: Katie Moran | F26: Invitation sent | P26: 10046 | Q26: 179604 | R26: =IFERROR(_xlfn.XLOOKUP($A26,Profitability!$A$5:$A$342,Profitability!$Q$5:$Q$342),"na") | S26: =IFERROR(_xlfn.XLOOKUP($A26,Profitability!$A$5:$A$342,Profitability!$R$5:$R$342),"na") | T26: Public | U26: Australia | V26: 1959 | W26: 2860 | X26: 2637.1 | Y26: Pacific | Z26: New South Wales (NSW) | AA26: 36354.899 | AB26: Scentre Group engages in the business of owning, managing, leasing, and developing Westfield destinations in Australia and New Zealand. It operates under the Property Investment, and Property Management and Construction segments. The Property Investment segment includes net property income from shopping centers. The Property Management and Construction segment focuses on external fee income from third parties primarily property management and development fees, and associated business expenses. The company was founded in July 1959 and is headquartered in Sydney, Australia. | AC26: Equity REITs | AD26: Real Estate Investment Trusts (REITs) | AE26: Real Estate | AF26: Equity REITs | AH26: 10211 | AI26: 1 | AJ26: "Scope 1 GHG emissions in tonnes of carbon dioxide 10,211",,► National Greenhouse and Energy Reporting Act 2007 (for,,, equivalent (tCO2-e),,,,, | AK26: 175110 | AL26: 1 | AM26: "Scope 2 GHG emissions as calculated using the 175,110",,,,, ,,GHG Protocol Corporate Standard,,, | AN26: 72655 | AO26: 1 | AP26: "Selected Scope 3 GHG emissions (limited to waste to 72,655",K,,,, "landfill, purchased electricity, employee commute",ey responsibilities,,,, | AQ26: 0 | AR26: 0.398089 | AS26: 0
A27: S32-AU | B27: South32 Ltd. | D27: KH | E27: Jazmin Searson | F27: Invitation sent | P27: 5697621 | Q27: 308477 | R27: =IFERROR(_xlfn.XLOOKUP($A27,Profitability!$A$5:$A$342,Profitability!$Q$5:$Q$342),"na") | S27: =IFERROR(_xlfn.XLOOKUP($A27,Profitability!$A$5:$A$342,Profitability!$R$5:$R$342),"na") | T27: Public | U27: Australia | V27: 2000 | W27: 8892 | X27: 8924.8354 | Y27: Pacific | Z27: Western Australia (WA) | AA27: 20946.06 | AB27: South32 Ltd. operates as a metal and mining company. It operates through the following segments: Worsley Alumina, Hillside Aluminium, Mozal Aluminium, Brazil Alumina, South Africa Energy Coal, Illawarra Metallurgical Coal, Eagle Downs Metallurgical Coal, Australia Manganese, South Africa Managanese, Cerro Matoso, Cannington, and Hermosa. The Worsley Alumina segment offers bauxite mine and alumina refinery in Western Australia. The Hillside Aluminium segment offers aluminium smelters at Richards Bay, South Africa. The Mozal Aluminium segment includes aluminium smelter in Mozambique. The Brazil Alumina segment covers alumina refinery in Brazil. The South Africa Energy Coal segment comprises of open-cut and underground energy coal mines and processing operations in South Africa. The Illawarra Metallurgical Coal segment consists of underground metallurgical coal mines in New South Wales, Australia. The Eagle Downs Metallurgical Coal segment involves in the exploration and development of metallurgical coal deposit in Queensland, Australia. The Australia Manganese segment produces manganese ore in the Northern Territory and manganese alloys in Tasmania. The South Africa Manganese segment involves in the production of ore and alloy in South Africa. The Cerro Matoso segment includes laterite ferronickel mining and smelting complex in Colombia. The Cannington segment explores silver, lead, and zinc. The Hermosa segment involves in exploration and development option for zinc, lead and silver sulphide deposit in Tucson, United States. The company was founded on July 12, 2000 and is headquartered in Perth, Australia. | AC27: Primary Metals Products | AD27: Metal Products | AE27: Mining and Mineral Products | AF27: Alumina and Aluminum Products Manufacturing | AH27: 7400000 | AI27: 1 | AJ27: Total high potential injuries,, ,0.2, and illnesses frequency (HPIIF),, | AK27: 17300000 | AL27: 1 | AM27: US$10.5 million exceeded our target of US$3.63 million.,Worsley Alumina’s Scope 1 emissions and a 4.2% reduction in total ,"Scope 1 emissions42, both relative to FY21 levels. However, in FY25" In Australia we are committed to increasing our procurement of, | AN27: 22700000 | AO27: 1 | AP27: Total high potential injuries,, ,0.2, and illnesses frequency (HPIIF),, | AQ27: 15 | AR27: 0.055017 | AS27: 0.001681
A28: SHA-AU | B28: Shape Australia Corp. Ltd. | D28: KH | E28: Shane Morgan | F28: Invitation sent | R28: =IFERROR(_xlfn.XLOOKUP($A28,Profitability!$A$5:$A$342,Profitability!$Q$5:$Q$342),"na") | S28: =IFERROR(_xlfn.XLOOKUP($A28,Profitability!$A$5:$A$342,Profitability!$R$5:$R$342),"na") | T28: Public | U28: Australia | V28: 2021 | W28: 686 | X28: 947.64 | Y28: Pacific | Z28: New South Wales (NSW) | AA28: 275.06601 | AB28: Shape Australia Corp. Ltd. operates an end-to-end service and delivery model across the project lifecycle, from new build, fit-out and refurbishment, and recurring minor works. The firm is focused on commercial fit-out and refurbishments, with select capabilities in new build. It acts as a head contractor on fit-out and refurbishment projects across Australia, with capabilities across a range of projects and services. The company was founded in 1989 and is headquartered in Sydney, Australia. | AC28: Specialty Contracting Services | AD28: Facilities and Construction Services | AE28: Industrial Services | AF28: Commercial Specialty Engineering Contractors | AQ28: 0 | AR28: 0.02229 | AS28: 0
A29: MQG-AU | B29: Macquarie Group Ltd. | D29: KH | E29: Mary Ann van Bodegraven | F29: Invitation sent | R29: =IFERROR(_xlfn.XLOOKUP($A29,Profitability!$A$5:$A$342,Profitability!$Q$5:$Q$342),"na") | S29: =IFERROR(_xlfn.XLOOKUP($A29,Profitability!$A$5:$A$342,Profitability!$R$5:$R$342),"na") | T29: Public | U29: Australia | V29: 2006 | W29: 19735 | X29: 32008 | Y29: Pacific | Z29: New South Wales (NSW) | AA29: 446434.01 | AB29: Macquarie Group Ltd. operates as a non-operating holding company. The firm engages in the provision of banking, financial, advisory, investment and funds management services. It operates through the following segments: Macquarie Asset Management (MAM), Banking and Financial Services (BFS), Commodities and Global Markets (CGM), Macquarie Capital and Corporate. The MAM segment delivers investment solutions to clients across a range of capabilities, including infrastructure, real estate, agriculture, equities, fixed income, private credit, liquid alternatives, and multi-asset solutions. The BFS segment offers personal banking, wealth management, business banking, and vehicle finance products and services to retail clients, advisers, brokers and business clients. The CGM segment comprises of integrated, end-to-end offering across global markets including equities, fixed income, foreign exchange, and commodities. The Macquarie Capital segment includes capital solutions across products and sectors including infrastructure, green and conventional energy. The Corporate segment refers to the head office and central service groups, including group treasury and other investments. The company was founded on December 10, 1969 and is headquartered in Sydney, Australia. | AC29: Diversified Investment | AD29: Investment Services | AE29: Investment Services | AF29: Diversified Investment | AH29: 482 | AJ29: FY25 Scope 1 emissions (tCO2e). | AK29: 0 | AM29: FY25 Scope 2 emissions (tCO2e). Scope 2 emissions reduced to zero since FY2022 due to the purchase of 100% renewable electricity equivalent. | AN29: 227896 | AP29: FY25 Total Scope 3 (Categories 1-6 & 8) operational emissions (tCO2e). | AQ29: 24 | AR29: 0.111941 | AS29: 0.00075
A30: Private | B30: CDC | D30: KH | E30: Nicholas Blay | F30: Invitation sent | R30: =IFERROR(_xlfn.XLOOKUP($A30,Profitability!$A$5:$A$342,Profitability!$Q$5:$Q$342),"na") | S30: =IFERROR(_xlfn.XLOOKUP($A30,Profitability!$A$5:$A$342,Profitability!$R$5:$R$342),"na") | AH30: 929 | AI30: 1 | AJ30: ,when compared to on-premises energy,,external partners and their suppliers the early vision for the company.,,"carbon by 2030 for Scope 1, 2 and", ,"consumption. At the same time, the data",,for their important role in driving a | AK30: 78601 | AL30: 1 | AM30: ,,is a particularly pertinent challenge in countries like, ,an average Water Usage Effectiveness of 0.01. CDC’s closed-loop chilled water system consumes almost,, ,,"Australia, where severe droughts can significantly",This innovation is considered a genuine game | AN30: 0 | AQ30: 13
A31: ING-AU | B31: Inghams Group Ltd. | D31: KH | E31: Naomi Martin | F31: Invitation sent | P31: 63131 | Q31: 131449 | R31: =IFERROR(_xlfn.XLOOKUP($A31,Profitability!$A$5:$A$342,Profitability!$Q$5:$Q$342),"na") | S31: =IFERROR(_xlfn.XLOOKUP($A31,Profitability!$A$5:$A$342,Profitability!$R$5:$R$342),"na") | T31: Public | U31: Australia | V31: 2013 | W31: - | X31: 3152.4 | Y31: Pacific | Z31: New South Wales (NSW) | AA31: 2364.3001 | AB31: Inghams Group Ltd. engages in the production and sale of chicken and turkey products. It operates through the Australia and New Zealand geographical segment. The company was founded in 1918 and is headquartered in North Ryde, Australia. | AC31: Food Production | AD31: Food and Beverage Production | AE31: Food and Tobacco Production | AF31: Meat and Seafood Production | AH31: 55812 | AI31: 1 | AJ31: Scope 1 GHG emissions (tCO2-eq),"55,812" | AK31: 128861 | AL31: 1 | AM31: Scope 2 GHG emissions (tCO2-eq) (location based),"128,861" | AN31: 0 | AO31: 0.95 | AP31: Production (t),"1,993,887" Scope 1 GHG emissions (tCO2-eq),"55,812" Scope 2 GHG emissions (tCO2-eq) (location based),"128,861" | AQ31: 0 | AR31: 0.028488 | AS31: 0
A32: DCFCQ-US | B32: Tritium DCFC Ltd. | C32: I thought they went into liquidation? Or was it just administration | D32: KH | E32: Sean Simmons | F32: Invitation sent | R32: =IFERROR(_xlfn.XLOOKUP($A32,Profitability!$A$5:$A$342,Profitability!$Q$5:$Q$342),"na") | S32: =IFERROR(_xlfn.XLOOKUP($A32,Profitability!$A$5:$A$342,Profitability!$R$5:$R$342),"na") | T32: Public | U32: Australia | V32: 2021 | W32: 1001 | X32: 274.35455 | Y32: Pacific | Z32: Queensland (QLD) | AA32: 413.39443 | AB32: Tritium DCFC Ltd. designs and manufactures proprietary hardware and software to develop direct current chargers for electric vehicles. It operates through the following segments: Hardware, Software, and Service and Maintenance. The company was founded by David Finn, Paul Serina and James Kennedy on May 7, 2021 and is headquartered in Murarrie, Australia. | AC32: Commercial and Industrial Electric Products | AD32: Electrical Equipment and Power Systems | AE32: Industrial Manufacturing | AF32: General Industrial Electrical Products
A33: TLS-AU | B33: Telstra Group Ltd. | D33: KH | E33: Justine Rowe | F33: Invitation sent | P33: 32771 | Q33: 757967 | R33: =IFERROR(_xlfn.XLOOKUP($A33,Profitability!$A$5:$A$342,Profitability!$Q$5:$Q$342),"na") | S33: =IFERROR(_xlfn.XLOOKUP($A33,Profitability!$A$5:$A$342,Profitability!$R$5:$R$342),"na") | T33: Public | U33: Australia | V33: 1992 | W33: 30553 | X33: 23125 | Y33: Pacific | Z33: Victoria (VIC) | AA33: 44968.001 | AB33: Telstra Group Ltd. engages in the provision of telecommunications and technology services. It operates through the following segments: Telstra Consumer and Small Business (TC&SB), Telstra Enterprise (TE), Networks and IT (N&IT), Telstra InfraCo, and All Other. The TC&SB segment consists of telecommunication, media, and technology products and services to consumer and small business customers, using mobile and fixed network technologies. The TE segment offers telecommunication services, technology solutions, network capacity and management, unified communications, cloud, security, industry solutions, and monitoring services to government and large enterprise. The N&IT segment maintains reliability and security network platforms and data. Telstra InfraCo covers telecommunication products and services delivered over Telstra networks to other carriers, carriage service providers, and internet service providers. The company was founded in 1992 and is headquartered in Melbourne, Australia. | AC33: Pan-Asia/Pacific Mixed Telecommunications Services | AD33: General Telecommunications Services | AE33: Telecommunications | AF33: Australia/New Zealand Mixed Telecom Services | AH33: 31794 | AJ33: FY25 Scope 1 total emissions (tCO2e). Calculated using location-based methodology for S1&S2. | AK33: 703989 | AM33: FY25 Scope 2 total emissions (tCO2e). Calculated using location-based methodology for S1&S2. | AN33: 1454930 | AP33: FY25 Scope 3 total emissions (tCO2e) (aligned to GHG protocol). | AQ33: 6 | AR33: 0.093924 | AS33: 0.000259
A34: LLC-AU | B34: Lendlease Group | D34: KH | E34: Darryl Stuckey | F34: Request message sent | P34: 15951 | Q34: 79159 | R34: =IFERROR(_xlfn.XLOOKUP($A34,Profitability!$A$5:$A$342,Profitability!$Q$5:$Q$342),"na") | S34: =IFERROR(_xlfn.XLOOKUP($A34,Profitability!$A$5:$A$342,Profitability!$R$5:$R$342),"na") | T34: Public | U34: Australia | V34: 1958 | W34: - | X34: 7786 | Y34: Pacific | Z34: New South Wales (NSW) | AA34: 14562 | AB34: Lendlease Group operates as a property and infrastructure development company. It engages in designing, developing, constructing, funding, owning, co-investing or managing property, and infrastructure assets. The firm operates through the following segments: Investments, Development, Construction, and Capital Release Unit. The Investments segment includes an investment management platform and the group's ownership interests in residential, office, retail, industrial, retirement and infrastructure investment assets. The Development segment includes the development of inner-city mixed-use developments, apartments, communities, retirement, retail, commercial assets and social and economic infrastructure. The Construction segment includes the provision of project management, design and construction services, predominantly in the commercial, residential, mixed use, defense, and social infrastructure sectors. The Capital Release Unit segment includes overseas construction operations, overseas development projects, the group’s residual ownership interest in retirement assets and the US Military Housing business, Australian communities projects and the retained engineering and services projects. The company was founded by Gerardus Jozef Dusseldorp in 1957 and is headquartered in Barangaroo, Australia. | AC34: Infrastructure Construction/Contracting Services | AD34: Facilities and Construction Services | AE34: Industrial Services | AF34: Diverse Construction and Engineering Services | AH34: 23715 | AJ34: FY25 Gross Scope 1 Emissions (tCO2-eq). | AK34: 0 | AM34: FY25 Gross Scope 2 Emissions (Market-based Method) (tCO2-eq). Market-based emissions resulted in zero due to application of renewable electricity purchases/offsets. | AN34: 1353639 | AP34: FY25 Total Scope 3 Emissions (tCO2-eq). | AQ34: 0 | AR34: 0.028898 | AS34: 0
A35: NXT-AU | B35: NextDC Ltd. | D35: KH | E35: Nishi Vissamraju | F35: Request message sent | P35: 1614 | Q35: 335627 | R35: =IFERROR(_xlfn.XLOOKUP($A35,Profitability!$A$5:$A$342,Profitability!$Q$5:$Q$342),"na") | S35: =IFERROR(_xlfn.XLOOKUP($A35,Profitability!$A$5:$A$342,Profitability!$R$5:$R$342),"na") | T35: Public | U35: Australia | V35: 2010 | W35: 310 | X35: 427.209 | Y35: Pacific | Z35: Queensland (QLD) | AA35: 5688.6871 | AB35: NextDC Ltd. engages in the operation and development of data centers. It operates through the following segments: Vic, NSW/ACT, Rest of Australia, International, and Other. The company was founded by Bevan Andrew Slattery on May 11, 2010, and is headquartered in Brisbane, Australia. | AC35: Internet Hosting Services | AD35: Internet and Data Services | AE35: Software and Consulting | AF35: Colocation and Data Center Services | AH35: 7927 | AI35: 1 | AJ35: ,,,,,,, Climate,"In FY25, our Scope 1 emissions totalled 7,927 tCO2-e,",emission,emission,,,, ,primarily driven by diesel consumption for backup,source,source,,,, | AK35: 358348 | AL35: 1 | AM35: ,environmental,,,, ,0,,,,Social highlights ,,,,, | AN35: 0 | AQ35: 13 | AR35: -0.141718 | AS35: 0.03043
A36: PRN-AU | B36: Perenti Ltd. | D36: Vishal | E36: Darren Batchler | F36: Request message sent | R36: =IFERROR(_xlfn.XLOOKUP($A36,Profitability!$A$5:$A$342,Profitability!$Q$5:$Q$342),"na") | S36: =IFERROR(_xlfn.XLOOKUP($A36,Profitability!$A$5:$A$342,Profitability!$R$5:$R$342),"na") | T36: Public | U36: Australia | V36: 1986 | W36: 10290 | X36: 3489.546 | Y36: Pacific | Z36: Western Australia (WA) | AA36: 3416.6921 | AB36: Perenti Ltd. is a mining and energy services company, which engages in the provision of exploration, mine development, surfacing and underground mining, and energy and infrastructure services. It operates through the following segments: Contract Mining, Drilling Services, Mining and Technology Services, and Corporate. The Contract Mining segment provides underground and surface contract mining services. The Drilling Services segment offers drilling services across all stages of the mine life cycle. The Mining and Technology Services segment includes equipment hire, equipment parts and sales, supply of equipment, logistics services, and technology driven products and services. The Corporate segment focuses on corporate activity covering strategy, treasury, accounting, human resources, information technology, procurement, legal, risk, investor relations, and other corporate administration. The company was founded by James Edward Askew and Ronald George Sayers in 1987 and is headquartered in Perth, Australia. | AC36: Specialty Contracting Services | AD36: Facilities and Construction Services | AE36: Industrial Services | AF36: Industrial Specialty Engineering Contractors | AH36: 2004 | AI36: 1 | AJ36: ,,OUR SUSTAINABILITY TARGETS,,, ,,,female executive and,,scope 1 and 2 ,,,,, | AK36: 2969 | AL36: 1 | AM36: Greenhouse gas emissions – Scope 2 (market-based),"1,834 tonnes CO2-e" Greenhouse gas emissions – Scope 2 (location-based),"2,969 tonnes CO2-e" | AN36: 0 | AO36: 0.9 | AP36: ,,OUR SUSTAINABILITY TARGETS,,, ,,,female executive and,,scope 1 and 2 ,,,,, | AQ36: 8 | AR36: 0.034565 | AS36: 0.002293
A37: NCK-AU | B37: Nick Scali Ltd. | D37: Vishal | E37: Angus McDonald | F37: Request message sent | R37: =IFERROR(_xlfn.XLOOKUP($A37,Profitability!$A$5:$A$342,Profitability!$Q$5:$Q$342),"na") | S37: =IFERROR(_xlfn.XLOOKUP($A37,Profitability!$A$5:$A$342,Profitability!$R$5:$R$342),"na") | T37: Public | U37: Australia | V37: 1962 | W37: 850 | X37: 495.283 | Y37: Pacific | Z37: New South Wales (NSW) | AA37: 705.80702 | AB37: Nick Scali Ltd. engages in the sourcing and retailing of household furniture and related accessories. It offers sofas and armchairs, rugs and accessories, and furniture for living, dining, and bedroom. The company was founded by Nicodemo Domenico Scali in 1962 and is headquartered in North Ryde, Australia. | AC37: Furniture and Home Furnishings Stores | AD37: Home Improvement Retail | AE37: Consumer Retail | AF37: Furniture Stores | AQ37: 0 | AR37: 0.116451 | AS37: 0
A38: STO-AU | B38: Santos Ltd. | D38: Vishal | E38: James Murphy | F38: Request message sent | M38: 2024 | N38: =4.44*10^6 | O38: =0.8*10^6 | P38: 4233840 | Q38: 733963 | R38: =IFERROR(_xlfn.XLOOKUP($A38,Profitability!$A$5:$A$342,Profitability!$Q$5:$Q$342),"na") | S38: =IFERROR(_xlfn.XLOOKUP($A38,Profitability!$A$5:$A$342,Profitability!$R$5:$R$342),"na") | T38: Public | U38: Australia | V38: 1954 | W38: 3958 | X38: 8298.981 | Y38: Pacific | Z38: South Australia (SA) | AA38: 49855.445 | AB38: Santos Ltd. engages in the exploration, development, transportation, and marketing of natural gas. It operates through the following segments: Cooper Basin, Queensland and New South Wales, Papua New Guinea, Northern Australia and Timor-Leste, and Western Australia. The company was founded by Reg Sprigg, John Bonython, and Douglas Mawson on March 18, 1954 and is headquartered in Adelaide, Australia. | AC38: Other Pipeline and Energy Storage Services | AD38: Midstream Energy | AE38: Downstream and Midstream Energy | AF38: Other Pipeline and Energy Storage Services | AH38: 4440000 | AJ38: 2024 Gross operated Scope 1 greenhouse gas emissions (4.44 MtCO2e). | AK38: 800000 | AM38: 2024 Gross operated Scope 2 greenhouse gas emissions (0.80 MtCO2e). | AN38: 29900000 | AP38: 2024 Total Scope 3 emissions (29.9 MtCO2e). | AQ38: 4 | AR38: 0.223602 | AS38: 0.000482
A39: KAR-AU | B39: Karoon Energy Ltd. | D39: Vishal | E39: Oscar Brooks | F39: Request message sent | R39: =IFERROR(_xlfn.XLOOKUP($A39,Profitability!$A$5:$A$342,Profitability!$Q$5:$Q$342),"na") | S39: =IFERROR(_xlfn.XLOOKUP($A39,Profitability!$A$5:$A$342,Profitability!$R$5:$R$342),"na") | T39: Public | U39: Australia | V39: 2003 | W39: - | X39: 1177.2303 | Y39: Pacific | Z39: Victoria (VIC) | AA39: 3135.7505 | AB39: Karoon Energy Ltd. is an oil and gas exploration company, which engages in oil and gas production, development assets, and providing energy. It operates through the following geographical segments: Australia, Brazil, U.S.A., and All Other. The Australia segment is involved in the exploration and evaluation of hydrocarbons. The Brazil segment refers to the exploration, development, and production of hydrocarbons. The U.S.A segment focuses on the acquisition of LLOG interests in the Mississippi Canyon Blocks in the Gulf of Mexico. The All Other segment relates to the closure of its Peruvian branches. The company was founded by Robert Michael Hosking on November 11, 2003 and is headquartered in Southbank, Australia. | AC39: Americas Fossil Fuel Exploration and Production | AD39: Fossil Fuel Exploration and Production | AE39: Upstream Energy | AF39: Other Americas Fossil Fuel Exploration/Production | AH39: 127937 | AI39: 1 | AJ39: 140,000" Carbon Neutral for Scope 1 and,"125,732 127,996" | AK39: 59 | AL39: 1 | AM39: 140,000" Carbon Neutral for Scope 1 and,"125,732 127,996" | AN39: 4651475 | AO39: 1 | AP39: Scope 2 Offset,129,38,55,- "Scope 3 emissions (tCO2e)7,8,9,10,11,12","1,000,886","2,679,198","3,941,858","4,651,475" Category 1 – Purchased Goods and Services,-,"34,644","27,693","30,148" | AQ39: 15 | AR39: 0.164198 | AS39: 0.012742
A40: TRS-AU | B40: The Reject Shop Ltd. | D40: Vishal | E40: navroop kaur sidhu | F40: Request message sent | R40: =IFERROR(_xlfn.XLOOKUP($A40,Profitability!$A$5:$A$342,Profitability!$Q$5:$Q$342),"na") | S40: =IFERROR(_xlfn.XLOOKUP($A40,Profitability!$A$5:$A$342,Profitability!$R$5:$R$342),"na") | T40: Public | U40: Australia | V40: 1983 | W40: 4000 | X40: 852.736 | Y40: Pacific | Z40: Victoria (VIC) | AA40: 492.715 | AB40: The Reject Shop Ltd. engages in retailing discount variety merchandise. It offers general consumer merchandise such as toiletries, cosmetics, homeware, personal care products, hardware, basic furniture, household cleaning products, kitchenware, confectionery, snack food, lifestyle and seasonal merchandise, such as seasonal gifts, cards and wrapping, toys, leisure items and home decorations. The company was founded by Ron Hall and John Shuster in 1981 and is headquartered in Kensington, Australia. | AC40: Discount Stores | AD40: General Merchandise Retail | AE40: Food and Staples Retail | AF40: General Discount Stores | AR40: 0.005527
A41: SFR-AU | B41: Sandfire Resources Ltd. | D41: Vishal | E41: Jared Jacob & Brendon Harris | F41: Request message sent | R41: =IFERROR(_xlfn.XLOOKUP($A41,Profitability!$A$5:$A$342,Profitability!$Q$5:$Q$342),"na") | S41: =IFERROR(_xlfn.XLOOKUP($A41,Profitability!$A$5:$A$342,Profitability!$R$5:$R$342),"na") | T41: Public | U41: Australia | V41: 2003 | W41: 5468 | X41: 1830.3324 | Y41: Pacific | Z41: Western Australia (WA) | AA41: 4483.3922 | AB41: Sandfire Resources Ltd. engages in the production and sale of copper, gold, and silver. It operates through the following segments: DeGrussa Copper Operations, MATSA Copper Operations, Black Butte Project, Motheo Copper Project, and Exploration and Other. The DeGrussa Copper Operations segment is involved in both the DeGrussa and Monty Copper-Gold mines in the Bryah basin. The company was founded on June 18, 2003 and is headquartered in West Perth, Australia. | AC41: Base Metal Mining | AD41: Metal Ore Mining | AE41: Mining and Mineral Products | AF41: Non-Ferrous Metal Ore Mining | AH41: 127075 | AI41: 1 | AJ41: ,,,,,,,"Sandfire Scope 1 - Diesel (tCO2e)","123,967","108,769",14% 5,,,,,,,Group,,, | AK41: 207796 | AL41: 1 | AM41: 35,,,,,,,Scope 1 - Other (tCO2e),894,709,26% ,,,,,,,Scope 2 - Market-based (tCO2e),0,0,N/A ,,,,,,,Scope 2 - Location-based (tCO2e),"82,288","73,272",12% | AN41: 718487 | AO41: 0.95 | AP41: === Table 6 (page 51) === factors that are aligned with our company jurisdictional footprint. This has resulted in an increase in our disclosed Scope 3 GHG emissions.,, Processing of Sold Products (Category 10) and Purchased Goods and Services (Category 1) remain the most significant contributing,, | AQ41: 20 | AR41: 0.078668 | AS41: 0.010927
A42: SSG-AU | B42: Shaver Shop Group Ltd. | C42: Can't remember who but someone knows the owner of this in our cohort I think | R42: =IFERROR(_xlfn.XLOOKUP($A42,Profitability!$A$5:$A$342,Profitability!$Q$5:$Q$342),"na") | S42: =IFERROR(_xlfn.XLOOKUP($A42,Profitability!$A$5:$A$342,Profitability!$R$5:$R$342),"na") | T42: Public | U42: Australia | V42: 2011 | W42: 750 | X42: 218.59827 | Y42: Pacific | Z42: Victoria (VIC) | AA42: 146.0998 | AB42: Shaver Shop Group Ltd. engages in selling personal grooming products through their corporate and online stores. It offers oral care, hair care, massage, air treatment, and beauty products. The company was founded in 1986 and is headquartered in Chadstone, Australia. | AC42: General Health and Personal Care Retail | AD42: Health and Personal Care Retail | AE42: Food and Staples Retail | AF42: Mixed Health and Personal Care Stores | AQ42: 0 | AR42: 0.068269 | AS42: 0
A43: WOW-AU | B43: Woolworths Group Ltd. | C43: I think Gus knows someone here | P43: 378135 | Q43: 1266614 | R43: =IFERROR(_xlfn.XLOOKUP($A43,Profitability!$A$5:$A$342,Profitability!$Q$5:$Q$342),"na") | S43: =IFERROR(_xlfn.XLOOKUP($A43,Profitability!$A$5:$A$342,Profitability!$R$5:$R$342),"na") | T43: Public | U43: Australia | V43: 1924 | W43: 202000 | X43: 69077 | Y43: Pacific | Z43: New South Wales (NSW) | AA43: 33829.001 | AB43: Woolworths Group Ltd. engages in the operation of general merchandise consumer stores and supermarkets in Australia, New Zealand and India. It operates through the following segments: Australian Food, Australian B2B, New Zealand Food, Big W, and Other. The Australian Food segment is involved in procurement of food and related products for resale and provision of services to retail customers. The Australian B2B segment pertains to the procurement and distribution of food and related products for resale to other businesses and provision of supply chain services. The New Zealand Food segment refers to the procurement of food and drinks for resale and provision of services to retail and wholesale customers. The BIG W segment is focused on the procurement of discount general merchandise products for resale to retail customers. The Other segment is comprised of Quantium and MyDeal. The company was founded by Percy Christmas, Stanley Edward Chatterton, Cecil Scott Waine, George William Percival Creed, and Ernest Robert Williams on December 5, 1924, and is headquartered in Sydney, Australia. | AC43: Grocery Stores | AD43: Food and Beverage Retail | AE43: Food and Staples Retail | AF43: Supermarkets | AH43: 43300 | AI43: 0.9 | AJ43: ,,,,vs F23 base year, ,"43,300+",,,, ,,,N Z,, | AK43: 66800 | AL43: 0.9 | AM43: ,V I C,,,Our planet, ,,,"66,800+",, ,,,,,Our reach enables us to influence change across our value chain | AQ43: 13 | AR43: 0.013942 | AS43: 0.000188
A44: PPT-AU | B44: Perpetual Ltd. | C44: Patrick knows this firm I believe | M44: 2025 | N44: 50 | O44: 1310 | R44: =IFERROR(_xlfn.XLOOKUP($A44,Profitability!$A$5:$A$342,Profitability!$Q$5:$Q$342),"na") | S44: =IFERROR(_xlfn.XLOOKUP($A44,Profitability!$A$5:$A$342,Profitability!$R$5:$R$342),"na") | T44: Public | U44: Australia | V44: 1963 | W44: 1789 | X44: 1406.5 | Y44: Pacific | Z44: New South Wales (NSW) | AA44: 3417.8001 | AB44: Perpetual Ltd. operates as an independent financial services group, which provides investment management, wealth advice, and corporate fiduciary services to individuals, families, financial advisers, and institutions. It operates through the following segments: Asset Management, Wealth Management, and Corporate Trust. The Asset Management segment is a global multi-boutique asset management business. The Wealth Management segment includes Perpetual Private and other specialist businesses offering wealth management, advice, and trustee services. The Corporate Trust segment provides fiduciary and digital solutions to the banking and financial industry; and administers securitization portfolios, investment. and debt structures. The company was founded on September 28, 1886 and is headquartered in Sydney, Australia. | AC44: Asset Management and Financial Advisory Services | AD44: Investment Services | AE44: Investment Services | AF44: Diverse Asset Management and Financial Advisors | AH44: 50 | AI44: 1 | AJ44: offices (FY23 baseline),,, Reduce paper purchased for printing in Australian,,Failed to achieve 50% reduction of FY21 baseline. Commitment was de‑prioritised due to separation activities in advance of, ,,,page 17 | AK44: 1310 | AL44: 1 | AM44: "4. FY25 figures utilise the EVIC methodology and prior years used the Market Capitalisation as Fixed Income (corporate bonds) data was not readily available. As a result, the table has been re‑baselined to FY25.", 5.,"For total carbon emissions, Scope 1 and Scope 2 GHG emissions are calculated using an Enterprise Value including Cash as the denominator. This is calculated by combining the total debt and market capitalisation of a" ,"holding. Where no market capitalisation is available (non‑listed issuers), total debt only is used." | AN44: 15312 | AO44: 1 | AP44: Operational emissions,,Electricity (market-based),011,335,242 ,,Total Scope 3 operational emissions5,"15,156","19,672","22,120" "As a global business, Perpetual Group is committed to",,,,, | AQ44: 0 | AR44: -0.041379 | AS44: 0
A45: WZR-AU | B45: Wisr Ltd. | R45: =IFERROR(_xlfn.XLOOKUP($A45,Profitability!$A$5:$A$342,Profitability!$Q$5:$Q$342),"na") | S45: =IFERROR(_xlfn.XLOOKUP($A45,Profitability!$A$5:$A$342,Profitability!$R$5:$R$342),"na") | T45: Public | U45: Australia | V45: 1966 | W45: - | X45: 91.57011 | Y45: Pacific | Z45: New South Wales (NSW) | AA45: 871.40509 | AB45: Wisr Ltd. engages in the provision of writing personal loans and secured vehicle loans to consumers. The company was founded on May 2, 1966 and is headquartered in Sydney, Australia. | AC45: Consumer Finance Services | AD45: Specialty Finance | AE45: Specialty Finance and Services | AF45: Personal Loans | AR45: -0.079283
A46: NAB-AU | B46: National Australia Bank Ltd. | M46: 2024 | N46: 7313 | O46: 49565 | P46: 4329 | Q46: 47165 | R46: =IFERROR(_xlfn.XLOOKUP($A46,Profitability!$A$5:$A$342,Profitability!$Q$5:$Q$342),"na") | S46: =IFERROR(_xlfn.XLOOKUP($A46,Profitability!$A$5:$A$342,Profitability!$R$5:$R$342),"na") | T46: Public | U46: Australia | V46: 1893 | W46: 39240 | X46: 63168 | Y46: Pacific | Z46: Victoria (VIC) | AA46: 1080356 | AB46: National Australia Bank Ltd. engages in the provision of banking and financial services. Its services include banking, credit and access card facilities, leasing, housing and general finance, international banking, investment banking, wealth management, funds management and custodian, trustee and nominee services. It operates through the following segments: Business and Private Banking, Personal Banking, Corporate and Institutional Banking, New Zealand Banking, and Corporate Functions and Others. The Business and Private Banking segment focuses on priority small and medium (SME) customers. The Personal Banking segment provides banking products and services to customers. The Corporate and Institutional Banking segment includes client coverage, corporate finance, markets, asset servicing, transactional banking and enterprise payments. The New Zealand Banking segment focuses on banking and financial services across customer segments in New Zealand. The Corporate Functions and Other segment covers ubank and enabling units. The company was founded on October 4, 1858 and is headquartered in Melbourne, Australia. | AC46: Asia/Pacific Banks | AD46: International Banks | AE46: Banking | AF46: Australia and New Zealand Banks | AH46: 8359 | AJ46: 2025 Scope 1 emissions (tCO2-e). Note: This is the gross Scope 1 figure. | AK46: 0 | AM46: 2025 Scope 2 market-based emissions (tCO2-e). Market-based emissions are zero, reflecting 100% renewable electricity sourcing. | AN46: 78259 | AP46: 2025 Total gross Scope 3 emissions (tCO2-e). This excludes financed emissions. | AQ46: 22 | AR46: 0.107459 | AS46: 0.000348
A47: ANN-AU | B47: Ansell Ltd. | M47: 2025 | N47: 181558 | O47: 46346 | R47: =IFERROR(_xlfn.XLOOKUP($A47,Profitability!$A$5:$A$342,Profitability!$Q$5:$Q$342),"na") | S47: =IFERROR(_xlfn.XLOOKUP($A47,Profitability!$A$5:$A$342,Profitability!$R$5:$R$342),"na") | T47: Public | U47: Australia | V47: 1893 | W47: 15724 | X47: 3093.2738 | Y47: Pacific | Z47: Victoria (VIC) | AA47: 5069.6576 | AB47: Ansell Ltd. engages in the development, manufacture, distribution, and sale of gloves and protective personal equipment in the industrial and medical end markets. It operates through the Healthcare and Industrial segment. The Healthcare segment includes surgical and examination gloves, healthcare safety devices, and active infection prevention products for healthcare patients and single use industrial application gloves. The Industrial segment provides multi-use hand and body protection solutions for industrial worker environments and specialty applications. The company was founded in 1893 and is headquartered in Richmond, Australia. | AC47: Medical Supplies | AD47: Other Medical Devices | AE47: Healthcare Equipment | AF47: Safety and Sterilization Medical Supplies | AH47: 181558 | AJ47: FY25 Scope 1 emissions | AK47: 46346 | AM47: FY25 Scope 2 emissions (market based) | AN47: 798935 | AP47: FY24 Scope 3 emissions. Current year (FY25) Scope 3 data is reported a year in arrears. | AQ47: 1 | AR47: 0.050716 | AS47: 0.000323
A48: ATP-AU | B48: Atlas Pearls Ltd. | M48: 2025 | N48: Scope 1 + 2 | O48: 4937 | R48: =IFERROR(_xlfn.XLOOKUP($A48,Profitability!$A$5:$A$342,Profitability!$Q$5:$Q$342),"na") | S48: =IFERROR(_xlfn.XLOOKUP($A48,Profitability!$A$5:$A$342,Profitability!$R$5:$R$342),"na") | T48: Public | U48: Australia | V48: 1987 | W48: 1200 | X48: 44.271016 | Y48: Pacific | Z48: Western Australia (WA) | AA48: 85.885515 | AB48: Atlas Pearls Ltd. produces white & silver South Sea pearls and farming operations in Indonesia. It operates through the Australia and Indonesia segments. The company was founded in 1992 and is headquartered in Perth, Australia. | AC48: Accessories Production | AD48: Apparel and Accessory Products | AE48: Consumer Goods | AF48: Jewelry and Other Accessories Production | AQ48: 0 | AR48: 0.49463 | AS48: 0
A49: ORG-AU | B49: Origin Energy Ltd. | P49: 15563946 | Q49: 2200940 | R49: =IFERROR(_xlfn.XLOOKUP($A49,Profitability!$A$5:$A$342,Profitability!$Q$5:$Q$342),"na") | S49: =IFERROR(_xlfn.XLOOKUP($A49,Profitability!$A$5:$A$342,Profitability!$R$5:$R$342),"na") | T49: Public | U49: Australia | V49: 1946 | W49: 5000 | X49: 17118 | Y49: Pacific | Z49: New South Wales (NSW) | AA49: 20989.001 | AB49: Origin Energy Ltd. is an integrated energy company, which engages in exploration and production of natural gas, electricity generation, wholesale and retail sale of electricity and gas, and sale of liquefied natural gas. It operates through the following business segments: Energy Markets, Share of Octopus Energy, Integrated Gas, and Corporate. The Energy Markets segment includes energy retailing, power generation and liquid petroleum gas operations. The Share of Octopus Energy segment focuses on the Origin’s investment in Octopus Energy Group Limited (Octopus Energy). The Integrated Gas segment engages in growth assets business and management of LNG price risk through hedging and trading activities. The Corporate segment includes various business development and support activities that are not allocated to operating segments. The company was founded on March 4, 1946 and is headquartered in Sydney, Australia. | AC49: Asia/Pacific Wholesale Power | AD49: Energy Utilities | AE49: Utilities | AF49: Other Asia/Pacific Wholesale Power | AH49: 16044000 | AI49: 1 | AJ49: Why it’s important,"is not linear. Our total Scope 1, 2 and 3 equity emissions for FY25 was 45.1 Mt CO2-e, largely consistent with FY24." ,"Emissions from Eraring made up 84 per cent of our total Scope 1 equity emissions of 16.0 Mt CO2-e, with Scope 1" "As a leading energy company in Australia, the energy transition is core to our","and 2 emissions up due to slightly higher generation output at our other generating sites. Scope 3 emissions, which" | AK49: 876000 | AL49: 1 | AM49: ,,baseline for FY25.,,,,,,,, ,,,Scope 1,,Scope 2,,Flaring,Venting,, | AN49: 28135000 | AO49: 1 | AP49: ,"4,262","4,436","4,483","4,591","4,695","we operate (including those under exploration, projects" "('000) 1, 5",,,,,,not eventuate. Scenarios may also be impacted by ,,,,,,"in development or execution phases, sites and closed" | AQ49: 10 | AR49: 0.086517 | AS49: 0.000584
A50: TAH-AU | B50: Tabcorp Holdings Ltd. | M50: 2025 | N50: Scope 1 + 2 | O50: 14602 | R50: =IFERROR(_xlfn.XLOOKUP($A50,Profitability!$A$5:$A$342,Profitability!$Q$5:$Q$342),"na") | S50: =IFERROR(_xlfn.XLOOKUP($A50,Profitability!$A$5:$A$342,Profitability!$R$5:$R$342),"na") | T50: Public | U50: Australia | V50: 1994 | W50: - | X50: 2151.5 | Y50: Pacific | Z50: Victoria (VIC) | AA50: 3140.2001 | AB50: Tabcorp Holdings Ltd. engages in the provision of entertainment services. It operates through the Wagering and Media, and Gaming Services segments. The Wagering and Media segment includes totalizator and fixed odds betting, retail wagering networks, and global racing media business. The Gaming Services segment provides regulatory monitoring and related services. The company was founded on April 13, 1994 and is headquartered in Melbourne, Australia. | AC50: Arts, Entertainment and Recreation Providers | AD50: Hospitality Services | AE50: Hospitality Services | AF50: Gaming Industries | AH50: 3108 | AI50: 1 | AJ50: and targets sections.,,,, ,how much and how quickly they,2019 levels,"Scope 1, 2 and 3 GHG emissions",set their own science-based ,need to reduce their GHG,,reduction targets. These,targets. While this is not a small | AK50: 11493 | AL50: 1 | AM50: ,, Company specific definitions that are publicly disclosed. Total scope 2 greenhouse gas emissions (tCO2-e),"11,493", ,,Key responsibilities | AN50: 57223 | AO50: 1 | AP50: emissions baseline to remove,,,, ,"were 57,223 tonnes CO2e, a",Scope 3 – 79.7%,, those emissions related to our,,,, | AQ50: 15 | AR50: 0.017011 | AS50: 0.006972
A51: CSL-AU | B51: CSL Ltd. | M51: 2025 | N51: 135000 | O51: 151000 | P51: 27439 | Q51: 76717 | R51: =IFERROR(_xlfn.XLOOKUP($A51,Profitability!$A$5:$A$342,Profitability!$Q$5:$Q$342),"na") | S51: =IFERROR(_xlfn.XLOOKUP($A51,Profitability!$A$5:$A$342,Profitability!$R$5:$R$342),"na") | T51: Public | U51: Australia | V51: 1961 | W51: 29000 | X51: 23825.296 | Y51: Pacific | Z51: Victoria (VIC) | AA51: 60126.651 | AB51: CSL Ltd. is a biopharmaceutical company, which engages in the manufacture, marketing, and distribution of biopharmaceutical and allied products. It operates through the following segments: CSL Behring, CSL Seqirus, and CSL Vifor. The CSL Behring segment provides plasma products, gene therapies, and recombinants. The CSL Seqirus segment includes predominantly influenza related products and provides pandemic services to governments. The CSL Vidor segment focuses on the distribution of products in the therapeutic areas of iron deficiency and nephrology. The company was founded on November 2, 1961 and is headquartered in Melbourne, Australia. | AC51: Diversified Biopharmaceuticals | AD51: Other Biopharmaceuticals | AE51: Biopharmaceuticals | AF51: Diversified Biopharmaceuticals | AH51: 135000 | AI51: 0.9 | AJ51: Product safety and quality,Critical ﬁndings in Plasma and Manufacturing,, ,regulatory inspections that prevent the release,#,0 ,of commercial product,, | AK51: 151000 | AL51: 0.9 | AM51: Product safety and quality,Critical ﬁndings in Plasma and Manufacturing,, ,regulatory inspections that prevent the release,#,0 ,of commercial product,, | AN51: 0 | AQ51: 0 | AR51: 0.194556 | AS51: 0
A52: CDA-AU | B52: Codan Ltd. | M52: 2025 | N52: 456 | O52: 1261 | R52: =IFERROR(_xlfn.XLOOKUP($A52,Profitability!$A$5:$A$342,Profitability!$Q$5:$Q$342),"na") | S52: =IFERROR(_xlfn.XLOOKUP($A52,Profitability!$A$5:$A$342,Profitability!$R$5:$R$342),"na") | T52: Public | U52: Australia | V52: 1959 | W52: 1000 | X52: 674.226 | Y52: Pacific | Z52: South Australia (SA) | AA52: 904.80502 | AB52: Codan Ltd. engages in the provision of electronic solutions, focusing on metal detection and communications technology. It operates through the following segments: Communications, Metal Detection, and Other. The Communications segment includes the design, development, manufacture, and marketing of communications equipment. The Metal Detection segment focuses on the designs, development, manufacture, and marketing of metal detection equipment. The Other segment refers to the tracking solutions business and the ongoing manufacturing and sale of tracking products. The company was founded by Alastair Wood, Ian Baker Wall, and Jim Irvine Bettison on July 1, 1959, and is headquartered in Mawson Lakes, Australia. | AC52: Other Communications Equipment | AD52: Communications Equipment | AE52: Hardware | AF52: Other Wireless Equipment | AH52: 1485 | AJ52: FY24 Scope 1 emissions (tCO2-e) | AK52: 1037 | AM52: FY24 Scope 2 emissions (tCO2-e) | AN52: 51835 | AP52: FY24 Scope 3 emissions (tCO2-e) | AQ52: 2 | AR52: 0.153499 | AS52: 0.002966
A53: OBL-AU | B53: Omni Bridgeway Ltd. | R53: =IFERROR(_xlfn.XLOOKUP($A53,Profitability!$A$5:$A$342,Profitability!$Q$5:$Q$342),"na") | S53: =IFERROR(_xlfn.XLOOKUP($A53,Profitability!$A$5:$A$342,Profitability!$R$5:$R$342),"na") | T53: Public | U53: Australia | V53: 1986 | W53: 167 | X53: 54.986 | Y53: Pacific | Z53: New South Wales (NSW) | AA53: 1191.955 | AB53: Omni Bridgeway Ltd. engages in the investigation, management, and funding of litigation and arbitration claims. It operates through the following geographical segments: Americas, APAC, EMEA, and Corporate. The Americas segment focuses on the investment management business operating in America, Canada, and Latin America. The APAC segment is involved in the investment management business operating in Australia, Asia, and New Zealand. The EMEA segment represents the investment management business operating in Europe, Middle East, and Africa. The company was founded in 1986 and is headquartered in Sydney, Australia. | AC53: Commercial Finance Services | AD53: Specialty Finance | AE53: Specialty Finance and Services | AF53: Diversified Loan Services | AQ53: 0 | AR53: 6.361565 | AS53: 0
A54: MOZ-AU | B54: Mosaic Brands Ltd. | R54: =IFERROR(_xlfn.XLOOKUP($A54,Profitability!$A$5:$A$342,Profitability!$Q$5:$Q$342),"na") | S54: =IFERROR(_xlfn.XLOOKUP($A54,Profitability!$A$5:$A$342,Profitability!$R$5:$R$342),"na") | T54: Public | U54: Australia | V54: 1987 | W54: - | X54: 505.7 | Y54: Pacific | Z54: New South Wales (NSW) | AA54: 317.09001 | AB54: Mosaic Brands Ltd. engages in the retail and sale of women's apparel and accessories. It offers classic and stylish contemporary fashion for woman under Noni B and Liz Jordan brand names. The company was founded by Alan A. Kindl in 1977 and is headquartered in Rosebery, Australia. | AC54: Apparel Retail | AD54: Apparel and Accessories Retail | AE54: Consumer Retail | AF54: Other Apparel Retail | AH54: 3300000 | AJ54: 2024 Scope 1 GHG (3.3 Million tonnes CO2e). | AK54: 1200000 | AM54: 2024 Scope 2 GHG (1.2 Million tonnes CO2e, assuming 'Tonnes CO2e' is a unit error in the source and refers to Millions for consistency with Scope 1). | AN54: 0 | AP54: No specific Scope 3 total found. | AQ54: 0 | AR54: 0.000526 | AS54: 0
A55: NST-AU | B55: Northern Star Resources Ltd. | P55: 750285 | Q55: 291511 | R55: =IFERROR(_xlfn.XLOOKUP($A55,Profitability!$A$5:$A$342,Profitability!$Q$5:$Q$342),"na") | S55: =IFERROR(_xlfn.XLOOKUP($A55,Profitability!$A$5:$A$342,Profitability!$R$5:$R$342),"na") | T55: Public | U55: Australia | V55: 2000 | W55: 8728 | X55: 6414.9 | Y55: Pacific | Z55: Western Australia (WA) | AA55: 21050.101 | AB55: Northern Star Resources Ltd. is a gold producer and exploration company. It operates through the following segments: KCGM, Kalgoorlie Operations, Carosue Dam, Pogo, Jundee, Thunderbox, and Exploration. The KCGM, Kalgoorlie Operations, Carosue Dam, Pogo, Jundee, and Thunderbox segments are involved in the mining and processing of gold. The Exploration segment focuses on the exploration and evaluation of gold mineralization. The company founded on May 12, 2000 and is headquartered in Subiaco, Australia. | AC55: Precious Metal Mining | AD55: Metal Ore Mining | AE55: Mining and Mineral Products | AF55: Asia/Pacific Gold Mining | AH55: 8368940 | AI55: 1 | AJ55: In our opinion, the total Scope 1 and Scope 2 Greenhouse Gas (GHG) emissions of 836,894 tCO2eq and 467,881 tCO2eq reported by Northern Star, | AK55: 4678810 | AL55: 1 | AM55: In our opinion, the total Scope 1 and Scope 2 Greenhouse Gas (GHG) emissions of 836,894 tCO2eq and 467,881 tCO2eq reported by Northern Star, | AN55: 836894000 | AO55: 0.95 | AP55: Reasonable Assurance Conclusion "In our opinion, the total Scope 1 and Scope 2 Greenhouse Gas (GHG) emissions of 836,894 tCO2eq and 467,881 tCO2eq reported by Northern Star," "along with the associated GHG emissions methods, assumptions, and estimation uncertainty within the scope of our reasonable assurance engagement," | AQ55: 0 | AR55: 0.208842 | AS55: 0
A56: EGG-AU | B56: Enero Group Ltd. | R56: =IFERROR(_xlfn.XLOOKUP($A56,Profitability!$A$5:$A$342,Profitability!$Q$5:$Q$342),"na") | S56: =IFERROR(_xlfn.XLOOKUP($A56,Profitability!$A$5:$A$342,Profitability!$R$5:$R$342),"na") | T56: Public | U56: Australia | V56: 2000 | W56: 600 | X56: 187.47 | Y56: Pacific | Z56: New South Wales (NSW) | AA56: 225.78501 | AB56: Enero Group Ltd. engages in integrated marketing and communication services. It operates through the Brand Transformation, and Creative Technology and Data segments. The Brand Transformation segment refers to human generated creative ideas to transform the way customers and stakeholders connect and engage with brands. The Creative Technology and Data segment is involved with high quality customer experience connected by technology and enabled by data. The company was founded on February 9, 2000, and is headquartered in Pyrmont, Australia. | AC56: Marketing and Advertising Services | AD56: Marketing and Printing Services | AE56: Business Services | AF56: Other Marketing and Advertising Services | AQ56: 0 | AR56: -0.039964 | AS56: 0
A57: AX1-AU | B57: Accent Group Ltd. | R57: =IFERROR(_xlfn.XLOOKUP($A57,Profitability!$A$5:$A$342,Profitability!$Q$5:$Q$342),"na") | S57: =IFERROR(_xlfn.XLOOKUP($A57,Profitability!$A$5:$A$342,Profitability!$R$5:$R$342),"na") | T57: Public | U57: Australia | V57: 2004 | W57: 8600 | X57: 1470.9674 | Y57: Pacific | Z57: Victoria (VIC) | AA57: 1257.8976 | AB57: Accent Group Ltd. operates as an investment holding company, which engages in the retail of performance and lifestyle footwear. It offers its products under the following brands: The Athlete's Foot, Platypus Shoes, Sneaker Lab, Hype DC, Skechers, Merrell, CAT, Vans, 4Workers, EXIE, Dr. Martens, Saucony, Timberland, Sperry, Palladium, Stance, Supra, Subtype, The Trybe, PIVOT, and Stylerunner. The company was founded by Michael Hapgood in 1966 and is headquartered in Melbourne, Australia. | AC57: Footwear Retail | AD57: Apparel and Accessories Retail | AE57: Consumer Retail | AF57: Footwear Stores | AR57: 0.0392
A58: INA-AU | B58: Ingenia Communities Group | R58: =IFERROR(_xlfn.XLOOKUP($A58,Profitability!$A$5:$A$342,Profitability!$Q$5:$Q$342),"na") | S58: =IFERROR(_xlfn.XLOOKUP($A58,Profitability!$A$5:$A$342,Profitability!$R$5:$R$342),"na") | T58: Public | U58: Australia | V58: 2003 | W58: - | X58: 518.174 | Y58: Pacific | Z58: New South Wales (NSW) | AA58: 2773.1501 | AB58: Ingenia Communities Group engages in managing and developing a portfolio of retirement and lifestyle communities. It operates through the following segments: Lifestyle Development; Lifestyle Rental; Ingenia Gardens; Holidays and Mixed Use; Fuel, Food, and Beverage Services; and Corporate and Other. The Lifestyle Development segment refers to the development and sale of lifestyle homes. The Lifestyle Rental segment relates to long-term accommodation within lifestyle and rental communities. The Ingenia Gardens is involved in rental villages. The Holidays and Mixed Use segment includes tourism and rental accommodation within holiday parks. The Fuel, Food, and Beverage Services segment focuses on its investment in service stations and food and beverage operations adjoined to Ingenia Holiday communities. The Corporate and Other segment covers its remaining assets and operating activities. The company was founded on November 22, 2003 and is headquartered in The Rocks, Australia. | AC58: Equity REITs | AD58: Real Estate Investment Trusts (REITs) | AE58: Real Estate | AF58: Equity REITs | AH58: 1409 | AI58: 1 | AJ58: Scope 1 Emissions (tCO2e),"1,409","1,494" | AK58: 12755 | AL58: 1 | AM58: Scope 2 Emissions (tCO2e),"12,755","13,130" | AN58: 7521 | AO58: 1 | AP58: Resident Emissions (tCO2e) - Scope 3 Emissions for Ingenia,"7,521","8,214" | AQ58: 17 | AR58: 0.247841 | AS58: 0.032808
A59: MMS-AU | B59: McMillan Shakespeare Ltd. | D59: Vishal | E59: Matthias Kehle | F59: Request message sent | R59: =IFERROR(_xlfn.XLOOKUP($A59,Profitability!$A$5:$A$342,Profitability!$Q$5:$Q$342),"na") | S59: =IFERROR(_xlfn.XLOOKUP($A59,Profitability!$A$5:$A$342,Profitability!$R$5:$R$342),"na") | T59: Public | U59: Australia | V59: 2003 | W59: 1311 | X59: 538.177 | Y59: Pacific | Z59: Victoria (VIC) | AA59: 1479.925 | AB59: McMillan Shakespeare Ltd. engages in salary packaging, novated leasing, disability plan management and support co-ordination, asset management and related financial products and services. It operates through the following segments: Group Remuneration Services, Asset Management, and Plan and Support Services. The Group Remuneration Services segment offers administrative services in respect of salary packaging and facilitates the settlement of motor vehicle novated leases for customers. The Asset Management segment offers financing and ancillary management services associated with motor vehicles, commercial vehicles, and equipment. The Plan and Support Services segment engages in the management and support coordination services to participants in the National Disability Insurance Scheme (NDIS). The company was founded by Anthony G. Podesta in 1988 and is headquartered in Melbourne, Australia. | AC59: Administrative Services | AD59: Other Professional Services | AE59: Business Services | AF59: Administrative Employment Services | AH59: 259 | AI59: 1 | AJ59: Scope 1 – Group (Net),CO2-e tonnes,149,207,164 | AK59: 591 | AL59: 1 | AM59: Scope 2 – Group (Net)11,CO2-e tonnes,144,143,16 | AN59: 0 | AQ59: 0 | AR59: 0.17799 | AS59: 0
A60: PPC-AU | B60: Peet Ltd. | R60: =IFERROR(_xlfn.XLOOKUP($A60,Profitability!$A$5:$A$342,Profitability!$Q$5:$Q$342),"na") | S60: =IFERROR(_xlfn.XLOOKUP($A60,Profitability!$A$5:$A$342,Profitability!$R$5:$R$342),"na") | T60: Public | U60: Australia | V60: 1905 | W60: 180 | X60: 414.785 | Y60: Pacific | Z60: Western Australia (WA) | AA60: 1111.716 | AB60: Peet Ltd. engages in the acquisition, development, and sale of residential land. It operates through the following segments: Funds Management, Company-owned Projects, Joint Arrangements, and Inter-segment Eliminations and Other Unallocated. The Funds Management segment offers equity funds towards the acquisition of land and is generally supplemented with debt funds. The Company-owned Projects segment acquires parcels of land in Australia, primarily for residential development purposes. The Joint Arrangements segment consists of government, statutory authorities, and private landowners. The Inter-segment Eliminations and Other Unallocated segment refers to the revenue, expenses, and results. The company was founded by James Thomas Peet in July 1895 and is headquartered in Perth, Australia. | AC60: Other Real Estate Investment and Services | AD60: Real Estate Investment and Services | AE60: Real Estate | AF60: Real Estate Developers | AR60: 0.140957
A61: PRU-AU | B61: Perseus Mining Ltd. | D61: Vishal | E61: Jordan Morrissey | F61: Request message sent | R61: =IFERROR(_xlfn.XLOOKUP($A61,Profitability!$A$5:$A$342,Profitability!$Q$5:$Q$342),"na") | S61: =IFERROR(_xlfn.XLOOKUP($A61,Profitability!$A$5:$A$342,Profitability!$R$5:$R$342),"na") | T61: Public | U61: Australia | V61: 2003 | W61: - | X61: 1927.1499 | Y61: Pacific | Z61: Western Australia (WA) | AA61: 3785.5452 | AB61: Perseus Mining Ltd. engages in production of gold, mineral exploration and gold project development. It operates through the following segments: Edikan, Sissingué, Yaouré, and Corporate & Other. The Edikan, Sissingué and Yaouré segments engages in mining, mineral exploration, evaluation and development activities. The Corporate & Other segment engages in investing activities and corporate management. The firm holds interest in Edikan Gold Mine, Sissingué Gold Mine, and Yaouré Gold Projects. The company was founded in 2004 and is headquartered in Subiaco, Australia. | AC61: Precious Metal Mining | AD61: Metal Ore Mining | AE61: Mining and Mineral Products | AF61: Other Gold Mining | AH61: 186110 | AJ61: FY2022 Total Scope 1 emissions (tCO2-e). | AK61: 86724 | AM61: FY2022 Total Scope 2 emissions (tCO2-e), calculated using the market-based method. | AN61: 472742 | AP61: FY2022 Total Scope 3 emissions (tCO2-e). | AR61: 0.29715
A62: EHL-AU | B62: Emeco Holdings Ltd. | R62: =IFERROR(_xlfn.XLOOKUP($A62,Profitability!$A$5:$A$342,Profitability!$Q$5:$Q$342),"na") | S62: =IFERROR(_xlfn.XLOOKUP($A62,Profitability!$A$5:$A$342,Profitability!$R$5:$R$342),"na") | T62: Public | U62: Australia | V62: 2004 | W62: 909 | X62: 785.354 | Y62: Pacific | Z62: Western Australia (WA) | AA62: 1247 | AB62: Emeco Holdings Ltd. engages in the provision of open cut, underground mining equipment rental, and providing complementary equipment and mining services, including maintenance, asset and component rebuilds, fleet optimization technology, and technical and engineering services. It operates through the following segments: Emeco Rental, Force Workshops, and Emeco Underground. The Emeco Rental segment provides earthmoving equipment solutions. The Force Workshops segment refers to the maintenance, equipment, and component rebuild services in Australia. The Emeco Underground segment focuses on the underground equipment rental services solutions and associated services in Australia. The company was founded in 1972 and is headquartered in Osborne Park, Australia. | AC62: Equipment and Supplies Distributors | AD62: Diversified Industrials Distribution | AE62: Industrial Services | AF62: Industrial Machinery and Supplies Distributors | AR62: 0.095677
A63: SEK-AU | B63: SEEK Ltd. | R63: =IFERROR(_xlfn.XLOOKUP($A63,Profitability!$A$5:$A$342,Profitability!$Q$5:$Q$342),"na") | S63: =IFERROR(_xlfn.XLOOKUP($A63,Profitability!$A$5:$A$342,Profitability!$R$5:$R$342),"na") | T63: Public | U63: Australia | V63: 1997 | W63: 3245 | X63: 1097 | Y63: Pacific | Z63: Victoria (VIC) | AA63: 4765.5001 | AB63: SEEK Ltd. engages in the provision of online matching of hires and candidates, and other related activities. It operates through the following segments: ANZ, SEEK Asia, Brasil Online, OCC, Platform Support, Corporate Costs, and Portfolio Investment. The ANZ, SEEK Asia, Brasil Online, and OCC segments refer to the online employment marketplace services. The Platform Support segment focuses on a portfolio of investments that complement and/or have synergies with its operating platform. The Corporate Costs segment supports its core business. The Portfolio Investment segment is involved in a portfolio of investments which are managed as standalone entities. The company was founded by Paul Moss Bassat, Andrew Reuven Bassat and Matthew Myer Rockman on September 17, 1997 and is headquartered in Cremorne, Australia. | AC63: Consumer Data and Services | AD63: Internet and Data Services | AE63: Software and Consulting | AF63: Information and News Content Providers and Sites | AH63: 166 | AJ63: FY2024 Scope 1 (1% of 16,570 tCO2e), including Continuing and Discontinued Operations. | AK63: 1326 | AM63: FY2024 Scope 2 (8% of 16,570 tCO2e), including Continuing and Discontinued Operations. | AN63: 15079 | AP63: FY2024 Scope 3 (91% of 16,570 tCO2e), including Continuing and Discontinued Operations. | AR63: 0.217229
A64: CWY-AU | B64: Cleanaway Waste Management Ltd. | R64: =IFERROR(_xlfn.XLOOKUP($A64,Profitability!$A$5:$A$342,Profitability!$Q$5:$Q$342),"na") | S64: =IFERROR(_xlfn.XLOOKUP($A64,Profitability!$A$5:$A$342,Profitability!$R$5:$R$342),"na") | T64: Public | U64: Australia | V64: 2002 | W64: 10000 | X64: 3788.9 | Y64: Pacific | Z64: Victoria (VIC) | AA64: 6578.2002 | AB64: Cleanaway Waste Management Ltd. engages in the provision of total waste management, industrial, and environmental services. It operates through the following segments: Solid Waste Services, ETS- Industrial Services, and ETS-Oils & Technical Services and Health Services. The Solid Waste Services segment includes the collection, recovery, and disposal of all types of solid waste, including putrescible waste, inert waste, household waste, and recovered waste. The ETS- Industrial Services segment consists of a variety of services provided to the Resources, Oil and Gas, Infrastructure, Industrial markets and also include Services include vacuum loading, high pressure cleaning, pipeline maintenance and non-destructive digging. The ETS-Oils & Technical Services and Health Services segment is involved in the collection, treatment, processing, refining and recycling, and destruction of hazardous and non-hazardous liquids, hydrocarbons and chemical waste, specialised product destruction, hazardous waste and e-waste, provision of services to the health sector for the safe treatment and disposal of health related waste which includes sharps management, medical waste, pharmaceutical waste, healthcare hazardous waste, and quarantine waste. The company was founded by Terrence Elmore Peabody in August 1987 and is headquartered in Melbourne, Australia. | AC64: General Waste Collection | AD64: Waste Management Services | AE64: Business Services | AF64: Diversified General Waste Collection | AH64: 1070000 | AI64: 0.9 | AJ64: CONTAINERS PROCESSED VIA CDS 1 224 kt | AK64: 52000 | AL64: 0.9 | AM64: Our net combined Scope 1 and 2 GHG emissions in FY25 were aligned with the 1.5oC net combined Scope 1 and 2 GHG target of 1,132kt CO2-e. | AN64: 484000 | AO64: 0.9 | AP64: decarbonisation. Our Scope 3 emissions were estimated at 484kt CO2-e, around 30% of our total footprint, with key contributors being fuel, transport, landfill use and | AQ64: 1 | AR64: 0.04141 | AS64: 0.000264
A65: CAJ-AU | B65: Capitol Health Ltd. | R65: =IFERROR(_xlfn.XLOOKUP($A65,Profitability!$A$5:$A$342,Profitability!$Q$5:$Q$342),"na") | S65: =IFERROR(_xlfn.XLOOKUP($A65,Profitability!$A$5:$A$342,Profitability!$R$5:$R$342),"na") | T65: Public | U65: Australia | V65: 2005 | W65: 1000 | X65: 234.816 | Y65: Pacific | Z65: Victoria (VIC) | AA65: 319.484 | AB65: Capitol Health Ltd. provides diagnostic imaging and related services. It provides general x-ray, magnetic resonance imaging, ultrasound, mammography, doppler, orthopantomogram, echocardiography, computer tomography, computed tomography angiography, cone beam computed tomography, nuclear medicine, bone densitomety, and fluoroscopy services. The company was founded by Andrew Duncan Harrison on December 1, 2005 and is headquartered in Docklands, Australia. | AC65: Ambulatory and Outpatient Diagnostic Patient Care | AD65: Patient Care | AE65: Healthcare Services | AF65: Other Ambulatory and Outpatient Diagnostic Care | AR65: -0.063254
A66: GOR-AU | B66: Gold Road Resources Ltd. | R66: =IFERROR(_xlfn.XLOOKUP($A66,Profitability!$A$5:$A$342,Profitability!$Q$5:$Q$342),"na") | S66: =IFERROR(_xlfn.XLOOKUP($A66,Profitability!$A$5:$A$342,Profitability!$R$5:$R$342),"na") | T66: Public | U66: Australia | V66: 2004 | W66: - | X66: 528.46 | Y66: Pacific | Z66: Western Australia (WA) | AA66: 1536.065 | AB66: Gold Road Resources Ltd. operates as a gold exploration company. It focuses on developing the Yamarna Belt comprising Gruyere, Central Bore and Attila projects. The firm operates through Development & Production and Exploration business segments. The Development & Production includes Gruyere joint operation with gold fields, which transitioned from development to production phase during the year. The Exploration segment includes the activities on all mineral exploration, including all joint venture tenements. The company was founded on May 28, 2004 and is headquartered in West Perth, Australia. | AC66: Precious Metal Mining | AD66: Metal Ore Mining | AE66: Mining and Mineral Products | AF66: Asia/Pacific Gold Mining | AH66: 800800 | AI66: 1 | AJ66: 287koz,8.81GJ/oz,287koz,3.80GJ/oz,331koz,5.52GJ/oz,229koz,4.08GJ/oz,267koz,7.26GJ/oz ,Scope 1 and 2,,Scope 1 and 2,,Scope 1 and 2,,Scope 1 and 2,,Scope 1 and 2 Renewable electricity,emissions,Renewable electricity,emissions,Renewable electricity,emissions,Renewable electricity,emissions,Renewable electricity,emissions | AK66: 831600 | AL66: 1 | AM66: Group carbon footprint: Scope 1 and 2 emissions (kt CO2e),,,,,,,,,,,,, ,,,,,Scope 1 emissions,,,,Scope 2 emissions,,,, ,,Diesel: haulage and,Diesel: power,,All other Scope 1,Total Scope 1,,Total Scope 1,Total Scope 2,Total Scope 2,Total Scope 1 and 2,,Total Scope 1 and 2 | AN66: 823000 | AO66: 1 | AP66: Decarbonisation,,,,,,,,,, •,Developed energy security,•,Set 2030 Scope 1 and 2 emissions,•,Re-baselined Scope 3 emissions,• Mid-point review of,•,Update reporting and visualisation,,• Maintain full visualisation of ,assessments and five-year,,targets,,and set target for a 10% net,Decarbonisation Strategy,•,Continue implementing,,energy in real time | AQ66: 7 | AR66: 0.270024 | AS66: 0.013246
A67: SVR-AU | B67: Solvar Ltd. | R67: =IFERROR(_xlfn.XLOOKUP($A67,Profitability!$A$5:$A$342,Profitability!$Q$5:$Q$342),"na") | S67: =IFERROR(_xlfn.XLOOKUP($A67,Profitability!$A$5:$A$342,Profitability!$R$5:$R$342),"na") | T67: Public | U67: Australia | V67: 2005 | W67: - | X67: 207.381 | Y67: Pacific | Z67: Victoria (VIC) | AA67: 961.58702 | AB67: Solvar Ltd. is a non-bank credit provider. It is focused on the provision of automotive finance in Australia and New Zealand. The firm engages in providing flexible secured and unsecured personal loans to customers often excluded by traditional lenders. The company was founded on November 25, 2005 and is headquartered in Bundoora, Australia. | AC67: Consumer Finance Services | AD67: Specialty Finance | AE67: Specialty Finance and Services | AF67: Automobile Financing | AR67: 0.151509
A68: HUM-AU | B68: Humm Group Ltd. | R68: =IFERROR(_xlfn.XLOOKUP($A68,Profitability!$A$5:$A$342,Profitability!$Q$5:$Q$342),"na") | S68: =IFERROR(_xlfn.XLOOKUP($A68,Profitability!$A$5:$A$342,Profitability!$R$5:$R$342),"na") | T68: Public | U68: Australia | V68: 2006 | W68: - | X68: 666.6 | Y68: Pacific | Z68: New South Wales (NSW) | AA68: 5338.3001 | AB68: Humm Group Ltd. operates as a financial services group, which engages in the financial products through a network of retailers and brokers. The firm's activities include a variety of financial risks, liquidity risk, funding risk, credit risk and market risk. It operates through the following segments: PosPP, New Zealand Cards, Australia Cards, and Commercial. The company was founded by David Berkman and Andrew Abercrombie in 1988 and is headquartered in Sydney, Australia. | AC68: Consumer Finance Services | AD68: Specialty Finance | AE68: Specialty Finance and Services | AF68: General Consumer Finance Services | AH68: 0 | AJ68: No Scope 1 emissions figure explicitly reported. The Company's GHG emission is limited to Scope 2 indirect and Scope 3 other indirect. | AK68: 291 | AM68: FY21 Scope 2: Electricity GHG emissions (tCO2e). | AN68: 216 | AP68: FY21 Scope 3: Travel GHG emissions (tCO2e). Currently, Scope 3 indirect emissions recorded are limited to travel. | AR68: 0.059406
A69: EGN-AU | B69: Engenco Ltd. | R69: =IFERROR(_xlfn.XLOOKUP($A69,Profitability!$A$5:$A$342,Profitability!$Q$5:$Q$342),"na") | S69: =IFERROR(_xlfn.XLOOKUP($A69,Profitability!$A$5:$A$342,Profitability!$R$5:$R$342),"na") | T69: Public | U69: Australia | V69: 2006 | W69: 500 | X69: 214.847 | Y69: Pacific | Z69: Victoria (VIC) | AA69: 190.496 | AB69: Engenco Ltd. engages in the provision of engineering services. It operates through the following business segments: Drivetrain, Convair, Gemco Rail, Workforce Solutions, and All Other. The Drivetrain segment is a provider of technical sales and services to the mining, oil & gas, rail, transport, defence, marine, construction, materials handling, automotive, agriculture, and power generation industries. The Convair segment is a manufacturer of bulk pneumatic road tankers and mobile silos for the carriage and storage of construction materials, grains, and other dry bulk materials. The Gemco Rail segment provides wheelset, bogie and in-field wagon maintenance and manufactures new and refurbished wagons, bogie component parts, remote controlled ballast car discharge gates, and a range of rail maintenance equipment and spares. The Workforce Solutions segment includes the people focused business, providing training and labour hire via its business units of Centre for Excellence in Rail Training, Total Momentum and Eureka 4WD Training. The All Other segment focuses on the parent entity, non-reportable segments and consolidation / inter-segment elimination adjustments. The company was founded in 1989 and is headquartered in Melbourne, Australia. | AC69: Commercial Transportation Equipment Manufacturing | AD69: Transportation Equipment Manufacturing | AE69: Industrial Manufacturing | AF69: Mixed Commercial Transportation Equipment Makers | AR69: 0.018292
A70: BCI-AU | B70: BCI Minerals Ltd. | D70: Vishal | E70: Nicholas Gajewski | F70: Request message sent | R70: =IFERROR(_xlfn.XLOOKUP($A70,Profitability!$A$5:$A$342,Profitability!$Q$5:$Q$342),"na") | S70: =IFERROR(_xlfn.XLOOKUP($A70,Profitability!$A$5:$A$342,Profitability!$R$5:$R$342),"na") | T70: Public | U70: Australia | V70: 2006 | W70: - | X70: 0 | Y70: Pacific | Z70: Western Australia (WA) | AA70: 1197.268 | AB70: BCI Minerals Ltd. is a mineral resources company, which engages in developing and industrial mineral business with salt and potash as its initial focus. It operates through the Mardie and Corporate and Other segments. The Mardie segment includes all activities related to the development and future operation of the Mardie Salt Operation and Potash Project which is the Group's principal project and primary focus of capital investment. The Corporate and Other segment focuses on the head office and corporate support functions, such as executive management, finance, legal, governance, and other administrative functions. The company was founded in 2006 and is headquartered in West Perth, Australia. | AC70: Nonmetallic Mineral Mining | AD70: Other Mining | AE70: Mining and Mineral Products | AF70: Other Nonmetallic Minerals Mining | AH70: 14183 | AI70: 1 | AJ70: Greenhouse and Energy Reporting (NGER), "requirements. BCI contributed 14,183 t", CO2-e (Scope 1) and 53 t CO2-e (Scope 2) for, | AK70: 53 | AL70: 1 | AM70: BCI contributed 53 t CO2-e (Scope 2) for FY24, which is below the NGER emissions reporting thresholds. | AN70: 0 | AO70: 0.95 | AP70: "requirements. BCI contributed 14,183 t", CO2-e (Scope 1) and 53 t CO2-e (Scope 2) for, "FY24, which is below the NGER emissions", | AQ70: 0
A71: GMD-AU | B71: Genesis Minerals Ltd. | P71: 110615 | Q71: 587 | R71: =IFERROR(_xlfn.XLOOKUP($A71,Profitability!$A$5:$A$342,Profitability!$Q$5:$Q$342),"na") | S71: =IFERROR(_xlfn.XLOOKUP($A71,Profitability!$A$5:$A$342,Profitability!$R$5:$R$342),"na") | T71: Public | U71: Australia | V71: 2007 | W71: - | X71: 920.141 | Y71: Pacific | Z71: Western Australia (WA) | AA71: 1797.922 | AB71: Genesis Minerals Ltd. engages in the exploration and development of gold deposits in Western Australia. Its projects include Leonora Gold and Barimaia Gold. The company was founded on April 16, 2007 and is headquartered in Perth, Australia. | AC71: Precious Metal Mining | AD71: Metal Ore Mining | AE71: Mining and Mineral Products | AF71: Asia/Pacific Gold Mining | AH71: 174700 | AI71: 1 | AJ71: 174.7kt CO -e2 | AK71: 1500 | AL71: 1 | AM71: 1.5kt CO -e2 | AN71: 0 | AO71: 0.95 | AP71: ,174.7kt CO -e2,1.5kt CO -e2 ,FY24: 110.6kt CO -e2,FY24: 0.6kt CO -e2 Genesis recognises that climate change is a pressing global issue. We are committed to,, | AQ71: 0 | AR71: 0.240368 | AS71: 0
A72: SRG-AU | B72: SRG Global Ltd. | R72: =IFERROR(_xlfn.XLOOKUP($A72,Profitability!$A$5:$A$342,Profitability!$Q$5:$Q$342),"na") | S72: =IFERROR(_xlfn.XLOOKUP($A72,Profitability!$A$5:$A$342,Profitability!$R$5:$R$342),"na") | T72: Public | U72: Australia | V72: 2003 | W72: - | X72: 1323.307 | Y72: Pacific | Z72: Western Australia (WA) | AA72: 881.08002 | AB72: SRG Global Ltd. engages in the provision of asset services on land. It operates through the following segments: Maintenance and Industrial Services, Engineering and Construction, and Corporate. The Maintenance and Industrial Services segment focuses on supplying integrated services to customers across the entire asset life cycle. The Engineering and Construction segment is involved in supplying integrated products and services to customers involved in the construction of complex infrastructure. The company was founded in 1961 and is headquartered in Subiaco, Australia. | AC72: Infrastructure Construction/Contracting Services | AD72: Facilities and Construction Services | AE72: Industrial Services | AF72: Diverse Construction and Engineering Services | AH72: 1341 | AJ72: FY25 Scope 1 emissions (tCO2-e). | AK72: 54937 | AM72: FY25 Market Based Scope 2 emissions (tCO2-e). | AN72: 0 | AP72: Scope 3 calculation figure is not able to be published this reporting period. | AR72: 0.035881
A73: SYR-AU | B73: Syrah Resources Ltd. | R73: =IFERROR(_xlfn.XLOOKUP($A73,Profitability!$A$5:$A$342,Profitability!$Q$5:$Q$342),"na") | S73: =IFERROR(_xlfn.XLOOKUP($A73,Profitability!$A$5:$A$342,Profitability!$R$5:$R$342),"na") | T73: Public | U73: Australia | V73: 2007 | W73: 615 | X73: 47.780541 | Y73: Pacific | Z73: Victoria (VIC) | AA73: 1117.8357 | AB73: Syrah Resources Ltd. is an industrial minerals and technology company. The firm operates through two segments: Balma and Corporate. The Balma segment includes mining, mineral exploration, evaluation and development activities associated with the Balama Graphite Project in Mozambique. The Corporate segment includes corporate administration and investing activities including development of the group's battery anode material strategy. Its projects includes Balma project, Sphercial Graphite Project, and Balama Vanadium Project. The company was founded on May 4, 2007 and is headquartered in Melbourne, Australia. | AC73: Nonmetallic Mineral Mining | AD73: Other Mining | AE73: Mining and Mineral Products | AF73: Other Nonmetallic Minerals Mining | AH73: 22024000 | AI73: 0.9 | AJ73: Q2 2024,"6,355",23,2.7,"40,000",,,,,10 Q3 2024,"1,264",0,N/A,,,,,, ,,,,0,,,,,0 | AK73: 0 | AL73: 0.9 | AM73: Q2 2024,"6,355",23,2.7,"40,000",,,,,10 Q3 2024,"1,264",0,N/A,,,,,, ,,,,0,,,,,0 | AN73: 1000 | AO73: 0.95 | AP73: === Table 1 (page 19) === ,Balama Graphite Operation,,,,,Greenhouse Gas Emissions - Scope 1 and Scope 2(3) Reporting,,, ,Scope 1 and 2 GHG Emissions,,,,,,,, | AQ73: 0 | AR73: -3.924229 | AS73: 0
A74: NHF-AU | B74: NIB Holdings Ltd. | R74: =IFERROR(_xlfn.XLOOKUP($A74,Profitability!$A$5:$A$342,Profitability!$Q$5:$Q$342),"na") | S74: =IFERROR(_xlfn.XLOOKUP($A74,Profitability!$A$5:$A$342,Profitability!$R$5:$R$342),"na") | T74: Public | U74: Australia | V74: 2007 | W74: - | X74: 3563.2 | Y74: Pacific | Z74: New South Wales (NSW) | AA74: 2187.2001 | AB74: NIB Holdings Ltd. engages in the provision of health and medical insurance. It operates through the following segments: Australian Residents Health Insurance, International (Inbound) Health Insurance, New Zealand Insurance, nib Travel, and nib Thrive. The Australian Residents Health Insurance segment offers product within the Australian private health insurance industry. The International (Inbound) Health Insurance segment includes health insurance products for international students and workers. The New Zealand Insurance segment consists of product for the New Zealand private health insurance industry. The nib Travel segment pertains to distribution of travel insurance products. The nib Thrive segment is involved in offering as a plan manager under the National Disability Insurance Scheme. The company was founded in 1952 and is headquartered in Newcastle, Australia. | AC74: Life and Health Insurance | AD74: Insurance | AE74: Insurance | AF74: Supplemental Health Insurance | AH74: 27 | AI74: 1 | AJ74: Scope 1,27.1,25.3 | AK74: 182 | AL74: 1 | AM74: Scope 22,182.3,202.3 | AN74: 14661 | AO74: 1 | AP74: Scope 3,"14,660.8","11,783.9" | AQ74: 3 | AR74: 0.054866 | AS74: 0.000842
A75: GEM-AU | B75: G8 Education Ltd. | R75: =IFERROR(_xlfn.XLOOKUP($A75,Profitability!$A$5:$A$342,Profitability!$Q$5:$Q$342),"na") | S75: =IFERROR(_xlfn.XLOOKUP($A75,Profitability!$A$5:$A$342,Profitability!$R$5:$R$342),"na") | T75: Public | U75: Australia | V75: 2007 | W75: 7099 | X75: 1015.268 | Y75: Pacific | Z75: Queensland (QLD) | AA75: 2068.3039 | AB75: G8 Education Ltd. engages in the provision of quality early childhood education and care. The firm is also involved in managing child care centres. The company was founded in 2006 and is headquartered in Gold Coast, Australia. | AC75: Educational Services | AD75: Personal Professional Services | AE75: Household Services | AF75: Other Educational Services | AH75: 667 | AI75: 1 | AJ75: Scope 1,"667,590 kg","756,899 kg","306,960 kg","351,762 kg" | AK75: 9360 | AL75: 1 | AM75: Scope 2,"9,360,624 kg","10,132,459 kg","11,761,701 kg","12,026,123 kg" | AQ75: 0 | AR75: 0.06667 | AS75: 0
A76: CKF-AU | B76: Collins Foods Ltd. | D76: Vishal | E76: Alexander Hill | F76: Request message sent | R76: =IFERROR(_xlfn.XLOOKUP($A76,Profitability!$A$5:$A$342,Profitability!$Q$5:$Q$342),"na") | S76: =IFERROR(_xlfn.XLOOKUP($A76,Profitability!$A$5:$A$342,Profitability!$R$5:$R$342),"na") | T76: Public | U76: Australia | V76: 2011 | W76: - | X76: 1519.2021 | Y76: Pacific | Z76: Queensland (QLD) | AA76: 1657.2225 | AB76: Collins Foods Ltd. engages in the operation of restaurants and food service retail outlets. It operates through the following business segments: KFC Restaurants Australia, KFC Restaurants Europe, Taco Bell Restaurants, and Other. The company was founded on June 10, 2011 and is headquartered in Hamilton, Australia. | AC76: Restaurants and Bars | AD76: Hospitality Services | AE76: Hospitality Services | AF76: Limited-Service and Fast Food Restaurants | AH76: 5849 | AI76: 1 | AJ76: (tonnes CO2-e),"62,153 6","7,977 6","70,130 6","62,508","6,813","69,321" Total Scope 1 and 2 emissions (tonnes CO2-e),"66,578 6","9,538 6","76,116 6","66,770","8,400","75,170" "Average emissions per ORE1,7 (tonnes CO2-e)2",221 6,131 6,203 6,215,111,195 | AK76: 69321 | AL76: 1 | AM76: FY24 methodology total Scope 2 emissions,,,,,, (tonnes CO2-e),"60,731","9,356","70,088",n/a,n/a,n/a Total location-based Scope 2 emissions,,,,,, | AN76: 0 | AQ76: 2 | AR76: 0.005814 | AS76: 0.001316
A77: WBC-AU | B77: Westpac Banking Corp. | P77: 4817 | Q77: 47775 | R77: =IFERROR(_xlfn.XLOOKUP($A77,Profitability!$A$5:$A$342,Profitability!$Q$5:$Q$342),"na") | S77: =IFERROR(_xlfn.XLOOKUP($A77,Profitability!$A$5:$A$342,Profitability!$R$5:$R$342),"na") | T77: Public | U77: Australia | V77: 2002 | W77: 35240 | X77: 57514 | Y77: Pacific | Z77: New South Wales (NSW) | AA77: 1078697 | AB77: Westpac Banking Corp. engages in the provision of banking and financial services. It operates through the following segments: Consumer, Business, Westpac Institutional Bank, Westpac New Zealand, Specialist Businesses and Group Businesses. The Consumer segment provides banking products, including mortgages, credit cards, personal loans, and savings and deposit products. The Business segment serves the banking needs of SME and commercial customers, including agribusiness and provides banking and advisory services to high net worth individuals through private wealth. The Westpac Institutional Bank segment provides a broad range of financial products and services to corporate, institutional and government customers. The Westpac New Zealand segment provides banking, wealth and insurance products and services for consumer, business and institutional customers in New Zealand. The Specialist Businesses segment comprises the operations that Westpac ultimately plans to exit with agreements in place for the sale of Westpac Life Insurance and motor vehicle dealer finance and notated leasing businesses. The Group Businesses segment includes the results of unallocated support functions such as treasury, chief operating office and core support. It also includes group-wide elimination entries arising on consolidation, centrally raised provisions and other unallocated revenue and expenses. The company was founded in 1817 and is headquartered in Sydney, Australia. | AC77: Asia/Pacific Banks | AD77: International Banks | AE77: Banking | AF77: Australia and New Zealand Banks | AH77: 4714 | AJ77: 2025 Scope 1 emissions (tCO2-e). | AK77: 1963 | AM77: 2025 Scope 2 emissions (tCO2-e) (market-based). | AN77: 56469 | AP77: 2025 Scope 3 upstream emissions only (tCO2-e). Financed emissions (Category 15) are calculated one year in arrears and are not included in this figure. | AR77: 0.120145
A78: CBA-AU | B78: Commonwealth Bank of Australia | P78: 4952 | Q78: 58505 | R78: =IFERROR(_xlfn.XLOOKUP($A78,Profitability!$A$5:$A$342,Profitability!$Q$5:$Q$342),"na") | S78: =IFERROR(_xlfn.XLOOKUP($A78,Profitability!$A$5:$A$342,Profitability!$R$5:$R$342),"na") | T78: Public | U78: Australia | V78: 1991 | W78: 51346 | X78: 69857 | Y78: Pacific | Z78: New South Wales (NSW) | AA78: 1353799 | AB78: Commonwealth Bank of Australia engages in the provision of banking and financial services. It operates through the following segments: Retail Banking Services, Business Banking, Institutional Banking and Markets, New Zealand, Corporate Centre and Other, and Wealth Management. The Retail Banking Services segment provides home loan, consumer finance, and retail deposit products and servicing to all retail bank customers and non-relationship managed small business customers. The Business Banking segment offers specialized banking services to relationship managed business and Agribusiness customers, private banking to high-net-worth individuals, and margin lending and trading through CommSec. The Institutional Banking and Markets segment serves the firm's major corporate, institutional, and government clients using a relationship management model based on industry expertise and insights. The New Zealand segment comprises of banking, funds management, and insurance businesses operating in New Zealand. The Corporate Centre and Other segments include support functions such as investor relations, group marketing and strategy, group governance, and group treasury. The Wealth Management segment includes the global asset management, platform administration, and financial advice and life and general insurance businesses of the Australian operations. The company was founded in 1911 and is headquartered in Sydney, Australia. | AC78: Asia/Pacific Banks | AD78: International Banks | AE78: Banking | AF78: Australia and New Zealand Banks | AH78: 29640 | AJ78: Reported as combined Scope 1 and 2 operational emissions (tCO2-e). | AK78: 29640 | AM78: Reported as combined Scope 1 and 2 operational emissions (tCO2-e). | AN78: 34288 | AP78: FY24 Scope 3 operational emissions (tCO2-e). | AR78: 0.145053
A79: AMP-AU | B79: AMP Ltd. | R79: =IFERROR(_xlfn.XLOOKUP($A79,Profitability!$A$5:$A$342,Profitability!$Q$5:$Q$342),"na") | S79: =IFERROR(_xlfn.XLOOKUP($A79,Profitability!$A$5:$A$342,Profitability!$R$5:$R$342),"na") | T79: Public | U79: Australia | V79: 1997 | W79: - | X79: 2679 | Y79: Pacific | Z79: New South Wales (NSW) | AA79: 33160.999 | AB79: AMP Ltd. engages in offering services in financial advice and superannuation, retirement income, banking, and investment products. It operates through the following segments: AMP Bank, Platforms, Superannuation & Investments, New Zealand Wealth Management, and Group. The AMP Bank segment offers residential mortgages, deposits, and transactional banking services. The Platforms segment provides superannuation, retirement, and investment solutions. The Superannuation & Investments segment market competitive super and pension solution across individual and corporate super through SignatureSuper. The New Zealand Wealth Management segment focuses on the wealth management solutions. The Group segment includes partnerships, costs not recovered from business units, investments income, and interest expense on corporate dept. The company was founded in 1849 and is headquartered in Sydney, Australia. | AC79: Asset Management and Financial Advisory Services | AD79: Investment Services | AE79: Investment Services | AF79: Diverse Asset Management and Financial Advisors | AH79: 531 | AI79: 1 | AJ79: ,,Gas Reporting Criteria’ inclusive of reporting boundaries "Auckland City Mission, Kindness Collective, RSA,",• Scope 1 greenhouse gases (‘GHG’) emissions of 26, ,,"for operational impact emissions, environmental" | AK79: 636 | AL79: 1 | AM79: • Scope 2 GHG emissions of 636 tCO2-e; | AN79: 3758 | AO79: 1 | AP79: • Selected scope 3 GHG emissions of 3,758 tCO2-e; | AQ79: 10 | AR79: 0.067189 | AS79: 0.003733
A80: DOW-AU | B80: Downer EDI Ltd. | P80: 184125 | Q80: 33816 | R80: =IFERROR(_xlfn.XLOOKUP($A80,Profitability!$A$5:$A$342,Profitability!$Q$5:$Q$342),"na") | S80: =IFERROR(_xlfn.XLOOKUP($A80,Profitability!$A$5:$A$342,Profitability!$R$5:$R$342),"na") | T80: Public | U80: Australia | V80: 1933 | W80: 26000 | X80: 10472.1 | Y80: Pacific | Z80: New South Wales (NSW) | AA80: 6773.9002 | AB80: Downer EDI Ltd. engages in the provision of integrated services. It operates through following business segments: Transport; Utilities; Facilities; Engineering, Construction, and Maintenance (EC&M); and Mining.. The Transport segment comprises the Group's road, rail infrastructure, bridge, airport and port businesses and provides a broad range of transport infrastructure services. The Utilities segment consists of the power, gas, water, renewable, energy and telecommunications businesses. The Facilities segment provides outsourced facility services to customers across a diverse range of industry sectors including: defense, education, government, healthcare, resources, leisure, and hospitality. The EC&M segment manages the design, engineering, construction, and maintenance services for greenfield and brownfield projects across a range of sectors and all stages of the project lifecycle. The Mining handles services across all stages of the mining lifecycle including: asset management; blasting services, explosive supply; civil projects; crushing; exploration drilling; mine closure and mine site rehabilitation; mobile plant maintenance; open cut mining; training and development for ATSI employees; tyre management; and underground mining. The company was founded in 1933 and is headquartered in North Ryde, Australia. | AC80: Infrastructure Construction/Contracting Services | AD80: Facilities and Construction Services | AE80: Industrial Services | AF80: Infrastructure Construction | AH80: 302151 | AJ80: Operational emissions—total Scope 1 and 2 (market based). Combined Scope 1 and 2 total. Operational emissions—total Scope 1 and 2 (market based). Citation(s): [39, 40] | AR80: 0.013054
A81: SUN-AU | B81: Suncorp Group Ltd. | R81: =IFERROR(_xlfn.XLOOKUP($A81,Profitability!$A$5:$A$342,Profitability!$Q$5:$Q$342),"na") | S81: =IFERROR(_xlfn.XLOOKUP($A81,Profitability!$A$5:$A$342,Profitability!$R$5:$R$342),"na") | T81: Public | U81: Australia | V81: 2010 | W81: 11500 | X81: 16848 | Y81: Pacific | Z81: Queensland (QLD) | AA81: 30364.001 | AB81: Suncorp Group Ltd. is a financial services company, which engages in the provision of banking, wealth, and insurance products and services. It operates through the following segments: Consumer Insurance, Commercial and Personal Injury, Suncorp New Zealand, and Corporate and Internal Reinsurance. The Consumer Insurance segment provides insurance products to customers in Australia including home and contents, motor, and boat. The Commercial and Personal Injury segment offers insurance products to customers in Australia including commercial motor, commercial property, marine, industrial special risks, public liability and professional indemnity, workers’ compensation and compulsory third party. The Suncorp New Zealand segment includes general and life insurance products to customers in New Zealand. The Corporate and Internal Reinsurance segment is involved in the business strategy activities and shared services. The company was founded in 1902 and is headquartered in Brisbane, Australia. | AC81: Property and Casualty Insurance | AD81: Insurance | AE81: Insurance | AF81: Personal Insurance | AH81: 1245 | AI81: 0.9 | AJ81: Scope 1,"1,731","1,419","1,324","1,245" | AK81: 718 | AL81: 0.9 | AM81: Scope 2 (location-based),"14,751","9,802","8,333","6,074" | AN81: 17964 | AO81: 0.9 | AP81: Upstream Scope 3 emissions3, 7",Metric,Total upstream Scope 3 emissions,tCO2-e,"15,980","19,551","17,9641" | AQ81: 2 | AR81: 0.092593 | AS81: 0.000119
A82: IAG-AU | B82: Insurance Australia Group Ltd. | R82: =IFERROR(_xlfn.XLOOKUP($A82,Profitability!$A$5:$A$342,Profitability!$Q$5:$Q$342),"na") | S82: =IFERROR(_xlfn.XLOOKUP($A82,Profitability!$A$5:$A$342,Profitability!$R$5:$R$342),"na") | T82: Public | U82: Australia | V82: 1999 | W82: - | X82: 17708 | Y82: Pacific | Z82: New South Wales (NSW) | AA82: 26309.001 | AB82: Insurance Australia Group Ltd. engages in underwriting of general insurance and related corporate services. It operates through the following business divisions: Retail Insurance Australia, Intermediated Insurance Australia, New Zealand, and Corporate and Other. The Retail Insurance Australia division provides personal lines, some commercial lines, and general insurance products sold to customers under the NRMA, SGIO, SGIC, the RACV in Victoria, as well as the CGU and Poncho brands. The Intermediated Insurance Australia division offers commercial lines, personal lines, and general insurance products sold to customers through intermediaries including brokers, authorized representatives, and distribution partners under the CGU and WFI brands. The New Zealand division deals with general insurance products underwritten in New Zealand. The Corporate and Other division represents other activities, including corporate services, capital management activity, shareholders’ funds investment activities, inward reinsurance from associates, investment in associates, and other businesses that offer products and services that are adjacent to IAG's insurance business. The company was founded in 1925 and is headquartered Sydney, Australia. | AC82: Property and Casualty Insurance | AD82: Insurance | AE82: Insurance | AF82: Personal Insurance | AH82: 6770 | AJ82: 2025 Scope 1 GHG Emissions (tCO2e). | AK82: 5429 | AM82: 2025 Scope 2 – Market based emissions (tCO2e). Market-based emissions are used in calculating Net GHG emissions. | AN82: 19383 | AP82: 2025 Total Scope 3 emissions (tCO2e). | AR82: 0.076745
A83: QBE-AU | B83: QBE Insurance Group Ltd. | R83: =IFERROR(_xlfn.XLOOKUP($A83,Profitability!$A$5:$A$342,Profitability!$Q$5:$Q$342),"na") | S83: =IFERROR(_xlfn.XLOOKUP($A83,Profitability!$A$5:$A$342,Profitability!$R$5:$R$342),"na") | T83: Public | U83: Australia | V83: 1886 | W83: 13479 | X83: 34596.775 | Y83: Pacific | Z83: New South Wales (NSW) | AA83: 72237.743 | AB83: QBE Insurance Group Ltd. engages in providing underwriting general insurance and reinsurance risks. It operates through the following geographical segments: North America, International, Australia Pacific, and Corporate and Other. The North America segment writes general insurance, re7insurance, and crop business in the United States. The International segment offers general insurance business in the United Kingdom, Europ, and Canada. The Australia Pacific segment underwrites general insurance risks throughout Australia, New Zealand, and the Pacific region. The Corporate and Other segment is involved in non-operating holding companies that do not form part pf the group’s insurance operations. The company was founded in October 1888 is headquartered in Sydney, Australia. | AC83: Property and Casualty Insurance | AD83: Insurance | AE83: Insurance | AF83: Commercial Insurance | AR83: 0.077958
A84: SGP-AU | B84: Stockland | R84: =IFERROR(_xlfn.XLOOKUP($A84,Profitability!$A$5:$A$342,Profitability!$Q$5:$Q$342),"na") | S84: =IFERROR(_xlfn.XLOOKUP($A84,Profitability!$A$5:$A$342,Profitability!$R$5:$R$342),"na") | T84: Public | U84: Australia | V84: 1952 | W84: 1674 | X84: 3131 | Y84: Pacific | Z84: New South Wales (NSW) | AA84: 17743 | AB84: Stockland engages in the business of real estate. It operates through the following segments: Development, Investment Management, and Other. The Development segment develops assets including residential properties, commercial properties and mixed-use assets. The Investment Management segment invests in and manages commercial properties and residential investment properties, manages capital investments, and earns management income for services performed. The company was founded by Ervin Graf in 1952 and is headquartered in Sydney, Australia. | AC84: Equity REITs | AD84: Real Estate Investment Trusts (REITs) | AE84: Real Estate | AF84: Equity REITs | AH84: 2155 | AI84: 1 | AJ84: Total Scope 1: 2,155tCO2-e (up 13%) | AK84: 32121 | AL84: 1 | AM84: Total Scope 2: 32,121tCO2-e (down 11%) | AQ84: 19 | AR84: 0.263813 | AS84: 0.006068
A85: HVN-AU | B85: Harvey Norman Holdings Ltd. | R85: =IFERROR(_xlfn.XLOOKUP($A85,Profitability!$A$5:$A$342,Profitability!$Q$5:$Q$342),"na") | S85: =IFERROR(_xlfn.XLOOKUP($A85,Profitability!$A$5:$A$342,Profitability!$R$5:$R$342),"na") | T85: Public | U85: Australia | V85: 1987 | W85: 6600 | X85: 4121.467 | Y85: Pacific | Z85: New South Wales (NSW) | AA85: 8373.2272 | AB85: Harvey Norman Holdings Ltd. engages in the retail, franchise, property, and digital enterprise business. It operates through the following segments: Franchising Operations, Retail-New Zealand, Retail-Singapore and Malaysia, Retail-Slovenia and Croatia, Retail-Ireland and Northern Ireland, Other Non-Franchised Retail, Retail Property, Retail Property Under Construction, Property Developments for Resale, Equity Investments, and Other. The company was founded by Gerald Harvey and Ian John Norman in October 1982 and is headquartered in Sydney, Australia. | AC85: Department Stores | AD85: General Merchandise Retail | AE85: Food and Staples Retail | AF85: Asia/Pacific Department Stores | AR85: 0.125687
A86: ALL-AU | B86: Aristocrat Leisure Ltd. | R86: =IFERROR(_xlfn.XLOOKUP($A86,Profitability!$A$5:$A$342,Profitability!$Q$5:$Q$342),"na") | S86: =IFERROR(_xlfn.XLOOKUP($A86,Profitability!$A$5:$A$342,Profitability!$R$5:$R$342),"na") | T86: Public | U86: Australia | V86: 1984 | W86: 8500 | X86: 6603.6 | Y86: Pacific | Z86: New South Wales (NSW) | AA86: 10303.4 | AB86: Aristocrat Leisure Ltd. is a global entertainment and gaming content creation company powered by technology. It offers offers a diverse range of products and services including electronic gaming machines, casino management systems, free-to-play mobile games and online real money games, that serve customers. The firm operates through the following segments: Aristocrat Gaming, Pixel United, and Aristocrat Interactive segments. The Aristocrat Gaming segment involves in the land-based gaming. The Aristocrat Interactive segment includes online real money gaming. The Pixel United segment includes mobile games. The company was founded in 1953 and is headquartered in Sydney, Australia. | AC86: Arts, Entertainment and Recreation Providers | AD86: Hospitality Services | AE86: Hospitality Services | AF86: Gaming Industries | AR86: 0.197377
A87: ORI-AU | B87: Orica Ltd. | D87: Vishal | E87: Germán Morales Baeza | F87: Request message sent | P87: 938397 | Q87: 141207 | R87: =IFERROR(_xlfn.XLOOKUP($A87,Profitability!$A$5:$A$342,Profitability!$Q$5:$Q$342),"na") | S87: =IFERROR(_xlfn.XLOOKUP($A87,Profitability!$A$5:$A$342,Profitability!$R$5:$R$342),"na") | T87: Public | U87: Australia | V87: 1874 | W87: 14000 | X87: 7662.8 | Y87: Pacific | Z87: Victoria (VIC) | AA87: 9792.6002 | AB87: Orica Ltd. engages in the provision of mining and infrastructure solutions. The firm is also involved in manufacturing and distribution of commercial explosives and blasting systems including technical services and solutions; mining and tunneling support systems to the mining and infrastructure markets; and various chemical products and services. It operates through the following segments: Australia, Pacific, and Asia (APA); North America; Latin America; Europe, Middle East, and Africa (EMEA); Digital Solutions; and Global Support. The company was founded in 1874 and is headquartered in Melbourne, Australia. | AC87: Additives Manufacturing | AD87: Specialty and Performance Chemicals | AE87: Chemical, Plastic and Rubber Materials | AF87: Manufacturing Additives Manufacturing | AH87: 1158000 | AJ87: FY2024 Global Scope 1 emissions (1,158 ktCO₂-e). | AK87: 139000 | AM87: FY2024 Global Scope 2 emissions (139 ktCO₂-e). | AN87: 7891000 | AP87: FY2024 Global Scope 3 emissions (7,891 ktCO₂-e). | AR87: 0.068461
A88: FLT-AU | B88: Flight Centre Travel Group Ltd. | R88: =IFERROR(_xlfn.XLOOKUP($A88,Profitability!$A$5:$A$342,Profitability!$Q$5:$Q$342),"na") | S88: =IFERROR(_xlfn.XLOOKUP($A88,Profitability!$A$5:$A$342,Profitability!$R$5:$R$342),"na") | T88: Public | U88: Australia | V88: 1987 | W88: 12411 | X88: 2783.944 | Y88: Pacific | Z88: Queensland (QLD) | AA88: 4222.6711 | AB88: Flight Centre Travel Group Ltd. is engaged in providing travel retailing, wholesaling and corporate travel management services. It also engages in in-destination travel experience businesses including tour operators, hotel management, destination management companies and wholesaling. The company was founded by William James, Chris Greive, Graham Francis Turner and Geoff L. Harris in 1982 and is headquartered in South Brisbane, Australia. | AC88: Travel Arrangement and Reservation Services | AD88: Hospitality Services | AE88: Hospitality Services | AF88: Travel Agencies | AH88: 22554 | AI88: 1 | AJ88: Scope 1 – Where activity data was available emissions were calculated on this basis. | AK88: 9324 | AL88: 1 | AM88: Scope 2 – Calculations were made where metered energy consumption billing data was available. | AN88: 181919 | AO88: 1 | AP88: === Table 7 (page 55) === Graph 1. FY19 and FY23 FLT carbon footprint (excluding scope 3 category 11) (‘000 tCO2e emissions)15,,,,,,, 350,,,,,,, | AQ88: 40 | AR88: 0.039329 | AS88: 0.014368
A89: TCL-AU | B89: Transurban Group Ltd. | R89: =IFERROR(_xlfn.XLOOKUP($A89,Profitability!$A$5:$A$342,Profitability!$Q$5:$Q$342),"na") | S89: =IFERROR(_xlfn.XLOOKUP($A89,Profitability!$A$5:$A$342,Profitability!$R$5:$R$342),"na") | T89: Public | U89: Australia | V89: 1996 | W89: 8200 | X89: 3942 | Y89: Pacific | Z89: Victoria (VIC) | AA89: 36851.001 | AB89: Transurban Group Ltd. engages in the development, operation, and maintenance of toll roads. It operates through the following geographical segments: Melbourne, Sydney, Brisbane, North America, and Corporate and Other. The company was founded in 1996 and is headquartered in Docklands, Australia. | AC89: Road and Rail Transportation Operators | AD89: Cargo Transportation and Infrastructure Services | AE89: Industrial Services | AF89: Road Transportation | AH89: 5910 | AJ89: Total Scope 1 greenhouse gas emissions (5,910 tCO2-e) for FY24. | AK89: 30669 | AM89: Total scope 2 greenhouse gas emissions (“market-based”) (30,669 tCO2-e) for FY24. | AN89: 370826 | AP89: Total Scope 3 greenhouse gas emissions (370,826 tCO2-e) for FY24. | AR89: 0.033739
A90: A1N-AU | B90: ARN Media Ltd. | R90: =IFERROR(_xlfn.XLOOKUP($A90,Profitability!$A$5:$A$342,Profitability!$Q$5:$Q$342),"na") | S90: =IFERROR(_xlfn.XLOOKUP($A90,Profitability!$A$5:$A$342,Profitability!$R$5:$R$342),"na") | T90: Public | U90: Australia | V90: 1988 | W90: - | X90: 365.648 | Y90: Pacific | Z90: New South Wales (NSW) | AA90: 907.04097 | AB90: ARN Media Ltd. is a media and entertainment company. It operates through the following business segments: Australian Radio Network, HK outdoor and Digital Investments. The Australian Radio Network segment involves in Metropolitan radio networks. The HK Outdoor segment engages in billboard, transit and other outdoor advertising activities in Hong Kong. The Digital Investments segment includes interest on conversant media, emotive and equity accounted investments. The company was founded in 1988 and is headquartered in Macquarie Park, Australia. | AC90: Broadcast Media Services | AD90: Media and Publishing Services | AE90: Media and Publishing Services | AF90: Radio and Television Broadcasting | AR90: 0.010554
A91: SOL-AU | B91: Washington H. Soul Pattinson & Co. Ltd. | R91: =IFERROR(_xlfn.XLOOKUP($A91,Profitability!$A$5:$A$342,Profitability!$Q$5:$Q$342),"na") | S91: =IFERROR(_xlfn.XLOOKUP($A91,Profitability!$A$5:$A$342,Profitability!$R$5:$R$342),"na") | T91: Public | U91: Australia | V91: 1903 | W91: 51 | X91: 557.6 | Y91: Pacific | Z91: New South Wales (NSW) | AA91: 10397.7 | AB91: Washington H. Soul Pattinson & Co. Ltd. engages in the ownership of shares, coal mining, distribution and retail of pharmaceutical products, and manufacture of building products. It operates through the following segments: Strategic Portfolio, Large Caps Portfolio, Private Equity Portfolio, Credit Portfolio, Emerging Companies Portfolio, and Property Portfolio. The Strategic Portfolio segment focuses on significant investments in largely uncorrelated listed companies, generally with board representation. The Large Caps Portfolio segment is involved in listed equities generating consistent income and capital growth over the long term. The Private Equity Portfolio segment includes long-term investments in unlisted companies to support their future growth. The Credit Portfolio segment refers to the investments in different types of credit related financial instruments across an investee's capital structure aimed at optimizing the portfolio's risk adjusted returns. The Emerging Companies Portfolio segment represents the exposure to faster growing companies often benefitting from structural changes and trends in the domestic and global economy. The Property Portfolio segment managed Australian property investments as well as investments in property development joint ventures. The company was founded by Caleb Soul in 1872 and is headquartered in Sydney, Australia. | AC91: Investment Holding Companies | AD91: Investment Services | AE91: Investment Services | AF91: Investment Company | AH91: 8373 | AJ91: FY24 Scope 1 emissions for Controlled investments (tCO2e). | AK91: 18595 | AM91: FY24 Scope 2 emissions for Controlled investments (tCO2e). Note: Direct operations Scope 2 emissions are zero using a market-based approach. | AN91: 0 | AP91: No specific Scope 3 total found. | AR91: 0.653156
A92: ASX-AU | B92: ASX Ltd. | R92: =IFERROR(_xlfn.XLOOKUP($A92,Profitability!$A$5:$A$342,Profitability!$Q$5:$Q$342),"na") | S92: =IFERROR(_xlfn.XLOOKUP($A92,Profitability!$A$5:$A$342,Profitability!$R$5:$R$342),"na") | T92: Public | U92: Australia | V92: 2009 | W92: 1331 | X92: 1712.1 | Y92: Pacific | Z92: New South Wales (NSW) | AA92: 17569.4 | AB92: ASX Ltd. engages in operating a securities exchange. Its products and services include listing and issuer services, trading venue; clearing and settlement activities, exchange-traded and over-the-counter products, and information and technical services. The company was founded in April 1987 and is headquartered in Sydney, Australia. | AC92: Securities Sales and Trading Services | AD92: Investment Services | AE92: Investment Services | AF92: Other Securities Sales and Trading Services | AH92: 1000 | AI92: 1 | AJ92: Scope 1 – diesel and gas,37,34 | AK92: 1000 | AL92: 1 | AM92: Scope 1 – diesel and gas,37 Scope 2 – electricity,60 Market-based GHG emissions by activity (t CO2-e), | AN92: 1592 | AO92: 1 | AP92: ,,emissions after purchase "c. ASX’s gross emissions reduced by 3% in FY25 for Scope 1, Scope 2 and Scope 3 emissions compared",, ,to our FY21 base year.,and surrender of offsets | AQ92: 13 | AR92: 0.293558 | AS92: 0.007593
A93: SHL-AU | B93: Sonic Healthcare Ltd. | P93: 7415 | Q93: 49650 | R93: =IFERROR(_xlfn.XLOOKUP($A93,Profitability!$A$5:$A$342,Profitability!$Q$5:$Q$342),"na") | S93: =IFERROR(_xlfn.XLOOKUP($A93,Profitability!$A$5:$A$342,Profitability!$R$5:$R$342),"na") | T93: Public | U93: Australia | V93: 1934 | W93: - | X93: 9494.304 | Y93: Pacific | Z93: New South Wales (NSW) | AA93: 16053.918 | AB93: Sonic Healthcare Ltd. engages in the provision of medical diagnostics services. It operates through the following segments: Laboratory, Radiology, and Other. The Laboratory segment offers pathology and clinical services. The Radiology segment is involved in diagnostic imaging services in Australia. The Other segment refers to the corporate office function, medical center operations and occupation health services, and other minor operations. The company was founded on September 25, 1934, and is headquartered in Sydney, Australia. | AC93: Ambulatory and Outpatient Diagnostic Patient Care | AD93: Patient Care | AE93: Healthcare Services | AF93: Clinical Laboratory Patient Diagnostics | AH93: 29908 | AJ93: FY2025 Total global Scope 1 emissions (tCO2-e). | AK93: 58507 | AM93: FY2025 Scope 2 emissions (market-based) (tCO2-e). | AN93: 323506 | AP93: FY2025 Total global Scope 3 (GHG protocol categories 1–9) emissions (tCO2-e). | AR93: 0.054095
A94: DNL-AU | B94: Dyno Nobel Ltd. | R94: =IFERROR(_xlfn.XLOOKUP($A94,Profitability!$A$5:$A$342,Profitability!$Q$5:$Q$342),"na") | S94: =IFERROR(_xlfn.XLOOKUP($A94,Profitability!$A$5:$A$342,Profitability!$R$5:$R$342),"na") | T94: Public | U94: Australia | V94: 1919 | W94: 5600 | X94: 5278.5 | Y94: Pacific | Z94: Victoria (VIC) | AA94: 8398.4001 | AB94: Dyno Nobel Ltd. engages in manufacturing and selling of explosives, fertilisers and industrial chemicals. The company operates through businesses: Asia Pacific, Americas, and Corporate. The Asia Pacific business operates through five segments: Incitec Pivot Fertilisers, Southern Cross International, Fertilisers Elimination, Dyno Nobel Asia Pacific and Asia Pacific Eliminations. The Incitec Pivot Fertilisers segment manufactures and distributes fertilisers in Eastern Australia. The Southern Cross International segment manufactures ammonium phosphates and distributes its manufactured fertilizer products to wholesalers in Australia. The Fertilisers Elimination segment represents the elimination of sales and profit in stock arising from the sale of SCI manufactured products. The Dyno Nobel Asia Pacific segment manufactures and sells industrial explosives and related products and services to the mining industry in the Asia Pacific region and Turkey. The Asia Pacific Eliminations segment represents elimination of sales and profit in stock arising from IPF and SCI sales to DNAP at an arm’s length transfer price. The America business operates through Dyno Nobel Americas segment, which manufactures and sells industrial explosives and related products and services to the mining, quarrying and construction industries in the Americas. The Corporate segment operates through Group Eliminations segment, which represents elimination of sales and profit in stock arising from intersegment sales at an arm's length transfer price. The company was founded in 2003 and is headquartered in Melbourne, Australia. | AC94: Additives Manufacturing | AD94: Specialty and Performance Chemicals | AE94: Chemical, Plastic and Rubber Materials | AF94: Manufacturing Additives Manufacturing | AR94: 0.027887
A95: CPU-AU | B95: Computershare Ltd. | R95: =IFERROR(_xlfn.XLOOKUP($A95,Profitability!$A$5:$A$342,Profitability!$Q$5:$Q$342),"na") | S95: =IFERROR(_xlfn.XLOOKUP($A95,Profitability!$A$5:$A$342,Profitability!$R$5:$R$342),"na") | T95: Public | U95: Australia | V95: 1978 | W95: - | X95: 4732.9761 | Y95: Pacific | Z95: Victoria (VIC) | AA95: 8141.3415 | AB95: Computershare Ltd. engages in the provision of investor services, plan services, communication services, business services, stakeholder relationship management services, and technology services. It operates through the following segments: Issuer Services, Global Corporate Trust, Employee Share Plans and Voucher Services, Mortgage Services and Property Rental Services, Communication Services and Utilities, Business Services, and Technology Services and Operations. The Issuer Services segment comprises register maintenance, corporate actions, stakeholder relationship management, corporate governance and related services. The Global Corporate Trust segment refers to the trust and agency services in connection with the administration of debt securities in the US. The Employee Share Plans and Voucher Services segment is involved in the administration and related services for employee share and option plans, together with Childcare Voucher administration in the UK. The Mortgage Services and Property Rental Services segment provides mortgage servicing and related activities, together with tenancy bond protection services in the UK. The Communication Services and Utilities segment focuses on the document composition and printing, intelligent mailing, inbound process automation, scanning, and electronic delivery. The Business Services segment offers bankruptcy, class actions, and corporate trust administration services. The Technology Services and Operations segment includes the provision of software in share registry and financial services. The company was founded by Christopher John Morris in 1978 and is headquartered in Melbourne, Australia. | AC95: Consulting/Business Process Outsourcing Services | AD95: Other Professional Services | AE95: Business Services | AF95: Other Consulting and Business Process Outsourcing | AH95: 1847 | AI95: 1 | AJ95: Scope 1,"2,791","1,847",2%,-944,-34% | AK95: 129 | AL95: 1 | AM95: Scope 2,"8,065",129,<1%,"-7,937",-98% | AN95: 93221 | AO95: 1 | AP95: Investments",941,1% "TOTAL, Scope 3 (excl. optional categories)","89,333",94% "TOTAL, Scope 3 (incl. optional categories)","93,221",98% | AQ95: 14 | AR95: 0.197389 | AS95: 0.002958
A96: REH-AU | B96: Reece Ltd. | R96: =IFERROR(_xlfn.XLOOKUP($A96,Profitability!$A$5:$A$342,Profitability!$Q$5:$Q$342),"na") | S96: =IFERROR(_xlfn.XLOOKUP($A96,Profitability!$A$5:$A$342,Profitability!$R$5:$R$342),"na") | T96: Public | U96: Australia | V96: 1920 | W96: 9000 | X96: 8978.382 | Y96: Pacific | Z96: Victoria (VIC) | AA96: 7417.4532 | AB96: Reece Ltd. engages in supplying plumbing, bathroom, heating, ventilation, air-conditioning, waterworks and refrigeration products to customers in the trade, retail and commercial markets. The firm operates through the Australia and New Zealand, and United States geographical segments. The company was founded in 1920 and is headquartered in Cremorne, Australia. | AC96: Equipment and Supplies Distributors | AD96: Diversified Industrials Distribution | AE96: Industrial Services | AF96: Hardware, Plumbing, Heating Supplies Distributors | AH96: 39623 | AI96: 1 | AJ96: (baseline) Scope 1 39,623 39,891 36,567 36,238 Scope 2 market-based 24,373 25,695 27,216 27,865 | AK96: 26299 | AL96: 1 | AM96: 4.8 Reducing our carbon footprint In FY24, the Group’s Scope 1 and 2 greenhouse gas emissions were 63,996 tonnes of carbon dioxide equivalent (tCO2e-), calculated on market-based methodology to reflect our use of renewable energy. This represents a 2.4% decrease on FY23, | AN96: 0 | AQ96: 3 | AR96: 0.0353 | AS96: 0.000334
A97: GWA-AU | B97: GWA Group Ltd. | R97: =IFERROR(_xlfn.XLOOKUP($A97,Profitability!$A$5:$A$342,Profitability!$Q$5:$Q$342),"na") | S97: =IFERROR(_xlfn.XLOOKUP($A97,Profitability!$A$5:$A$342,Profitability!$R$5:$R$342),"na") | T97: Public | U97: Australia | V97: 1992 | W97: - | X97: 418.475 | Y97: Pacific | Z97: New South Wales (NSW) | AA97: 670.24802 | AB97: GWA Group Ltd. engages in the the delivery of sustainable water solutions for bathrooms, kitchens, and laundries. It operates through the Australia, New Zealand, and Other geographical segments. The company was founded in 1989 and headquartered in Pinkenba, Australia. | AC97: Small Appliances and Accessories Manufacturing | AD97: Household Appliances and Tools | AE97: Household Products | AF97: Plumbing Fixtures and Trim Manufacturing | AH97: 321 | AI97: 0.9 | AJ97: GWA’s approach is grounded in data-driven,,,,,, "monitoring of Scope 1 and Scope 2 emissions,",,,,,, and laying the groundwork to review and,,,,,, | AK97: 1064 | AL97: 0.9 | AM97: ,,,,,CO2e,, China,Tonnes,0,0,,,, ,,,,New Zealand,Tonnes,37,32 | AN97: 0 | AQ97: 0 | AR97: 0.103657 | AS97: 0
A98: NUF-AU | B98: Nufarm Ltd. | R98: =IFERROR(_xlfn.XLOOKUP($A98,Profitability!$A$5:$A$342,Profitability!$Q$5:$Q$342),"na") | S98: =IFERROR(_xlfn.XLOOKUP($A98,Profitability!$A$5:$A$342,Profitability!$R$5:$R$342),"na") | T98: Public | U98: Australia | V98: 2000 | W98: 3159 | X98: 3345.909 | Y98: Pacific | Z98: Victoria (VIC) | AA98: 4498.1071 | AB98: Nufarm Ltd. engages in the provision of manufacture and sale of crop protection products. It operates through the Crop Protection and Seed Technologies segments. The Crop Protection segment deals with the manufacture and sale of crop protection products used by farmers to protect crops from damage caused by weeds, pests, and disease. The Seed Technologies segment sells seeds and treatment products. The company was founded by Maxwell A. Fremder on May 21, 1957 and is headquartered in Melbourne, Australia. | AC98: Agrochemical Products | AD98: Specialty and Performance Chemicals | AE98: Chemical, Plastic and Rubber Materials | AF98: General Agrochemicals Manufacturing | AH98: 38043 | AI98: 1 | AJ98: Other8,,,226,194,85 Total scope 1 - direct emissions,"18,848","16,951","17,039","38,049","38,043" Scope 2 – energy indirect emissions,,,,, | AK98: 18628 | AL98: 1 | AM98: Purchased electricity,,,"45,914","32,251","16,824" Total Scope 2 – energy indirect emissions,"75,070","70,430","64,485","37,760","18,628" | AN98: 0 | AQ98: 0 | AR98: -0.001673 | AS98: 0
A99: SGM-AU | B99: Sims Ltd. | R99: =IFERROR(_xlfn.XLOOKUP($A99,Profitability!$A$5:$A$342,Profitability!$Q$5:$Q$342),"na") | S99: =IFERROR(_xlfn.XLOOKUP($A99,Profitability!$A$5:$A$342,Profitability!$R$5:$R$342),"na") | T99: Public | U99: Australia | V99: 2005 | W99: 3916 | X99: 7494 | Y99: Pacific | Z99: New South Wales (NSW) | AA99: 4446.1001 | AB99: Sims Ltd. engages in the recycling of metal and electronics. It operates through the following segments: North America Metals (NAM), Australia, New Zealand Metals (ANZ), UK Metal (UK), Global Trading, Investment in SA Recycling (SAR), Sims Lifecycle Services (SLS), and Unallocated. The NAM segment consists of subsidiaries and joint ventures in the U.S. and Canada, which perform ferrous and non-ferrous secondary recycling functions. The ANZ segment includes subsidiaries and joint arrangements in Australia, New Zealand, and Papua New Guinea, which perform ferrous and non-ferrous secondary recycling functions. The UK segment consists of subsidiaries in the United Kingdom, which perform ferrous and non-ferrous secondary recycling functions. The Global Trading segment consists of the group’s ferrous and non-ferrous marketing subsidiaries that coordinate sales of ferrous bulk cargo shipments, non-ferrous sales into primarily China and Southeast Asia, and brokerage sales on behalf of third and related parties. The SAR segment consists of the group’s share of results from its investment in the SA Recycling joint venture. The SLS segment consists of subsidiaries, which provide electronic recycling solutions in the following countries: Australia, Germany, India, Ireland, Netherlands, New Zealand, Poland, Singapore, the United Kingdom, and the United States of America. The Unallocated segment contains unallocated corporate costs, interests in a joint venture in Australia, Sims Municipal Recycling, and Global Sustainability Insurance Corporation. The company was founded by Albert George Sims in 1917 and is headquartered in Mascot, Australia. | AC99: Primary Metals Products | AD99: Metal Products | AE99: Mining and Mineral Products | AF99: Metal Processing and Recycling Services | AH99: 75000 | AJ99: FY25 Total Scope 1 emissions (75.0 kt CO₂e). | AK99: 0 | AM99: FY25 Total Scope 2 emissions (Market-based) (0.0 kt CO₂e). Zero emissions achieved by procuring 100% renewable energy. | AN99: 5098300 | AP99: FY25 Total Scope 3 emissions (5,098.3 kt CO₂e). | AR99: 0.00032
A100: APA-AU | B100: APA Group | R100: =IFERROR(_xlfn.XLOOKUP($A100,Profitability!$A$5:$A$342,Profitability!$Q$5:$Q$342),"na") | S100: =IFERROR(_xlfn.XLOOKUP($A100,Profitability!$A$5:$A$342,Profitability!$R$5:$R$342),"na") | T100: Public | U100: Australia | V100: 2000 | W100: 2164 | X100: 3144 | Y100: Pacific | Z100: New South Wales (NSW) | AA100: 20514.001 | AB100: APA Group engages in the business of owning, managing, and operating diverse portfolios of gas, electricity, solar, and wind assets. It operates through the following segments: Energy Infrastructure, Asset Management, Energy Investments, and Other. The Energy Infrastructure segment includes infrastructure assets across gas transmission, compression, processing, storage and electricity generation, and transmission. The Asset Management segment provides asset management and operating services for third parties and the majority of energy investments. The Energy Investments segment focuses on energy infrastructure investments. The company was founded in June 2000 and is headquartered in Sydney, Australia. | AC100: Natural Gas Pipeline and Storage Services | AD100: Midstream Energy | AE100: Downstream and Midstream Energy | AF100: International Natural Gas Pipeline and Storage | AH100: 1862659 | AI100: 1 | AJ100: Scope 1,,305-1,t CO2-e,"1,862,659","1,905,327","1,379,338","1,492,977","1,429,979" | AK100: 139281 | AL100: 1 | AM100: Scope 2 (market method) - line loss,,,t CO2-e,"139,281","129,718","137,643","76,737","68,264" | AN100: 636284 | AO100: 1 | AP100: Total Upsteam and Downstream (net),,305-3,t CO2-e,"629,401","656,841","809,638","853,473","771,671","708,901" | AQ100: 3 | AR100: 0.031489 | AS100: 0.000954
...

Sheet Summary
A1: Search Parameters (5)
A2: Company Type | B2: Public
A3: Total Assets (MM) | B3: Greater than or equal to 500
A4: Number of Employees | B4: Greater than or equal to 500
A5: Revenue (MM) | B5: Greater than or equal to 250
A6: Company Location | B6: Australia
A10: Logic | B10: "Company Type" AND "Company Location" AND ( "Total Assets (MM)" OR "Number of Employees" OR "Revenue (MM)" )

Sheet Profitability
A1: Company Details | B1: Company Details | C1: Company Details | D1: Company Details | E1: Company Details | F1: Size Metrics | G1: Financials | H1: Company Details | I1: Company Details | J1: Financials | K1: Company Details | L1: Industry | M1: Industry | N1: Industry | O1: Industry | P1: Financials | Q1: Financials | R1: Financials | S1: Ratios | T1: Ratios | U1: Ratios
A2: Company Details | B2: Company Details | C2: Company Details | D2: Company Location | E2: Company Details | F2: Size Metrics | G2: Income Statement | H2: Company Location | I2: Company Location | J2: Balance Sheet | K2: Company Details | L2: Industry Company Details | M2: Industry Company Details | N2: Industry Company Details | O2: Industry Company Details | P2: Income Statement | Q2: Income Statement | R2: Income Statement | S2: Profitability | T2: Profitability | U2: Profitability
L3: Primary RBICS | M3: Primary RBICS | N3: Primary RBICS | O3: Primary RBICS
A4: Identifier | B4: Name | C4: Company Type Main | D4: Company Country | E4: Year Founded | F4: Number of Employees | G4: Revenue (MM) (AUD) | H4: Company Region | I4: Company State | J4: Total Assets (MM) (AUD) | K4: Business Description | L4: Primary FactSet RBICS Industry Group | M4: Primary FactSet RBICS Sub Sector | N4: Primary FactSet RBICS Sector | O4: Primary FactSet RBICS Industry | P4: Gross Profit (MM) (AUD) | Q4: EBITDA (MM) (AUD) | R4: Net Income (MM) (AUD) | S4: EBITDA Margin (AUD) | T4: Gross Income Margin (AUD) | U4: Net Income Margin (AUD)
A5: NAB-AU | B5: National Australia Bank Ltd. | C5: Public | D5: Australia | E5: 1893 | F5: 41880 | G5: 60247 | H5: Pacific | I5: Victoria (VIC) | J5: 1109256 | K5: National Australia Bank Ltd. engages in the provision of banking and financial services. Its services include banking, credit and access card facilities, leasing, housing and general finance, international banking, investment banking, wealth management, funds management and custodian, trustee and nominee services. It operates through the following segments: Business and Private Banking, Personal Banking, Corporate and Institutional Banking, New Zealand Banking, and Corporate Functions and Others. The Business and Private Banking segment focuses on priority small and medium (SME) customers. The Personal Banking segment provides banking products and services to customers. The Corporate and Institutional Banking segment includes client coverage, corporate finance, markets, asset servicing, transactional banking and enterprise payments. The New Zealand Banking segment focuses on banking and financial services across customer segments in New Zealand. The Corporate Functions and Other segment covers ubank and enabling units. The company was founded on October 4, 1858 and is headquartered in Melbourne, Australia. | L5: Asia/Pacific Banks | M5: International Banks | N5: Banking | O5: Australia and New Zealand Banks | P5: - | Q5: - | R5: 6788 | S5: - | T5: - | U5: 11.266951
A6: BHP-AU | B6: BHP Group Ltd. | C6: Public | D6: Australia | E6: 1885 | F6: - | G6: 79153.099 | H6: Pacific | I6: Victoria (VIC) | J6: 166002.9 | K6: BHP Group Ltd. engages in the exploration, development, production and processing of iron ore, metallurgical coal, and copper. It operates through the following segments: Copper, Iron Ore, and Coal. The Copper segment refers to the mining of copper, silver, lead, zinc, molybdenum, uranium, and gold. The Iron Ore segment involves in the mining of iron ore. The Coal segment focuses on metallurgical coal and energy coal. The company was founded on August 13, 1885 and is headquartered in Melbourne, Australia. | L6: Base Metal Mining | M6: Metal Ore Mining | N6: Mining and Mineral Products | O6: Other Base Metal Ore Mining | P6: 36902.187 | Q6: 38227.016 | R6: 13926.14 | S6: 48.295033 | T6: 46.621279 | U6: 17.593929
A7: PPT-AU | B7: Perpetual Ltd. | C7: Public | D7: Australia | E7: 1963 | F7: 1789 | G7: 1406.5 | H7: Pacific | I7: New South Wales (NSW) | J7: 3417.8001 | K7: Perpetual Ltd. operates as an independent financial services group, which provides investment management, wealth advice, and corporate fiduciary services to individuals, families, financial advisers, and institutions. It operates through the following segments: Asset Management, Wealth Management, and Corporate Trust. The Asset Management segment is a global multi-boutique asset management business. The Wealth Management segment includes Perpetual Private and other specialist businesses offering wealth management, advice, and trustee services. The Corporate Trust segment provides fiduciary and digital solutions to the banking and financial industry; and administers securitization portfolios, investment. and debt structures. The company was founded on September 28, 1886 and is headquartered in Sydney, Australia. | L7: Asset Management and Financial Advisory Services | M7: Investment Services | N7: Investment Services | O7: Diverse Asset Management and Financial Advisors | P7: 1205 | Q7: 317.09999 | R7: -58.2 | S7: 22.545325 | T7: 85.673658 | U7: -4.137931
A8: ANN-AU | B8: Ansell Ltd. | C8: Public | D8: Australia | E8: 1893 | F8: 15724 | G8: 3093.2738 | H8: Pacific | I8: Victoria (VIC) | J8: 5069.6576 | K8: Ansell Ltd. engages in the development, manufacturing, distribution, and sale of gloves and protective solutions. It operates through the Healthcare and Industrial segment. The Healthcare segment includes surgical and examination gloves, healthcare safety devices, and active infection prevention products for healthcare patients and single use industrial application gloves. The Industrial segment provides multi-use hand and body protection solutions for industrial worker environments and specialty applications. The company was founded in 1893 and is headquartered in Richmond, Australia. | L8: Medical Supplies | M8: Other Medical Devices | N8: Healthcare Equipment | O8: Safety and Sterilization Medical Supplies | P8: 1267.0796 | Q8: 542.12971 | R8: 156.87946 | S8: 17.526082 | T8: 40.962412 | U8: 5.0716318
A9: STO-AU | B9: Santos Ltd. | C9: Public | D9: Australia | E9: 1954 | F9: 3958 | G9: 8298.981 | H9: Pacific | I9: South Australia (SA) | J9: 49855.445 | K9: Santos Ltd. engages in the exploration, development, transportation, and marketing of natural gas. It operates through the following segments: Cooper Basin, Queensland and New South Wales, Papua New Guinea, Northern Australia and Timor-Leste, and Western Australia. The company was founded by Reg Sprigg, John Bonython, and Douglas Mawson on March 18, 1954 and is headquartered in Adelaide, Australia. | L9: Other Pipeline and Energy Storage Services | M9: Midstream Energy | N9: Downstream and Midstream Energy | O9: Other Pipeline and Energy Storage Services | P9: 2907.8271 | Q9: 5359.3163 | R9: 1855.6728 | S9: 64.578005 | T9: 35.038363 | U9: 22.360248
A10: ATP-AU | B10: Atlas Pearls Ltd. | C10: Public | D10: Australia | E10: 1987 | F10: 1200 | G10: 44.271016 | H10: Pacific | I10: Western Australia (WA) | J10: 85.885515 | K10: Atlas Pearls Ltd. produces white & silver South Sea pearls and farming operations in Indonesia. It operates through the Australia and Indonesia segments. The company was founded in 1992 and is headquartered in Perth, Australia. | L10: Accessories Production | M10: Apparel and Accessory Products | N10: Consumer Goods | O10: Jewelry and Other Accessories Production | P10: 30.011675 | Q10: 21.585548 | R10: 21.897781 | S10: 48.75777 | T10: 67.790798 | U10: 49.463019
A11: WDS-AU | B11: Woodside Energy Group Ltd. | C11: Public | D11: Australia | E11: 1971 | F11: 4718 | G11: 21202.274 | H11: Pacific | I11: Western Australia (WA) | J11: 98948.555 | K11: Woodside Energy Group Ltd. engages in the exploration, evaluation, development, and production of hydrocarbon and oil and gas properties. It operates through the following segments: North West Shelf, Pluto, Australia Oil, Wheatstone, Development, and Others. The North West Shelf segment produces liquefied natural gas, pipeline natural gas, condensate, liquefied petroleum gas and crude oil from the North West Shelf ventures. The Pluto segment develops liquefied natural gas in assigned permit areas. The Australia Oil segment is involved in the exploration, evaluation, development, production and sale of crude oil in assigned permit areas. The Wheatstone segment is involved in the exploration, evaluation, and development of liquefied natural gas, pipeline natural gas, and condensate. The Development segment includes the exploration of gas resources in Scarborough, Sangomar, and other project areas. The Other segment is composed of the activities undertaken by exploration, international and Sunrise Business Units. The company was founded on July 26, 1954 and is headquartered in Perth, Australia. | L11: Other Fossil Fuel Exploration and Production | M11: Fossil Fuel Exploration and Production | N11: Upstream Energy | O11: Asia/Pacific Fossil Fuel Exploration/Production | P11: 8538.5204 | Q11: 15527.615 | R11: 5416.9271 | S11: 73.23561 | T11: 40.27172 | U11: 25.548802
A12: ORG-AU | B12: Origin Energy Ltd. | C12: Public | D12: Australia | E12: 1946 | F12: 5000 | G12: 17118 | H12: Pacific | I12: New South Wales (NSW) | J12: 20989.001 | K12: Origin Energy Ltd. is an integrated energy company, which engages in exploration and production of natural gas, electricity generation, wholesale and retail sale of electricity and gas, and sale of liquefied natural gas. It operates through the following business segments: Energy Markets, Share of Octopus Energy, Integrated Gas, and Corporate. The Energy Markets segment includes energy retailing, power generation and liquid petroleum gas operations. The Share of Octopus Energy segment focuses on the Origin’s investment in Octopus Energy Group Limited (Octopus Energy). The Integrated Gas segment engages in growth assets business and management of LNG price risk through hedging and trading activities. The Corporate segment includes various business development and support activities that are not allocated to operating segments. The company was founded on March 4, 1946 and is headquartered in Sydney, Australia. | L12: Asia/Pacific Wholesale Power | M12: Energy Utilities | N12: Utilities | O12: Other Asia/Pacific Wholesale Power | P12: 2202 | Q12: 2034 | R12: 1481 | S12: 11.882229 | T12: 12.863652 | U12: 8.6517116
A13: TAH-AU | B13: Tabcorp Holdings Ltd. | C13: Public | D13: Australia | E13: 1994 | F13: - | G13: 2151.5 | H13: Pacific | I13: Victoria (VIC) | J13: 3140.2001 | K13: Tabcorp Holdings Ltd. engages in the provision of entertainment services. It operates through the Wagering and Media, and Gaming Services segments. The Wagering and Media segment includes totalizator and fixed odds betting, retail wagering networks, and global racing media business. The Gaming Services segment provides regulatory monitoring and related services. The company was founded on April 13, 1994 and is headquartered in Melbourne, Australia. | L13: Arts, Entertainment and Recreation Providers | M13: Hospitality Services | N13: Hospitality Services | O13: Gaming Industries | P13: 424.3 | Q13: 356.19999 | R13: 36.6 | S13: 16.555891 | T13: 19.721125 | U13: 1.7011387
A14: CSL-AU | B14: CSL Ltd. | C14: Public | D14: Australia | E14: 1961 | F14: 29000 | G14: 23825.296 | H14: Pacific | I14: Victoria (VIC) | J14: 60126.651 | K14: CSL Ltd. is a biopharmaceutical company, which engages in the manufacture, marketing, and distribution of biopharmaceutical and allied products. It operates through the following segments: CSL Behring, CSL Seqirus, and CSL Vifor. The CSL Behring segment provides plasma products, gene therapies, and recombinants. The CSL Seqirus segment includes predominantly influenza related products and provides pandemic services to governments. The CSL Vidor segment focuses on the distribution of products in the therapeutic areas of iron deficiency and nephrology. The company was founded on November 2, 1961 and is headquartered in Melbourne, Australia. | L14: Diversified Biopharmaceuticals | M14: Other Biopharmaceuticals | N14: Biopharmaceuticals | O14: Diversified Biopharmaceuticals | P14: 11639.344 | Q14: 7794.5622 | R14: 4635.3557 | S14: 32.715489 | T14: 48.852884 | U14: 19.455606
A15: CDA-AU | B15: Codan Ltd. | C15: Public | D15: Australia | E15: 1959 | F15: 1000 | G15: 674.226 | H15: Pacific | I15: South Australia (SA) | J15: 904.80502 | K15: Codan Ltd. engages in the provision of electronic solutions, focusing on metal detection and communications technology. It operates through the following segments: Communications, Metal Detection, and Other. The Communications segment includes the design, development, manufacture, and marketing of communications equipment. The Metal Detection segment focuses on the designs, development, manufacture, and marketing of metal detection equipment. The Other segment refers to the tracking solutions business and the ongoing manufacturing and sale of tracking products. The company was founded by Alastair Wood, Ian Baker Wall, and Jim Irvine Bettison on July 1, 1959, and is headquartered in Mawson Lakes, Australia. | L15: Other Communications Equipment | M15: Communications Equipment | N15: Hardware | O15: Other Wireless Equipment | P15: 339.254 | Q15: 184.30001 | R15: 103.493 | S15: 27.335048 | T15: 50.317549 | U15: 15.349898
A16: OBL-AU | B16: Omni Bridgeway Ltd. | C16: Public | D16: Australia | E16: 1986 | F16: 167 | G16: 54.986 | H16: Pacific | I16: New South Wales (NSW) | J16: 1191.955 | K16: Omni Bridgeway Ltd. engages in the investigation, management, and funding of litigation and arbitration claims. It operates through the following geographical segments: Americas, APAC, EMEA, and Corporate. The Americas segment focuses on the investment management business operating in America, Canada, and Latin America. The APAC segment is involved in the investment management business operating in Australia, Asia, and New Zealand. The EMEA segment represents the investment management business operating in Europe, Middle East, and Africa. The company was founded in 1986 and is headquartered in Sydney, Australia. | L16: Commercial Finance Services | M16: Specialty Finance | N16: Specialty Finance and Services | O16: Diversified Loan Services | P16: 26.95 | Q16: -25.777997 | R16: 349.797 | S16: -46.881024 | T16: 49.012476 | U16: 636.15648
A17: MOZ-AU | B17: Mosaic Brands Ltd. | C17: Public | D17: Australia | E17: 1987 | F17: - | G17: 505.7 | H17: Pacific | I17: New South Wales (NSW) | J17: 317.09001 | K17: Mosaic Brands Ltd. engages in the retail and sale of women's apparel and accessories. It offers classic and stylish contemporary fashion for woman under Noni B and Liz Jordan brand names. The company was founded by Alan A. Kindl in 1977 and is headquartered in Rosebery, Australia. | L17: Apparel Retail | M17: Apparel and Accessories Retail | N17: Consumer Retail | O17: Other Apparel Retail | P17: 278.07 | Q17: 54.935 | R17: 0.266 | S17: 10.86316 | T17: 54.987147 | U17: 0.052600356
A18: NST-AU | B18: Northern Star Resources Ltd. | C18: Public | D18: Australia | E18: 2000 | F18: 8728 | G18: 6414.9 | H18: Pacific | I18: Western Australia (WA) | J18: 21050.101 | K18: Northern Star Resources Ltd. is a gold producer and exploration company. It operates through the following segments: KCGM, Kalgoorlie Operations, Carosue Dam, Pogo, Jundee, Thunderbox, and Exploration. The KCGM, Kalgoorlie Operations, Carosue Dam, Pogo, Jundee, and Thunderbox segments are involved in the mining and processing of gold. The Exploration segment focuses on the exploration and evaluation of gold mineralization. The company founded on May 12, 2000 and is headquartered in Subiaco, Australia. | L18: Precious Metal Mining | M18: Metal Ore Mining | N18: Mining and Mineral Products | O18: Asia/Pacific Gold Mining | P18: 2234.4 | Q18: 3488.4 | R18: 1339.7 | S18: 54.379647 | T18: 34.831408 | U18: 20.884191
A19: EGG-AU | B19: Enero Group Ltd. | C19: Public | D19: Australia | E19: 2000 | F19: 600 | G19: 187.47 | H19: Pacific | I19: New South Wales (NSW) | J19: 225.78501 | K19: Enero Group Ltd. engages in integrated marketing and communication services. It operates through the Brand Transformation, and Creative Technology and Data segments. The Brand Transformation segment refers to human generated creative ideas to transform the way customers and stakeholders connect and engage with brands. The Creative Technology and Data segment is involved with high quality customer experience connected by technology and enabled by data. The company was founded on February 9, 2000, and is headquartered in Pyrmont, Australia. | L19: Marketing and Advertising Services | M19: Marketing and Printing Services | N19: Business Services | O19: Other Marketing and Advertising Services | P19: 20.576 | Q19: 14.194009 | R19: -7.492 | S19: 7.5713447 | T19: 10.975623 | U19: -3.9963728
A20: NCK-AU | B20: Nick Scali Ltd. | C20: Public | D20: Australia | E20: 1962 | F20: 850 | G20: 495.283 | H20: Pacific | I20: New South Wales (NSW) | J20: 705.80702 | K20: Nick Scali Ltd. engages in the sourcing and retailing of household furniture and related accessories. It offers sofas and armchairs, rugs and accessories, and furniture for living, dining, and bedroom. The company was founded by Nicodemo Domenico Scali in 1962 and is headquartered in North Ryde, Australia. | L20: Furniture and Home Furnishings Stores | M20: Home Improvement Retail | N20: Consumer Retail | O20: Furniture Stores | P20: 174.453 | Q20: 154.762 | R20: 57.676 | S20: 31.247186 | T20: 35.222893 | U20: 11.645059
A21: AX1-AU | B21: Accent Group Ltd. | C21: Public | D21: Australia | E21: 2004 | F21: 8600 | G21: 1470.9674 | H21: Pacific | I21: Victoria (VIC) | J21: 1257.8976 | K21: Accent Group Ltd. operates as an investment holding company, which engages in the retail of performance and lifestyle footwear. It offers its products under the following brands: The Athlete's Foot, Platypus Shoes, Sneaker Lab, Hype DC, Skechers, Merrell, CAT, Vans, 4Workers, EXIE, Dr. Martens, Saucony, Timberland, Sperry, Palladium, Stance, Supra, Subtype, The Trybe, PIVOT, and Stylerunner. The company was founded by Michael Hapgood in 1966 and is headquartered in Melbourne, Australia. | L21: Footwear Retail | M21: Apparel and Accessories Retail | N21: Consumer Retail | O21: Footwear Stores | P21: 306.16103 | Q21: 288.84424 | R21: 57.662643 | S21: 19.636345 | T21: 20.813584 | U21: 3.9200489
A22: INA-AU | B22: Ingenia Communities Group | C22: Public | D22: Australia | E22: 2003 | F22: - | G22: 518.174 | H22: Pacific | I22: New South Wales (NSW) | J22: 2773.1501 | K22: Ingenia Communities Group engages in managing and developing a portfolio of retirement and lifestyle communities. It operates through the following segments: Lifestyle Development; Lifestyle Rental; Ingenia Gardens; Holidays and Mixed Use; Fuel, Food, and Beverage Services; and Corporate and Other. The Lifestyle Development segment refers to the development and sale of lifestyle homes. The Lifestyle Rental segment relates to long-term accommodation within lifestyle and rental communities. The Ingenia Gardens is involved in rental villages. The Holidays and Mixed Use segment includes tourism and rental accommodation within holiday parks. The Fuel, Food, and Beverage Services segment focuses on its investment in service stations and food and beverage operations adjoined to Ingenia Holiday communities. The Corporate and Other segment covers its remaining assets and operating activities. The company was founded on November 22, 2003 and is headquartered in Sydney, Australia. | L22: Equity REITs | M22: Real Estate Investment Trusts (REITs) | N22: Real Estate | O22: Equity REITs | P22: 314.94 | Q22: 135.26 | R22: 128.425 | S22: 26.103201 | T22: 60.778812 | U22: 24.784146
A23: KAR-AU | B23: Karoon Energy Ltd. | C23: Public | D23: Australia | E23: 2003 | F23: - | G23: 1177.2303 | H23: Pacific | I23: Victoria (VIC) | J23: 3135.7505 | K23: Karoon Energy Ltd. is an oil and gas exploration company, which engages in oil and gas production, development assets, and providing energy. It operates through the following geographical segments: Australia, Brazil, U.S.A., and All Other. The Australia segment is involved in the exploration and evaluation of hydrocarbons. The Brazil segment refers to the exploration, development, and production of hydrocarbons. The U.S.A segment focuses on the acquisition of LLOG interests in the Mississippi Canyon Blocks in the Gulf of Mexico. The All Other segment relates to the closure of its Peruvian branches. The company was founded by Robert Michael Hosking on November 11, 2003 and is headquartered in Southbank, Australia. | L23: Americas Fossil Fuel Exploration and Production | M23: Fossil Fuel Exploration and Production | N23: Upstream Energy | O23: Other Americas Fossil Fuel Exploration/Production | P23: 551.8504 | Q23: 791.99628 | R23: 193.29925 | S23: 67.276239 | T23: 46.877012 | U23: 16.419833
A24: TRS-AU | B24: The Reject Shop Ltd. | C24: Public | D24: Australia | E24: 1983 | F24: 4000 | G24: 852.736 | H24: Pacific | I24: Victoria (VIC) | J24: 492.715 | K24: The Reject Shop Ltd. engages in retailing discount variety merchandise. It offers general consumer merchandise such as toiletries, cosmetics, homeware, personal care products, hardware, basic furniture, household cleaning products, kitchenware, confectionery, snack food, lifestyle and seasonal merchandise, such as seasonal gifts, cards and wrapping, toys, leisure items and home decorations. The company was founded by Ron Hall and John Shuster in 1981 and is headquartered in Kensington, Australia. | L24: Discount Stores | M24: General Merchandise Retail | N24: Food and Staples Retail | O24: General Discount Stores | P24: 238.154 | Q24: 126.40301 | R24: 4.713 | S24: 14.823228 | T24: 27.928222 | U24: 0.55269157
A25: MMS-AU | B25: McMillan Shakespeare Ltd. | C25: Public | D25: Australia | E25: 2003 | F25: 1311 | G25: 538.177 | H25: Pacific | I25: Victoria (VIC) | J25: 1479.925 | K25: McMillan Shakespeare Ltd. engages in salary packaging, novated leasing, disability plan management and support co-ordination, asset management and related financial products and services. It operates through the following segments: Group Remuneration Services, Asset Management, and Plan and Support Services. The Group Remuneration Services segment offers administrative services in respect of salary packaging and facilitates the settlement of motor vehicle novated leases for customers. The Asset Management segment offers financing and ancillary management services associated with motor vehicles, commercial vehicles, and equipment. The Plan and Support Services segment engages in the management and support coordination services to participants in the National Disability Insurance Scheme (NDIS). The company was founded by Anthony G. Podesta in 1988 and is headquartered in Melbourne, Australia. | L25: Administrative Services | M25: Other Professional Services | N25: Business Services | O25: Administrative Employment Services | P25: 210.185 | Q25: 220.675 | R25: 95.79 | S25: 41.004168 | T25: 39.054995 | U25: 17.798977
A26: PPC-AU | B26: Peet Ltd. | C26: Public | D26: Australia | E26: 1905 | F26: 180 | G26: 414.785 | H26: Pacific | I26: Western Australia (WA) | J26: 1111.716 | K26: Peet Ltd. engages in the acquisition, development, and sale of residential land. It operates through the following segments: Funds Management, Company-owned Projects, Joint Arrangements, and Inter-segment Eliminations and Other Unallocated. The Funds Management segment offers equity funds towards the acquisition of land and is generally supplemented with debt funds. The Company-owned Projects segment acquires parcels of land in Australia, primarily for residential development purposes. The Joint Arrangements segment consists of government, statutory authorities, and private landowners. The Inter-segment Eliminations and Other Unallocated segment refers to the revenue, expenses, and results. The company was founded by James Thomas Peet in July 1895 and is headquartered in Perth, Australia. | L26: Other Real Estate Investment and Services | M26: Real Estate Investment and Services | N26: Real Estate | O26: Real Estate Developers | P26: 115.832 | Q26: 61.601005 | R26: 58.467 | S26: 14.851309 | T26: 27.925793 | U26: 14.095736
A27: SFR-AU | B27: Sandfire Resources Ltd. | C27: Public | D27: Australia | E27: 2003 | F27: 5468 | G27: 1830.3324 | H27: Pacific | I27: Western Australia (WA) | J27: 4483.3922 | K27: Sandfire Resources Ltd. engages in the production and sale of copper, gold, and silver. It operates through the following segments: DeGrussa Copper Operations, MATSA Copper Operations, Black Butte Project, Motheo Copper Project, and Exploration and Other. The DeGrussa Copper Operations segment is involved in both the DeGrussa and Monty Copper-Gold mines in the Bryah basin. The company was founded on June 18, 2003 and is headquartered in West Perth, Australia. | L27: Base Metal Mining | M27: Metal Ore Mining | N27: Mining and Mineral Products | O27: Non-Ferrous Metal Ore Mining | P27: 360.92467 | Q27: 830.24131 | R27: 143.98786 | S27: 45.360138 | T27: 19.719077 | U27: 7.86676
A28: PRU-AU | B28: Perseus Mining Ltd. | C28: Public | D28: Australia | E28: 2003 | F28: - | G28: 1927.1499 | H28: Pacific | I28: Western Australia (WA) | J28: 3785.5452 | K28: Perseus Mining Ltd. is engaged in gold mining activities, mineral exploration, evaluation, and project development. It operates through the following segments: Edikan, Sissingué, Yaouré, Sudan, Tanzania, and Corporate and Other. The Corporate and Other segment refers to investing activities and corporate management. The company was founded in 2004 and is headquartered in Subiaco, Australia. | L28: Precious Metal Mining | M28: Metal Ore Mining | N28: Mining and Mineral Products | O28: Other Gold Mining | P28: 905.61911 | Q28: 1111.0247 | R28: 572.65172 | S28: 57.65118 | T28: 46.992666 | U28: 29.714955
A29: EHL-AU | B29: Emeco Holdings Ltd. | C29: Public | D29: Australia | E29: 2004 | F29: 909 | G29: 785.354 | H29: Pacific | I29: Western Australia (WA) | J29: 1247 | K29: Emeco Holdings Ltd. engages in the provision of open cut, underground mining equipment rental, and providing complementary equipment and mining services, including maintenance, asset and component rebuilds, fleet optimization technology, and technical and engineering services. It operates through the following segments: Emeco Rental, Force Workshops, and Emeco Underground. The Emeco Rental segment provides earthmoving equipment solutions. The Force Workshops segment refers to the maintenance, equipment, and component rebuild services in Australia. The Emeco Underground segment focuses on the underground equipment rental services solutions and associated services in Australia. The company was founded in 1972 and is headquartered in Osborne Park, Australia. | L29: Equipment and Supplies Distributors | M29: Diversified Industrials Distribution | N29: Industrial Services | O29: Industrial Machinery and Supplies Distributors | P29: 228.275 | Q29: 288.428 | R29: 75.14 | S29: 36.725859 | T29: 29.06651 | U29: 9.5676599
A30: SEK-AU | B30: SEEK Ltd. | C30: Public | D30: Australia | E30: 1997 | F30: 3245 | G30: 1097 | H30: Pacific | I30: Victoria (VIC) | J30: 4765.5001 | K30: SEEK Ltd. engages in the provision of online matching of hires and candidates, and other related activities. It operates through the following segments: ANZ, SEEK Asia, Brasil Online, OCC, Platform Support, Corporate Costs, and Portfolio Investment. The ANZ, SEEK Asia, Brasil Online, and OCC segments refer to the online employment marketplace services. The Platform Support segment focuses on a portfolio of investments that complement and/or have synergies with its operating platform. The Corporate Costs segment supports its core business. The Portfolio Investment segment is involved in a portfolio of investments which are managed as standalone entities. The company was founded by Paul Moss Bassat, Andrew Reuven Bassat and Matthew Myer Rockman on September 17, 1997 and is headquartered in Cremorne, Australia. | L30: Consumer Data and Services | M30: Internet and Data Services | N30: Software and Consulting | O30: Information and News Content Providers and Sites | P30: 502.4 | Q30: 407.5 | R30: 238.3 | S30: 37.146764 | T30: 45.79763 | U30: 21.722881
A31: CWY-AU | B31: Cleanaway Waste Management Ltd. | C31: Public | D31: Australia | E31: 2002 | F31: 10000 | G31: 3788.9 | H31: Pacific | I31: Victoria (VIC) | J31: 6578.2002 | K31: Cleanaway Waste Management Ltd. engages in the provision of total waste management, industrial, and environmental services. It operates through the following segments: Solid Waste Services, ETS- Industrial Services, and ETS-Oils & Technical Services and Health Services. The Solid Waste Services segment includes the collection, recovery, and disposal of all types of solid waste, including putrescible waste, inert waste, household waste, and recovered waste. The ETS- Industrial Services segment consists of a variety of services provided to the Resources, Oil and Gas, Infrastructure, Industrial markets and also include Services include vacuum loading, high pressure cleaning, pipeline maintenance and non-destructive digging. The ETS-Oils & Technical Services and Health Services segment is involved in the collection, treatment, processing, refining and recycling, and destruction of hazardous and non-hazardous liquids, hydrocarbons and chemical waste, specialised product destruction, hazardous waste and e-waste, provision of services to the health sector for the safe treatment and disposal of health related waste which includes sharps management, medical waste, pharmaceutical waste, healthcare hazardous waste, and quarantine waste. The company was founded by Terrence Elmore Peabody in August 1987 and is headquartered in Melbourne, Australia. | L31: General Waste Collection | M31: Waste Management Services | N31: Business Services | O31: Diversified General Waste Collection | P31: 518.9 | Q31: 770.5 | R31: 156.9 | S31: 20.335717 | T31: 13.695268 | U31: 4.1410436
A32: CAJ-AU | B32: Capitol Health Ltd. | C32: Public | D32: Australia | E32: 2005 | F32: 1000 | G32: 234.816 | H32: Pacific | I32: Victoria (VIC) | J32: 319.484 | K32: Capitol Health Ltd. provides diagnostic imaging and related services. It provides general x-ray, magnetic resonance imaging, ultrasound, mammography, doppler, orthopantomogram, echocardiography, computer tomography, computed tomography angiography, cone beam computed tomography, nuclear medicine, bone densitomety, and fluoroscopy services. The company was founded by Andrew Duncan Harrison on December 1, 2005 and is headquartered in Docklands, Australia. | L32: Ambulatory and Outpatient Diagnostic Patient Care | M32: Patient Care | N32: Healthcare Services | O32: Other Ambulatory and Outpatient Diagnostic Care | P32: 44.744 | Q32: 49.282994 | R32: -14.853 | S32: 20.987922 | T32: 19.05492 | U32: -6.3253782
A33: GOR-AU | B33: Gold Road Resources Ltd. | C33: Public | D33: Australia | E33: 2004 | F33: - | G33: 528.46 | H33: Pacific | I33: Western Australia (WA) | J33: 1536.065 | K33: Gold Road Resources Ltd. operates as a gold exploration company. It focuses on developing the Yamarna Belt comprising Gruyere, Central Bore and Attila projects. The firm operates through Development & Production and Exploration business segments. The Development & Production includes Gruyere joint operation with gold fields, which transitioned from development to production phase during the year. The Exploration segment includes the activities on all mineral exploration, including all joint venture tenements. The company was founded on May 28, 2004 and is headquartered in West Perth, Australia. | L33: Precious Metal Mining | M33: Metal Ore Mining | N33: Mining and Mineral Products | O33: Asia/Pacific Gold Mining | P33: 224.503 | Q33: 298.763 | R33: 142.697 | S33: 56.534648 | T33: 42.482496 | U33: 27.002422
A34: MIN-AU | B34: Mineral Resources Ltd. | C34: Public | D34: Australia | E34: 2006 | F34: 8456 | G34: 4472 | H34: Pacific | I34: Western Australia (WA) | J34: 11927 | K34: Mineral Resources Ltd. engages in mining and processing of mineral properties. The firm operates through the following segments: Mining Services, Iron Ore, Energy, Lithium, Other Commodities, and Central. It offers contract crushing, infrastructure, and recovery of base metals concentrate. The company was founded by Christopher J. Ellison on February 27, 2006, and is headquartered in Perth, Australia. | L34: Base Metal Mining | M34: Metal Ore Mining | N34: Mining and Mineral Products | O34: Other Base Metal Ore Mining | P34: 1407 | Q34: 857 | R34: -904 | S34: 19.163685 | T34: 31.462433 | U34: -20.214669
A35: SVR-AU | B35: Solvar Ltd. | C35: Public | D35: Australia | E35: 2005 | F35: - | G35: 207.381 | H35: Pacific | I35: Victoria (VIC) | J35: 961.58702 | K35: Solvar Ltd. is a non-bank credit provider. It is focused on the provision of automotive finance in Australia and New Zealand. The firm engages in providing flexible secured and unsecured personal loans to customers often excluded by traditional lenders. The company was founded on November 25, 2005 and is headquartered in Bundoora, Australia. | L35: Consumer Finance Services | M35: Specialty Finance | N35: Specialty Finance and Services | O35: Automobile Financing | P35: 188.321 | Q35: 98.242998 | R35: 31.42 | S35: 47.373192 | T35: 90.809187 | U35: 15.150858
A36: HUM-AU | B36: Humm Group Ltd. | C36: Public | D36: Australia | E36: 2006 | F36: - | G36: 666.6 | H36: Pacific | I36: New South Wales (NSW) | J36: 5338.3001 | K36: Humm Group Ltd. operates as a financial services group, which engages in the financial products through a network of retailers and brokers. The firm's activities include a variety of financial risks, liquidity risk, funding risk, credit risk and market risk. It operates through the following segments: PosPP, New Zealand Cards, Australia Cards, and Commercial. The company was founded by David Berkman and Andrew Abercrombie in 1988 and is headquartered in Sydney, Australia. | L36: Consumer Finance Services | M36: Specialty Finance | N36: Specialty Finance and Services | O36: General Consumer Finance Services | P36: 614.1 | Q36: 376.3 | R36: 39.6 | S36: 56.450645 | T36: 92.124212 | U36: 5.9405941
A37: EGN-AU | B37: Engenco Ltd. | C37: Public | D37: Australia | E37: 2006 | F37: 500 | G37: 214.847 | H37: Pacific | I37: Victoria (VIC) | J37: 190.496 | K37: Engenco Ltd. engages in the provision of engineering services. It operates through the following business segments: Drivetrain, Convair, Gemco Rail, Workforce Solutions, and All Other. The Drivetrain segment is a provider of technical sales and services to the mining, oil & gas, rail, transport, defence, marine, construction, materials handling, automotive, agriculture, and power generation industries. The Convair segment is a manufacturer of bulk pneumatic road tankers and mobile silos for the carriage and storage of construction materials, grains, and other dry bulk materials. The Gemco Rail segment provides wheelset, bogie and in-field wagon maintenance and manufactures new and refurbished wagons, bogie component parts, remote controlled ballast car discharge gates, and a range of rail maintenance equipment and spares. The Workforce Solutions segment includes the people focused business, providing training and labour hire via its business units of Centre for Excellence in Rail Training, Total Momentum and Eureka 4WD Training. The All Other segment focuses on the parent entity, non-reportable segments and consolidation / inter-segment elimination adjustments. The company was founded in 1989 and is headquartered in Melbourne, Australia. | L37: Commercial Transportation Equipment Manufacturing | M37: Transportation Equipment Manufacturing | N37: Industrial Manufacturing | O37: Mixed Commercial Transportation Equipment Makers | P37: 25.415 | Q37: 17.490007 | R37: 3.93 | S37: 8.1406769 | T37: 11.829348 | U37: 1.8292087
A38: BCI-AU | B38: BCI Minerals Ltd. | C38: Public | D38: Australia | E38: 2006 | F38: - | G38: 0 | H38: Pacific | I38: Western Australia (WA) | J38: 1197.268 | K38: BCI Minerals Ltd. is a mineral resources company, which engages in developing and industrial mineral business with salt and potash as its initial focus. It operates through the Mardie and Corporate and Other segments. The Mardie segment includes all activities related to the development and future operation of the Mardie Salt Operation and Potash Project which is the Group's principal project and primary focus of capital investment. The Corporate and Other segment focuses on the head office and corporate support functions, such as executive management, finance, legal, governance, and other administrative functions. The company was founded in 2006 and is headquartered in West Perth, Australia. | L38: Nonmetallic Mineral Mining | M38: Other Mining | N38: Mining and Mineral Products | O38: Other Nonmetallic Minerals Mining | P38: -4.955 | Q38: -60.984003 | R38: -60.171 | S38: - | T38: - | U38: -
A39: LTR-AU | B39: Liontown Resources Ltd. | C39: Public | D39: Australia | E39: 2006 | F39: 306 | G39: 297.565 | H39: Pacific | I39: Western Australia (WA) | J39: 1563.541 | K39: Liontown Resources Ltd. engages in the exploration and evaluation of minerals. Its projects include Kathleen Valley, Buldania, Moora Gold-PGE-Ni-Cu, and Toolebuc. The company was founded on February 2, 2006 and is headquartered in West Perth, Australia. | L39: Base Metal Mining | M39: Metal Ore Mining | N39: Mining and Mineral Products | O39: Lithium Ore Mining | P39: -151.76 | Q39: -26.751993 | R39: -193.277 | S39: -8.9903046 | T39: -51.000622 | U39: -64.952867
A40: DVP-AU | B40: Develop Global Ltd. | C40: Public | D40: Australia | E40: 2006 | F40: - | G40: 231.47203 | H40: Pacific | I40: Western Australia (WA) | J40: 898.08494 | K40: Develop Global Ltd. engages in the exploration and production of mine base and precious metal resources. It owns the Sulphur Springs Project, Whim Creek Joint Venture Project, and Woodlawn Project. It operates through the following segments: Mining Services, Mining and Exploration, and Other. The company was founded on October 13, 2006 and is headquartered in Leederville, Australia. | L40: Base Metal Mining | M40: Metal Ore Mining | N40: Mining and Mineral Products | O40: Non-Ferrous Metal Ore Mining | P40: 22.125089 | Q40: 26.0635 | R40: 72.393528 | S40: 11.259887 | T40: 9.5584287 | U40: 31.275281
A41: WHC-AU | B41: Whitehaven Coal Ltd. | C41: Public | D41: Australia | E41: 2007 | F41: - | G41: 5832 | H41: Pacific | I41: New South Wales (NSW) | J41: 12227 | K41: Whitehaven Coal Ltd. engages in the development and operation of coal mines. It operates through the NSW Operations and QLD Operations segments. Its projects include Canyon, Maules Creek, Narrabri North, Rocglen, Sunnyside, Tarrawonga, Vickery, Werris Creek, and Other Projects. The company was founded by Keith Ross in 1999 and is headquartered in Sydney, Australia. | L41: Asia/Pacific International Coal Mining | M41: Coal and Uranium Mining | N41: Upstream Energy | O41: Asia/Pacific International Coal Mining | P41: 1392 | Q41: 1350 | R41: 649 | S41: 23.148148 | T41: 23.868313 | U41: 11.128258
A42: GMD-AU | B42: Genesis Minerals Ltd. | C42: Public | D42: Australia | E42: 2007 | F42: 1693 | G42: 920.141 | H42: Pacific | I42: Western Australia (WA) | J42: 1797.922 | K42: Genesis Minerals Ltd. engages in the exploration and development of gold deposits in Western Australia. Its projects include Leonora Gold and Barimaia Gold. The company was founded on April 16, 2007 and is headquartered in Perth, Australia. | L42: Precious Metal Mining | M42: Metal Ore Mining | N42: Mining and Mineral Products | O42: Asia/Pacific Gold Mining | P42: 349.46 | Q42: 454.501 | R42: 221.172 | S42: 49.394712 | T42: 37.978962 | U42: 24.036751
A43: SRG-AU | B43: SRG Global Ltd. | C43: Public | D43: Australia | E43: 2003 | F43: - | G43: 1323.307 | H43: Pacific | I43: Western Australia (WA) | J43: 881.08002 | K43: SRG Global Ltd. engages in the provision of asset services on land. It operates through the following segments: Maintenance and Industrial Services, Engineering and Construction, and Corporate. The Maintenance and Industrial Services segment focuses on supplying integrated services to customers across the entire asset life cycle. The Engineering and Construction segment is involved in supplying integrated products and services to customers involved in the construction of complex infrastructure. The company was founded in 1961 and is headquartered in Subiaco, Australia. | L43: Infrastructure Construction/Contracting Services | M43: Facilities and Construction Services | N43: Industrial Services | O43: Diverse Construction and Engineering Services | P43: 117.744 | Q43: 118.796 | R43: 47.482 | S43: 8.9772063 | T43: 8.8977085 | U43: 3.5881319
A44: SYR-AU | B44: Syrah Resources Ltd. | C44: Public | D44: Australia | E44: 2007 | F44: 615 | G44: 47.780541 | H44: Pacific | I44: Victoria (VIC) | J44: 1117.8357 | K44: Syrah Resources Ltd. is an industrial minerals and technology company. The firm operates through two segments: Balma and Corporate. The Balma segment includes mining, mineral exploration, evaluation and development activities associated with the Balama Graphite Project in Mozambique. The Corporate segment includes corporate administration and investing activities including development of the group's battery anode material strategy. Its projects includes Balma project, Sphercial Graphite Project, and Balama Vanadium Project. The company was founded on May 4, 2007 and is headquartered in Melbourne, Australia. | L44: Nonmetallic Mineral Mining | M44: Other Mining | N44: Mining and Mineral Products | O44: Other Nonmetallic Minerals Mining | P44: -108.93587 | Q44: -115.95529 | R44: -187.50178 | S44: -242.68308 | T44: -227.99213 | U44: -392.4229
A45: NHF-AU | B45: NIB Holdings Ltd. | C45: Public | D45: Australia | E45: 2007 | F45: - | G45: 3563.2 | H45: Pacific | I45: New South Wales (NSW) | J45: 2187.2001 | K45: NIB Holdings Ltd. engages in the provision of health and medical insurance. It operates through the following segments: Australian Residents Health Insurance, International (Inbound) Health Insurance, New Zealand Insurance, nib Travel, and nib Thrive. The Australian Residents Health Insurance segment offers product within the Australian private health insurance industry. The International (Inbound) Health Insurance segment includes health insurance products for international students and workers. The New Zealand Insurance segment consists of product for the New Zealand private health insurance industry. The nib Travel segment pertains to distribution of travel insurance products. The nib Thrive segment is involved in offering as a plan manager under the National Disability Insurance Scheme. The company was founded in 1952 and is headquartered in Newcastle, Australia. | L45: Life and Health Insurance | M45: Insurance | N45: Insurance | O45: Supplemental Health Insurance | P45: - | Q45: - | R45: 195.5 | S45: - | T45: - | U45: 5.4866412
A46: GEM-AU | B46: G8 Education Ltd. | C46: Public | D46: Australia | E46: 2007 | F46: 7099 | G46: 1015.268 | H46: Pacific | I46: Queensland (QLD) | J46: 2068.3039 | K46: G8 Education Ltd. engages in the provision of quality early childhood education and care. The firm is also involved in managing child care centres. The company was founded in 2006 and is headquartered in Gold Coast, Australia. | L46: Educational Services | M46: Personal Professional Services | N46: Household Services | O46: Other Educational Services | P46: 254.702 | Q46: 261.649 | R46: 67.688 | S46: 25.771422 | T46: 25.087169 | U46: 6.6670081
A47: CKF-AU | B47: Collins Foods Ltd. | C47: Public | D47: Australia | E47: 2011 | F47: - | G47: 1519.2021 | H47: Pacific | I47: Queensland (QLD) | J47: 1657.2225 | K47: Collins Foods Ltd. engages in the operation of restaurants and food service retail outlets. It operates through the following business segments: KFC Restaurants Australia, KFC Restaurants Europe, Taco Bell Restaurants, and Other. The company was founded on June 10, 2011 and is headquartered in Hamilton, Australia. | L47: Restaurants and Bars | M47: Hospitality Services | N47: Hospitality Services | O47: Limited-Service and Fast Food Restaurants | P47: 776.27739 | Q47: 236.49433 | R47: 8.8323319 | S47: 15.56701 | T47: 51.097705 | U47: 0.58137966
